42069667           0 LOAD_CONST               1 (True)
                   2 STORE_FAST               1 (OVXPEYYWSK)

42069668           4 LOAD_FAST                1 (OVXPEYYWSK)
                   6 JUMP_IF_FALSE_OR_POP   198
                   8 LOAD_GLOBAL              0 (ord)
                  10 LOAD_FAST                0 (QFBKDVBLQX)
                  12 LOAD_CONST               2 (12)
                  14 BINARY_SUBSCR
                  16 CALL_FUNCTION            1
                  18 LOAD_CONST               3 (128)
                  20 BINARY_AND
                  22 LOAD_CONST               4 (7)
                  24 BINARY_RSHIFT
                  26 LOAD_CONST               5 (0)
                  28 COMPARE_OP               2 (==)
                  30 JUMP_IF_FALSE_OR_POP   198
                  32 LOAD_GLOBAL              0 (ord)
                  34 LOAD_FAST                0 (QFBKDVBLQX)
                  36 LOAD_CONST               2 (12)
                  38 BINARY_SUBSCR
                  40 CALL_FUNCTION            1
                  42 LOAD_CONST               6 (64)
                  44 BINARY_AND
                  46 LOAD_CONST               7 (6)
                  48 BINARY_RSHIFT
                  50 LOAD_CONST               8 (1)
                  52 COMPARE_OP               2 (==)
                  54 JUMP_IF_FALSE_OR_POP   198
                  56 LOAD_GLOBAL              0 (ord)
                  58 LOAD_FAST                0 (QFBKDVBLQX)
                  60 LOAD_CONST               2 (12)
                  62 BINARY_SUBSCR
                  64 CALL_FUNCTION            1
                  66 LOAD_CONST               9 (32)
                  68 BINARY_AND
                  70 LOAD_CONST              10 (5)
                  72 BINARY_RSHIFT
                  74 LOAD_CONST               8 (1)
                  76 COMPARE_OP               2 (==)
                  78 JUMP_IF_FALSE_OR_POP   198
                  80 LOAD_GLOBAL              0 (ord)
                  82 LOAD_FAST                0 (QFBKDVBLQX)
                  84 LOAD_CONST               2 (12)
                  86 BINARY_SUBSCR
                  88 CALL_FUNCTION            1
                  90 LOAD_CONST              11 (16)
                  92 BINARY_AND
                  94 LOAD_CONST              12 (4)
                  96 BINARY_RSHIFT
                  98 LOAD_CONST               5 (0)
                 100 COMPARE_OP               2 (==)
                 102 JUMP_IF_FALSE_OR_POP   198
                 104 LOAD_GLOBAL              0 (ord)
                 106 LOAD_FAST                0 (QFBKDVBLQX)
                 108 LOAD_CONST               2 (12)
                 110 BINARY_SUBSCR
                 112 CALL_FUNCTION            1
                 114 LOAD_CONST              13 (8)
                 116 BINARY_AND
                 118 LOAD_CONST              14 (3)
                 120 BINARY_RSHIFT
                 122 LOAD_CONST               8 (1)
                 124 COMPARE_OP               2 (==)
                 126 JUMP_IF_FALSE_OR_POP   198
                 128 LOAD_GLOBAL              0 (ord)
                 130 LOAD_FAST                0 (QFBKDVBLQX)
                 132 LOAD_CONST               2 (12)
                 134 BINARY_SUBSCR
                 136 CALL_FUNCTION            1
                 138 LOAD_CONST              12 (4)
                 140 BINARY_AND
                 142 LOAD_CONST              15 (2)
                 144 BINARY_RSHIFT
                 146 LOAD_CONST               5 (0)
                 148 COMPARE_OP               2 (==)
                 150 JUMP_IF_FALSE_OR_POP   198
                 152 LOAD_GLOBAL              0 (ord)
                 154 LOAD_FAST                0 (QFBKDVBLQX)
                 156 LOAD_CONST               2 (12)
                 158 BINARY_SUBSCR
                 160 CALL_FUNCTION            1
                 162 LOAD_CONST              15 (2)
                 164 BINARY_AND
                 166 LOAD_CONST               8 (1)
                 168 BINARY_RSHIFT
                 170 LOAD_CONST               5 (0)
                 172 COMPARE_OP               2 (==)
                 174 JUMP_IF_FALSE_OR_POP   198
                 176 LOAD_GLOBAL              0 (ord)
                 178 LOAD_FAST                0 (QFBKDVBLQX)
                 180 LOAD_CONST               2 (12)
                 182 BINARY_SUBSCR
                 184 CALL_FUNCTION            1
                 186 LOAD_CONST               8 (1)
                 188 BINARY_AND
                 190 LOAD_CONST               5 (0)
                 192 BINARY_RSHIFT
                 194 LOAD_CONST               8 (1)
                 196 COMPARE_OP               2 (==)
             >>  198 STORE_FAST               1 (OVXPEYYWSK)

42069669         200 LOAD_FAST                1 (OVXPEYYWSK)
                 202 JUMP_IF_FALSE_OR_POP   218
                 204 LOAD_GLOBAL              0 (ord)
                 206 LOAD_FAST                0 (QFBKDVBLQX)
                 208 LOAD_CONST              10 (5)
                 210 BINARY_SUBSCR
                 212 CALL_FUNCTION            1
                 214 LOAD_CONST              16 (123)
                 216 COMPARE_OP               2 (==)
             >>  218 STORE_FAST               1 (OVXPEYYWSK)

42069670         220 LOAD_FAST                1 (OVXPEYYWSK)
                 222 EXTENDED_ARG             1
                 224 JUMP_IF_FALSE_OR_POP   274
                 226 LOAD_GLOBAL              0 (ord)
                 228 LOAD_FAST                0 (QFBKDVBLQX)
                 230 LOAD_CONST               9 (32)
                 232 BINARY_SUBSCR
                 234 CALL_FUNCTION            1
                 236 LOAD_CONST              17 (240)
                 238 BINARY_AND
                 240 LOAD_CONST              18 (96)
                 242 BINARY_XOR
                 244 LOAD_CONST               5 (0)
                 246 COMPARE_OP               2 (==)
                 248 EXTENDED_ARG             1
                 250 JUMP_IF_FALSE_OR_POP   274
                 252 LOAD_GLOBAL              0 (ord)
                 254 LOAD_FAST                0 (QFBKDVBLQX)
                 256 LOAD_CONST               9 (32)
                 258 BINARY_SUBSCR
                 260 CALL_FUNCTION            1
                 262 LOAD_CONST              19 (15)
                 264 BINARY_AND
                 266 LOAD_CONST              20 (9)
                 268 BINARY_XOR
                 270 LOAD_CONST               5 (0)
                 272 COMPARE_OP               2 (==)
             >>  274 STORE_FAST               1 (OVXPEYYWSK)

42069671         276 LOAD_FAST                1 (OVXPEYYWSK)
                 278 EXTENDED_ARG             1
                 280 JUMP_IF_FALSE_OR_POP   486
                 282 LOAD_GLOBAL              0 (ord)
                 284 LOAD_FAST                0 (QFBKDVBLQX)
                 286 LOAD_CONST              21 (23)
                 288 BINARY_SUBSCR
                 290 CALL_FUNCTION            1
                 292 LOAD_CONST               3 (128)
                 294 BINARY_AND
                 296 LOAD_CONST               4 (7)
                 298 BINARY_RSHIFT
                 300 LOAD_CONST               5 (0)
                 302 COMPARE_OP               2 (==)
                 304 EXTENDED_ARG             1
                 306 JUMP_IF_FALSE_OR_POP   486
                 308 LOAD_GLOBAL              0 (ord)
                 310 LOAD_FAST                0 (QFBKDVBLQX)
                 312 LOAD_CONST              21 (23)
                 314 BINARY_SUBSCR
                 316 CALL_FUNCTION            1
                 318 LOAD_CONST               6 (64)
                 320 BINARY_AND
                 322 LOAD_CONST               7 (6)
                 324 BINARY_RSHIFT
                 326 LOAD_CONST               8 (1)
                 328 COMPARE_OP               2 (==)
                 330 EXTENDED_ARG             1
                 332 JUMP_IF_FALSE_OR_POP   486
                 334 LOAD_GLOBAL              0 (ord)
                 336 LOAD_FAST                0 (QFBKDVBLQX)
                 338 LOAD_CONST              21 (23)
                 340 BINARY_SUBSCR
                 342 CALL_FUNCTION            1
                 344 LOAD_CONST               9 (32)
                 346 BINARY_AND
                 348 LOAD_CONST              10 (5)
                 350 BINARY_RSHIFT
                 352 LOAD_CONST               8 (1)
                 354 COMPARE_OP               2 (==)
                 356 EXTENDED_ARG             1
                 358 JUMP_IF_FALSE_OR_POP   486
                 360 LOAD_GLOBAL              0 (ord)
                 362 LOAD_FAST                0 (QFBKDVBLQX)
                 364 LOAD_CONST              21 (23)
                 366 BINARY_SUBSCR
                 368 CALL_FUNCTION            1
                 370 LOAD_CONST              11 (16)
                 372 BINARY_AND
                 374 LOAD_CONST              12 (4)
                 376 BINARY_RSHIFT
                 378 LOAD_CONST               5 (0)
                 380 COMPARE_OP               2 (==)
                 382 EXTENDED_ARG             1
                 384 JUMP_IF_FALSE_OR_POP   486
                 386 LOAD_GLOBAL              0 (ord)
                 388 LOAD_FAST                0 (QFBKDVBLQX)
                 390 LOAD_CONST              21 (23)
                 392 BINARY_SUBSCR
                 394 CALL_FUNCTION            1
                 396 LOAD_CONST              13 (8)
                 398 BINARY_AND
                 400 LOAD_CONST              14 (3)
                 402 BINARY_RSHIFT
                 404 LOAD_CONST               5 (0)
                 406 COMPARE_OP               2 (==)
                 408 EXTENDED_ARG             1
                 410 JUMP_IF_FALSE_OR_POP   486
                 412 LOAD_GLOBAL              0 (ord)
                 414 LOAD_FAST                0 (QFBKDVBLQX)
                 416 LOAD_CONST              21 (23)
                 418 BINARY_SUBSCR
                 420 CALL_FUNCTION            1
                 422 LOAD_CONST              12 (4)
                 424 BINARY_AND
                 426 LOAD_CONST              15 (2)
                 428 BINARY_RSHIFT
                 430 LOAD_CONST               5 (0)
                 432 COMPARE_OP               2 (==)
                 434 EXTENDED_ARG             1
                 436 JUMP_IF_FALSE_OR_POP   486
                 438 LOAD_GLOBAL              0 (ord)
                 440 LOAD_FAST                0 (QFBKDVBLQX)
                 442 LOAD_CONST              21 (23)
                 444 BINARY_SUBSCR
                 446 CALL_FUNCTION            1
                 448 LOAD_CONST              15 (2)
                 450 BINARY_AND
                 452 LOAD_CONST               8 (1)
                 454 BINARY_RSHIFT
                 456 LOAD_CONST               8 (1)
                 458 COMPARE_OP               2 (==)
                 460 EXTENDED_ARG             1
                 462 JUMP_IF_FALSE_OR_POP   486
                 464 LOAD_GLOBAL              0 (ord)
                 466 LOAD_FAST                0 (QFBKDVBLQX)
                 468 LOAD_CONST              21 (23)
                 470 BINARY_SUBSCR
                 472 CALL_FUNCTION            1
                 474 LOAD_CONST               8 (1)
                 476 BINARY_AND
                 478 LOAD_CONST               5 (0)
                 480 BINARY_RSHIFT
                 482 LOAD_CONST               8 (1)
                 484 COMPARE_OP               2 (==)
             >>  486 STORE_FAST               1 (OVXPEYYWSK)

42069672         488 LOAD_FAST                1 (OVXPEYYWSK)
                 490 EXTENDED_ARG             2
                 492 JUMP_IF_FALSE_OR_POP   542
                 494 LOAD_GLOBAL              0 (ord)
                 496 LOAD_FAST                0 (QFBKDVBLQX)
                 498 LOAD_CONST              15 (2)
                 500 BINARY_SUBSCR
                 502 CALL_FUNCTION            1
                 504 LOAD_CONST              17 (240)
                 506 BINARY_AND
                 508 LOAD_CONST               6 (64)
                 510 BINARY_XOR
                 512 LOAD_CONST               5 (0)
                 514 COMPARE_OP               2 (==)
                 516 EXTENDED_ARG             2
                 518 JUMP_IF_FALSE_OR_POP   542
                 520 LOAD_GLOBAL              0 (ord)
                 522 LOAD_FAST                0 (QFBKDVBLQX)
                 524 LOAD_CONST              15 (2)
                 526 BINARY_SUBSCR
                 528 CALL_FUNCTION            1
                 530 LOAD_CONST              19 (15)
                 532 BINARY_AND
                 534 LOAD_CONST               8 (1)
                 536 BINARY_XOR
                 538 LOAD_CONST               5 (0)
                 540 COMPARE_OP               2 (==)
             >>  542 STORE_FAST               1 (OVXPEYYWSK)

42069673         544 LOAD_FAST                1 (OVXPEYYWSK)
                 546 EXTENDED_ARG             2
                 548 JUMP_IF_FALSE_OR_POP   598
                 550 LOAD_GLOBAL              0 (ord)
                 552 LOAD_FAST                0 (QFBKDVBLQX)
                 554 LOAD_CONST              22 (29)
                 556 BINARY_SUBSCR
                 558 CALL_FUNCTION            1
                 560 LOAD_CONST              17 (240)
                 562 BINARY_AND
                 564 LOAD_CONST              23 (112)
                 566 BINARY_XOR
                 568 LOAD_CONST               5 (0)
                 570 COMPARE_OP               2 (==)
                 572 EXTENDED_ARG             2
                 574 JUMP_IF_FALSE_OR_POP   598
                 576 LOAD_GLOBAL              0 (ord)
                 578 LOAD_FAST                0 (QFBKDVBLQX)
                 580 LOAD_CONST              22 (29)
                 582 BINARY_SUBSCR
                 584 CALL_FUNCTION            1
                 586 LOAD_CONST              19 (15)
                 588 BINARY_AND
                 590 LOAD_CONST              12 (4)
                 592 BINARY_XOR
                 594 LOAD_CONST               5 (0)
                 596 COMPARE_OP               2 (==)
             >>  598 STORE_FAST               1 (OVXPEYYWSK)

42069674         600 LOAD_FAST                1 (OVXPEYYWSK)
                 602 EXTENDED_ARG             3
                 604 JUMP_IF_FALSE_OR_POP   810
                 606 LOAD_GLOBAL              0 (ord)
                 608 LOAD_FAST                0 (QFBKDVBLQX)
                 610 LOAD_CONST              12 (4)
                 612 BINARY_SUBSCR
                 614 CALL_FUNCTION            1
                 616 LOAD_CONST               3 (128)
                 618 BINARY_AND
                 620 LOAD_CONST               4 (7)
                 622 BINARY_RSHIFT
                 624 LOAD_CONST               5 (0)
                 626 COMPARE_OP               2 (==)
                 628 EXTENDED_ARG             3
                 630 JUMP_IF_FALSE_OR_POP   810
                 632 LOAD_GLOBAL              0 (ord)
                 634 LOAD_FAST                0 (QFBKDVBLQX)
                 636 LOAD_CONST              12 (4)
                 638 BINARY_SUBSCR
                 640 CALL_FUNCTION            1
                 642 LOAD_CONST               6 (64)
                 644 BINARY_AND
                 646 LOAD_CONST               7 (6)
                 648 BINARY_RSHIFT
                 650 LOAD_CONST               8 (1)
                 652 COMPARE_OP               2 (==)
                 654 EXTENDED_ARG             3
                 656 JUMP_IF_FALSE_OR_POP   810
                 658 LOAD_GLOBAL              0 (ord)
                 660 LOAD_FAST                0 (QFBKDVBLQX)
                 662 LOAD_CONST              12 (4)
                 664 BINARY_SUBSCR
                 666 CALL_FUNCTION            1
                 668 LOAD_CONST               9 (32)
                 670 BINARY_AND
                 672 LOAD_CONST              10 (5)
                 674 BINARY_RSHIFT
                 676 LOAD_CONST               5 (0)
                 678 COMPARE_OP               2 (==)
                 680 EXTENDED_ARG             3
                 682 JUMP_IF_FALSE_OR_POP   810
                 684 LOAD_GLOBAL              0 (ord)
                 686 LOAD_FAST                0 (QFBKDVBLQX)
                 688 LOAD_CONST              12 (4)
                 690 BINARY_SUBSCR
                 692 CALL_FUNCTION            1
                 694 LOAD_CONST              11 (16)
                 696 BINARY_AND
                 698 LOAD_CONST              12 (4)
                 700 BINARY_RSHIFT
                 702 LOAD_CONST               8 (1)
                 704 COMPARE_OP               2 (==)
                 706 EXTENDED_ARG             3
                 708 JUMP_IF_FALSE_OR_POP   810
                 710 LOAD_GLOBAL              0 (ord)
                 712 LOAD_FAST                0 (QFBKDVBLQX)
                 714 LOAD_CONST              12 (4)
                 716 BINARY_SUBSCR
                 718 CALL_FUNCTION            1
                 720 LOAD_CONST              13 (8)
                 722 BINARY_AND
                 724 LOAD_CONST              14 (3)
                 726 BINARY_RSHIFT
                 728 LOAD_CONST               5 (0)
                 730 COMPARE_OP               2 (==)
                 732 EXTENDED_ARG             3
                 734 JUMP_IF_FALSE_OR_POP   810
                 736 LOAD_GLOBAL              0 (ord)
                 738 LOAD_FAST                0 (QFBKDVBLQX)
                 740 LOAD_CONST              12 (4)
                 742 BINARY_SUBSCR
                 744 CALL_FUNCTION            1
                 746 LOAD_CONST              12 (4)
                 748 BINARY_AND
                 750 LOAD_CONST              15 (2)
                 752 BINARY_RSHIFT
                 754 LOAD_CONST               5 (0)
                 756 COMPARE_OP               2 (==)
                 758 EXTENDED_ARG             3
                 760 JUMP_IF_FALSE_OR_POP   810
                 762 LOAD_GLOBAL              0 (ord)
                 764 LOAD_FAST                0 (QFBKDVBLQX)
                 766 LOAD_CONST              12 (4)
                 768 BINARY_SUBSCR
                 770 CALL_FUNCTION            1
                 772 LOAD_CONST              15 (2)
                 774 BINARY_AND
                 776 LOAD_CONST               8 (1)
                 778 BINARY_RSHIFT
                 780 LOAD_CONST               8 (1)
                 782 COMPARE_OP               2 (==)
                 784 EXTENDED_ARG             3
                 786 JUMP_IF_FALSE_OR_POP   810
                 788 LOAD_GLOBAL              0 (ord)
                 790 LOAD_FAST                0 (QFBKDVBLQX)
                 792 LOAD_CONST              12 (4)
                 794 BINARY_SUBSCR
                 796 CALL_FUNCTION            1
                 798 LOAD_CONST               8 (1)
                 800 BINARY_AND
                 802 LOAD_CONST               5 (0)
                 804 BINARY_RSHIFT
                 806 LOAD_CONST               8 (1)
                 808 COMPARE_OP               2 (==)
             >>  810 STORE_FAST               1 (OVXPEYYWSK)

42069675         812 LOAD_FAST                1 (OVXPEYYWSK)
                 814 EXTENDED_ARG             3
                 816 JUMP_IF_FALSE_OR_POP   832
                 818 LOAD_GLOBAL              0 (ord)
                 820 LOAD_FAST                0 (QFBKDVBLQX)
                 822 LOAD_CONST              24 (26)
                 824 BINARY_SUBSCR
                 826 CALL_FUNCTION            1
                 828 LOAD_CONST              25 (51)
                 830 COMPARE_OP               2 (==)
             >>  832 STORE_FAST               1 (OVXPEYYWSK)

42069676         834 LOAD_FAST                1 (OVXPEYYWSK)
                 836 EXTENDED_ARG             4
                 838 JUMP_IF_FALSE_OR_POP  1044
                 840 LOAD_GLOBAL              0 (ord)
                 842 LOAD_FAST                0 (QFBKDVBLQX)
                 844 LOAD_CONST              26 (28)
                 846 BINARY_SUBSCR
                 848 CALL_FUNCTION            1
                 850 LOAD_CONST               3 (128)
                 852 BINARY_AND
                 854 LOAD_CONST               4 (7)
                 856 BINARY_RSHIFT
                 858 LOAD_CONST               5 (0)
                 860 COMPARE_OP               2 (==)
                 862 EXTENDED_ARG             4
                 864 JUMP_IF_FALSE_OR_POP  1044
                 866 LOAD_GLOBAL              0 (ord)
                 868 LOAD_FAST                0 (QFBKDVBLQX)
                 870 LOAD_CONST              26 (28)
                 872 BINARY_SUBSCR
                 874 CALL_FUNCTION            1
                 876 LOAD_CONST               6 (64)
                 878 BINARY_AND
                 880 LOAD_CONST               7 (6)
                 882 BINARY_RSHIFT
                 884 LOAD_CONST               8 (1)
                 886 COMPARE_OP               2 (==)
                 888 EXTENDED_ARG             4
                 890 JUMP_IF_FALSE_OR_POP  1044
                 892 LOAD_GLOBAL              0 (ord)
                 894 LOAD_FAST                0 (QFBKDVBLQX)
                 896 LOAD_CONST              26 (28)
                 898 BINARY_SUBSCR
                 900 CALL_FUNCTION            1
                 902 LOAD_CONST               9 (32)
                 904 BINARY_AND
                 906 LOAD_CONST              10 (5)
                 908 BINARY_RSHIFT
                 910 LOAD_CONST               8 (1)
                 912 COMPARE_OP               2 (==)
                 914 EXTENDED_ARG             4
                 916 JUMP_IF_FALSE_OR_POP  1044
                 918 LOAD_GLOBAL              0 (ord)
                 920 LOAD_FAST                0 (QFBKDVBLQX)
                 922 LOAD_CONST              26 (28)
                 924 BINARY_SUBSCR
                 926 CALL_FUNCTION            1
                 928 LOAD_CONST              11 (16)
                 930 BINARY_AND
                 932 LOAD_CONST              12 (4)
                 934 BINARY_RSHIFT
                 936 LOAD_CONST               5 (0)
                 938 COMPARE_OP               2 (==)
                 940 EXTENDED_ARG             4
                 942 JUMP_IF_FALSE_OR_POP  1044
                 944 LOAD_GLOBAL              0 (ord)
                 946 LOAD_FAST                0 (QFBKDVBLQX)
                 948 LOAD_CONST              26 (28)
                 950 BINARY_SUBSCR
                 952 CALL_FUNCTION            1
                 954 LOAD_CONST              13 (8)
                 956 BINARY_AND
                 958 LOAD_CONST              14 (3)
                 960 BINARY_RSHIFT
                 962 LOAD_CONST               5 (0)
                 964 COMPARE_OP               2 (==)
                 966 EXTENDED_ARG             4
                 968 JUMP_IF_FALSE_OR_POP  1044
                 970 LOAD_GLOBAL              0 (ord)
                 972 LOAD_FAST                0 (QFBKDVBLQX)
                 974 LOAD_CONST              26 (28)
                 976 BINARY_SUBSCR
                 978 CALL_FUNCTION            1
                 980 LOAD_CONST              12 (4)
                 982 BINARY_AND
                 984 LOAD_CONST              15 (2)
                 986 BINARY_RSHIFT
                 988 LOAD_CONST               5 (0)
                 990 COMPARE_OP               2 (==)
                 992 EXTENDED_ARG             4
                 994 JUMP_IF_FALSE_OR_POP  1044
                 996 LOAD_GLOBAL              0 (ord)
                 998 LOAD_FAST                0 (QFBKDVBLQX)
                1000 LOAD_CONST              26 (28)
                1002 BINARY_SUBSCR
                1004 CALL_FUNCTION            1
                1006 LOAD_CONST              15 (2)
                1008 BINARY_AND
                1010 LOAD_CONST               8 (1)
                1012 BINARY_RSHIFT
                1014 LOAD_CONST               8 (1)
                1016 COMPARE_OP               2 (==)
                1018 EXTENDED_ARG             4
                1020 JUMP_IF_FALSE_OR_POP  1044
                1022 LOAD_GLOBAL              0 (ord)
                1024 LOAD_FAST                0 (QFBKDVBLQX)
                1026 LOAD_CONST              26 (28)
                1028 BINARY_SUBSCR
                1030 CALL_FUNCTION            1
                1032 LOAD_CONST               8 (1)
                1034 BINARY_AND
                1036 LOAD_CONST               5 (0)
                1038 BINARY_RSHIFT
                1040 LOAD_CONST               8 (1)
                1042 COMPARE_OP               2 (==)
             >> 1044 STORE_FAST               1 (OVXPEYYWSK)

42069677        1046 LOAD_FAST                1 (OVXPEYYWSK)
                1048 EXTENDED_ARG             4
                1050 JUMP_IF_FALSE_OR_POP  1100
                1052 LOAD_GLOBAL              0 (ord)
                1054 LOAD_FAST                0 (QFBKDVBLQX)
                1056 LOAD_CONST              27 (20)
                1058 BINARY_SUBSCR
                1060 CALL_FUNCTION            1
                1062 LOAD_CONST              17 (240)
                1064 BINARY_AND
                1066 LOAD_CONST              23 (112)
                1068 BINARY_XOR
                1070 LOAD_CONST               5 (0)
                1072 COMPARE_OP               2 (==)
                1074 EXTENDED_ARG             4
                1076 JUMP_IF_FALSE_OR_POP  1100
                1078 LOAD_GLOBAL              0 (ord)
                1080 LOAD_FAST                0 (QFBKDVBLQX)
                1082 LOAD_CONST              27 (20)
                1084 BINARY_SUBSCR
                1086 CALL_FUNCTION            1
                1088 LOAD_CONST              19 (15)
                1090 BINARY_AND
                1092 LOAD_CONST              20 (9)
                1094 BINARY_XOR
                1096 LOAD_CONST               5 (0)
                1098 COMPARE_OP               2 (==)
             >> 1100 STORE_FAST               1 (OVXPEYYWSK)

42069678        1102 LOAD_FAST                1 (OVXPEYYWSK)
                1104 EXTENDED_ARG             4
                1106 JUMP_IF_FALSE_OR_POP  1122
                1108 LOAD_GLOBAL              0 (ord)
                1110 LOAD_FAST                0 (QFBKDVBLQX)
                1112 LOAD_CONST              28 (14)
                1114 BINARY_SUBSCR
                1116 CALL_FUNCTION            1
                1118 LOAD_CONST              29 (49)
                1120 COMPARE_OP               2 (==)
             >> 1122 STORE_FAST               1 (OVXPEYYWSK)

42069679        1124 LOAD_FAST                0 (QFBKDVBLQX)
                1126 LOAD_CONST               0 (None)
                1128 LOAD_CONST              10 (5)
                1130 BUILD_SLICE              2
                1132 BINARY_SUBSCR
                1134 LOAD_CONST              30 ('UMASS')
                1136 COMPARE_OP               3 (!=)
                1138 EXTENDED_ARG             4
                1140 POP_JUMP_IF_FALSE     1148

42069680        1142 LOAD_CONST              31 (False)
                1144 BUILD_LIST               1
                1146 RETURN_VALUE

42069681     >> 1148 LOAD_FAST                1 (OVXPEYYWSK)
                1150 EXTENDED_ARG             4
                1152 JUMP_IF_FALSE_OR_POP  1202
                1154 LOAD_GLOBAL              0 (ord)
                1156 LOAD_FAST                0 (QFBKDVBLQX)
                1158 LOAD_CONST              32 (18)
                1160 BINARY_SUBSCR
                1162 CALL_FUNCTION            1
                1164 LOAD_CONST              17 (240)
                1166 BINARY_AND
                1168 LOAD_CONST              33 (80)
                1170 BINARY_XOR
                1172 LOAD_CONST               5 (0)
                1174 COMPARE_OP               2 (==)
                1176 EXTENDED_ARG             4
                1178 JUMP_IF_FALSE_OR_POP  1202
                1180 LOAD_GLOBAL              0 (ord)
                1182 LOAD_FAST                0 (QFBKDVBLQX)
                1184 LOAD_CONST              32 (18)
                1186 BINARY_SUBSCR
                1188 CALL_FUNCTION            1
                1190 LOAD_CONST              19 (15)
                1192 BINARY_AND
                1194 LOAD_CONST              19 (15)
                1196 BINARY_XOR
                1198 LOAD_CONST               5 (0)
                1200 COMPARE_OP               2 (==)
             >> 1202 STORE_FAST               1 (OVXPEYYWSK)

42069682        1204 LOAD_FAST                1 (OVXPEYYWSK)
                1206 EXTENDED_ARG             5
                1208 JUMP_IF_FALSE_OR_POP  1414
                1210 LOAD_GLOBAL              0 (ord)
                1212 LOAD_FAST                0 (QFBKDVBLQX)
                1214 LOAD_CONST              19 (15)
                1216 BINARY_SUBSCR
                1218 CALL_FUNCTION            1
                1220 LOAD_CONST               3 (128)
                1222 BINARY_AND
                1224 LOAD_CONST               4 (7)
                1226 BINARY_RSHIFT
                1228 LOAD_CONST               5 (0)
                1230 COMPARE_OP               2 (==)
                1232 EXTENDED_ARG             5
                1234 JUMP_IF_FALSE_OR_POP  1414
                1236 LOAD_GLOBAL              0 (ord)
                1238 LOAD_FAST                0 (QFBKDVBLQX)
                1240 LOAD_CONST              19 (15)
                1242 BINARY_SUBSCR
                1244 CALL_FUNCTION            1
                1246 LOAD_CONST               6 (64)
                1248 BINARY_AND
                1250 LOAD_CONST               7 (6)
                1252 BINARY_RSHIFT
                1254 LOAD_CONST               8 (1)
                1256 COMPARE_OP               2 (==)
                1258 EXTENDED_ARG             5
                1260 JUMP_IF_FALSE_OR_POP  1414
                1262 LOAD_GLOBAL              0 (ord)
                1264 LOAD_FAST                0 (QFBKDVBLQX)
                1266 LOAD_CONST              19 (15)
                1268 BINARY_SUBSCR
                1270 CALL_FUNCTION            1
                1272 LOAD_CONST               9 (32)
                1274 BINARY_AND
                1276 LOAD_CONST              10 (5)
                1278 BINARY_RSHIFT
                1280 LOAD_CONST               8 (1)
                1282 COMPARE_OP               2 (==)
                1284 EXTENDED_ARG             5
                1286 JUMP_IF_FALSE_OR_POP  1414
                1288 LOAD_GLOBAL              0 (ord)
                1290 LOAD_FAST                0 (QFBKDVBLQX)
                1292 LOAD_CONST              19 (15)
                1294 BINARY_SUBSCR
                1296 CALL_FUNCTION            1
                1298 LOAD_CONST              11 (16)
                1300 BINARY_AND
                1302 LOAD_CONST              12 (4)
                1304 BINARY_RSHIFT
                1306 LOAD_CONST               5 (0)
                1308 COMPARE_OP               2 (==)
                1310 EXTENDED_ARG             5
                1312 JUMP_IF_FALSE_OR_POP  1414
                1314 LOAD_GLOBAL              0 (ord)
                1316 LOAD_FAST                0 (QFBKDVBLQX)
                1318 LOAD_CONST              19 (15)
                1320 BINARY_SUBSCR
                1322 CALL_FUNCTION            1
                1324 LOAD_CONST              13 (8)
                1326 BINARY_AND
                1328 LOAD_CONST              14 (3)
                1330 BINARY_RSHIFT
                1332 LOAD_CONST               5 (0)
                1334 COMPARE_OP               2 (==)
                1336 EXTENDED_ARG             5
                1338 JUMP_IF_FALSE_OR_POP  1414
                1340 LOAD_GLOBAL              0 (ord)
                1342 LOAD_FAST                0 (QFBKDVBLQX)
                1344 LOAD_CONST              19 (15)
                1346 BINARY_SUBSCR
                1348 CALL_FUNCTION            1
                1350 LOAD_CONST              12 (4)
                1352 BINARY_AND
                1354 LOAD_CONST              15 (2)
                1356 BINARY_RSHIFT
                1358 LOAD_CONST               5 (0)
                1360 COMPARE_OP               2 (==)
                1362 EXTENDED_ARG             5
                1364 JUMP_IF_FALSE_OR_POP  1414
                1366 LOAD_GLOBAL              0 (ord)
                1368 LOAD_FAST                0 (QFBKDVBLQX)
                1370 LOAD_CONST              19 (15)
                1372 BINARY_SUBSCR
                1374 CALL_FUNCTION            1
                1376 LOAD_CONST              15 (2)
                1378 BINARY_AND
                1380 LOAD_CONST               8 (1)
                1382 BINARY_RSHIFT
                1384 LOAD_CONST               5 (0)
                1386 COMPARE_OP               2 (==)
                1388 EXTENDED_ARG             5
                1390 JUMP_IF_FALSE_OR_POP  1414
                1392 LOAD_GLOBAL              0 (ord)
                1394 LOAD_FAST                0 (QFBKDVBLQX)
                1396 LOAD_CONST              19 (15)
                1398 BINARY_SUBSCR
                1400 CALL_FUNCTION            1
                1402 LOAD_CONST               8 (1)
                1404 BINARY_AND
                1406 LOAD_CONST               5 (0)
                1408 BINARY_RSHIFT
                1410 LOAD_CONST               8 (1)
                1412 COMPARE_OP               2 (==)
             >> 1414 STORE_FAST               1 (OVXPEYYWSK)

42069683        1416 LOAD_FAST                1 (OVXPEYYWSK)
                1418 EXTENDED_ARG             5
                1420 JUMP_IF_FALSE_OR_POP  1436
                1422 LOAD_GLOBAL              0 (ord)
                1424 LOAD_FAST                0 (QFBKDVBLQX)
                1426 LOAD_CONST              34 (25)
                1428 BINARY_SUBSCR
                1430 CALL_FUNCTION            1
                1432 LOAD_CONST              35 (100)
                1434 COMPARE_OP               2 (==)
             >> 1436 STORE_FAST               1 (OVXPEYYWSK)

42069684        1438 LOAD_FAST                1 (OVXPEYYWSK)
                1440 EXTENDED_ARG             5
                1442 JUMP_IF_FALSE_OR_POP  1458
                1444 LOAD_GLOBAL              0 (ord)
                1446 LOAD_FAST                0 (QFBKDVBLQX)
                1448 LOAD_CONST              36 (36)
                1450 BINARY_SUBSCR
                1452 CALL_FUNCTION            1
                1454 LOAD_CONST              37 (104)
                1456 COMPARE_OP               2 (==)
             >> 1458 STORE_FAST               1 (OVXPEYYWSK)

42069685        1460 LOAD_FAST                1 (OVXPEYYWSK)
                1462 EXTENDED_ARG             5
                1464 JUMP_IF_FALSE_OR_POP  1514
                1466 LOAD_GLOBAL              0 (ord)
                1468 LOAD_FAST                0 (QFBKDVBLQX)
                1470 LOAD_CONST              20 (9)
                1472 BINARY_SUBSCR
                1474 CALL_FUNCTION            1
                1476 LOAD_CONST              17 (240)
                1478 BINARY_AND
                1480 LOAD_CONST              33 (80)
                1482 BINARY_XOR
                1484 LOAD_CONST               5 (0)
                1486 COMPARE_OP               2 (==)
                1488 EXTENDED_ARG             5
                1490 JUMP_IF_FALSE_OR_POP  1514
                1492 LOAD_GLOBAL              0 (ord)
                1494 LOAD_FAST                0 (QFBKDVBLQX)
                1496 LOAD_CONST              20 (9)
                1498 BINARY_SUBSCR
                1500 CALL_FUNCTION            1
                1502 LOAD_CONST              19 (15)
                1504 BINARY_AND
                1506 LOAD_CONST              19 (15)
                1508 BINARY_XOR
                1510 LOAD_CONST               5 (0)
                1512 COMPARE_OP               2 (==)
             >> 1514 STORE_FAST               1 (OVXPEYYWSK)

42069686        1516 LOAD_GLOBAL              1 (copy)
                1518 LOAD_METHOD              1 (copy)
                1520 LOAD_FAST                0 (QFBKDVBLQX)
                1522 CALL_METHOD              1
                1524 POP_TOP

42069687        1526 LOAD_FAST                1 (OVXPEYYWSK)
                1528 EXTENDED_ARG             6
                1530 JUMP_IF_FALSE_OR_POP  1580
                1532 LOAD_GLOBAL              0 (ord)
                1534 LOAD_FAST                0 (QFBKDVBLQX)
                1536 LOAD_CONST              14 (3)
                1538 BINARY_SUBSCR
                1540 CALL_FUNCTION            1
                1542 LOAD_CONST              17 (240)
                1544 BINARY_AND
                1546 LOAD_CONST              33 (80)
                1548 BINARY_XOR
                1550 LOAD_CONST               5 (0)
                1552 COMPARE_OP               2 (==)
                1554 EXTENDED_ARG             6
                1556 JUMP_IF_FALSE_OR_POP  1580
                1558 LOAD_GLOBAL              0 (ord)
                1560 LOAD_FAST                0 (QFBKDVBLQX)
                1562 LOAD_CONST              14 (3)
                1564 BINARY_SUBSCR
                1566 CALL_FUNCTION            1
                1568 LOAD_CONST              19 (15)
                1570 BINARY_AND
                1572 LOAD_CONST              14 (3)
                1574 BINARY_XOR
                1576 LOAD_CONST               5 (0)
                1578 COMPARE_OP               2 (==)
             >> 1580 STORE_FAST               1 (OVXPEYYWSK)

42069688        1582 LOAD_FAST                1 (OVXPEYYWSK)
                1584 EXTENDED_ARG             7
                1586 JUMP_IF_FALSE_OR_POP  1792
                1588 LOAD_GLOBAL              0 (ord)
                1590 LOAD_FAST                0 (QFBKDVBLQX)
                1592 LOAD_CONST              38 (17)
                1594 BINARY_SUBSCR
                1596 CALL_FUNCTION            1
                1598 LOAD_CONST               3 (128)
                1600 BINARY_AND
                1602 LOAD_CONST               4 (7)
                1604 BINARY_RSHIFT
                1606 LOAD_CONST               5 (0)
                1608 COMPARE_OP               2 (==)
                1610 EXTENDED_ARG             7
                1612 JUMP_IF_FALSE_OR_POP  1792
                1614 LOAD_GLOBAL              0 (ord)
                1616 LOAD_FAST                0 (QFBKDVBLQX)
                1618 LOAD_CONST              38 (17)
                1620 BINARY_SUBSCR
                1622 CALL_FUNCTION            1
                1624 LOAD_CONST               6 (64)
                1626 BINARY_AND
                1628 LOAD_CONST               7 (6)
                1630 BINARY_RSHIFT
                1632 LOAD_CONST               5 (0)
                1634 COMPARE_OP               2 (==)
                1636 EXTENDED_ARG             7
                1638 JUMP_IF_FALSE_OR_POP  1792
                1640 LOAD_GLOBAL              0 (ord)
                1642 LOAD_FAST                0 (QFBKDVBLQX)
                1644 LOAD_CONST              38 (17)
                1646 BINARY_SUBSCR
                1648 CALL_FUNCTION            1
                1650 LOAD_CONST               9 (32)
                1652 BINARY_AND
                1654 LOAD_CONST              10 (5)
                1656 BINARY_RSHIFT
                1658 LOAD_CONST               8 (1)
                1660 COMPARE_OP               2 (==)
                1662 EXTENDED_ARG             7
                1664 JUMP_IF_FALSE_OR_POP  1792
                1666 LOAD_GLOBAL              0 (ord)
                1668 LOAD_FAST                0 (QFBKDVBLQX)
                1670 LOAD_CONST              38 (17)
                1672 BINARY_SUBSCR
                1674 CALL_FUNCTION            1
                1676 LOAD_CONST              11 (16)
                1678 BINARY_AND
                1680 LOAD_CONST              12 (4)
                1682 BINARY_RSHIFT
                1684 LOAD_CONST               8 (1)
                1686 COMPARE_OP               2 (==)
                1688 EXTENDED_ARG             7
                1690 JUMP_IF_FALSE_OR_POP  1792
                1692 LOAD_GLOBAL              0 (ord)
                1694 LOAD_FAST                0 (QFBKDVBLQX)
                1696 LOAD_CONST              38 (17)
                1698 BINARY_SUBSCR
                1700 CALL_FUNCTION            1
                1702 LOAD_CONST              13 (8)
                1704 BINARY_AND
                1706 LOAD_CONST              14 (3)
                1708 BINARY_RSHIFT
                1710 LOAD_CONST               5 (0)
                1712 COMPARE_OP               2 (==)
                1714 EXTENDED_ARG             7
                1716 JUMP_IF_FALSE_OR_POP  1792
                1718 LOAD_GLOBAL              0 (ord)
                1720 LOAD_FAST                0 (QFBKDVBLQX)
                1722 LOAD_CONST              38 (17)
                1724 BINARY_SUBSCR
                1726 CALL_FUNCTION            1
                1728 LOAD_CONST              12 (4)
                1730 BINARY_AND
                1732 LOAD_CONST              15 (2)
                1734 BINARY_RSHIFT
                1736 LOAD_CONST               5 (0)
                1738 COMPARE_OP               2 (==)
                1740 EXTENDED_ARG             7
                1742 JUMP_IF_FALSE_OR_POP  1792
                1744 LOAD_GLOBAL              0 (ord)
                1746 LOAD_FAST                0 (QFBKDVBLQX)
                1748 LOAD_CONST              38 (17)
                1750 BINARY_SUBSCR
                1752 CALL_FUNCTION            1
                1754 LOAD_CONST              15 (2)
                1756 BINARY_AND
                1758 LOAD_CONST               8 (1)
                1760 BINARY_RSHIFT
                1762 LOAD_CONST               8 (1)
                1764 COMPARE_OP               2 (==)
                1766 EXTENDED_ARG             7
                1768 JUMP_IF_FALSE_OR_POP  1792
                1770 LOAD_GLOBAL              0 (ord)
                1772 LOAD_FAST                0 (QFBKDVBLQX)
                1774 LOAD_CONST              38 (17)
                1776 BINARY_SUBSCR
                1778 CALL_FUNCTION            1
                1780 LOAD_CONST               8 (1)
                1782 BINARY_AND
                1784 LOAD_CONST               5 (0)
                1786 BINARY_RSHIFT
                1788 LOAD_CONST               8 (1)
                1790 COMPARE_OP               2 (==)
             >> 1792 STORE_FAST               1 (OVXPEYYWSK)

42069689        1794 LOAD_FAST                1 (OVXPEYYWSK)
                1796 EXTENDED_ARG             7
                1798 JUMP_IF_FALSE_OR_POP  2004
                1800 LOAD_GLOBAL              0 (ord)
                1802 LOAD_FAST                0 (QFBKDVBLQX)
                1804 LOAD_CONST               5 (0)
                1806 BINARY_SUBSCR
                1808 CALL_FUNCTION            1
                1810 LOAD_CONST               3 (128)
                1812 BINARY_AND
                1814 LOAD_CONST               4 (7)
                1816 BINARY_RSHIFT
                1818 LOAD_CONST               5 (0)
                1820 COMPARE_OP               2 (==)
                1822 EXTENDED_ARG             7
                1824 JUMP_IF_FALSE_OR_POP  2004
                1826 LOAD_GLOBAL              0 (ord)
                1828 LOAD_FAST                0 (QFBKDVBLQX)
                1830 LOAD_CONST               5 (0)
                1832 BINARY_SUBSCR
                1834 CALL_FUNCTION            1
                1836 LOAD_CONST               6 (64)
                1838 BINARY_AND
                1840 LOAD_CONST               7 (6)
                1842 BINARY_RSHIFT
                1844 LOAD_CONST               8 (1)
                1846 COMPARE_OP               2 (==)
                1848 EXTENDED_ARG             7
                1850 JUMP_IF_FALSE_OR_POP  2004
                1852 LOAD_GLOBAL              0 (ord)
                1854 LOAD_FAST                0 (QFBKDVBLQX)
                1856 LOAD_CONST               5 (0)
                1858 BINARY_SUBSCR
                1860 CALL_FUNCTION            1
                1862 LOAD_CONST               9 (32)
                1864 BINARY_AND
                1866 LOAD_CONST              10 (5)
                1868 BINARY_RSHIFT
                1870 LOAD_CONST               5 (0)
                1872 COMPARE_OP               2 (==)
                1874 EXTENDED_ARG             7
                1876 JUMP_IF_FALSE_OR_POP  2004
                1878 LOAD_GLOBAL              0 (ord)
                1880 LOAD_FAST                0 (QFBKDVBLQX)
                1882 LOAD_CONST               5 (0)
                1884 BINARY_SUBSCR
                1886 CALL_FUNCTION            1
                1888 LOAD_CONST              11 (16)
                1890 BINARY_AND
                1892 LOAD_CONST              12 (4)
                1894 BINARY_RSHIFT
                1896 LOAD_CONST               8 (1)
                1898 COMPARE_OP               2 (==)
                1900 EXTENDED_ARG             7
                1902 JUMP_IF_FALSE_OR_POP  2004
                1904 LOAD_GLOBAL              0 (ord)
                1906 LOAD_FAST                0 (QFBKDVBLQX)
                1908 LOAD_CONST               5 (0)
                1910 BINARY_SUBSCR
                1912 CALL_FUNCTION            1
                1914 LOAD_CONST              13 (8)
                1916 BINARY_AND
                1918 LOAD_CONST              14 (3)
                1920 BINARY_RSHIFT
                1922 LOAD_CONST               5 (0)
                1924 COMPARE_OP               2 (==)
                1926 EXTENDED_ARG             7
                1928 JUMP_IF_FALSE_OR_POP  2004
                1930 LOAD_GLOBAL              0 (ord)
                1932 LOAD_FAST                0 (QFBKDVBLQX)
                1934 LOAD_CONST               5 (0)
                1936 BINARY_SUBSCR
                1938 CALL_FUNCTION            1
                1940 LOAD_CONST              12 (4)
                1942 BINARY_AND
                1944 LOAD_CONST              15 (2)
                1946 BINARY_RSHIFT
                1948 LOAD_CONST               8 (1)
                1950 COMPARE_OP               2 (==)
                1952 EXTENDED_ARG             7
                1954 JUMP_IF_FALSE_OR_POP  2004
                1956 LOAD_GLOBAL              0 (ord)
                1958 LOAD_FAST                0 (QFBKDVBLQX)
                1960 LOAD_CONST               5 (0)
                1962 BINARY_SUBSCR
                1964 CALL_FUNCTION            1
                1966 LOAD_CONST              15 (2)
                1968 BINARY_AND
                1970 LOAD_CONST               8 (1)
                1972 BINARY_RSHIFT
                1974 LOAD_CONST               5 (0)
                1976 COMPARE_OP               2 (==)
                1978 EXTENDED_ARG             7
                1980 JUMP_IF_FALSE_OR_POP  2004
                1982 LOAD_GLOBAL              0 (ord)
                1984 LOAD_FAST                0 (QFBKDVBLQX)
                1986 LOAD_CONST               5 (0)
                1988 BINARY_SUBSCR
                1990 CALL_FUNCTION            1
                1992 LOAD_CONST               8 (1)
                1994 BINARY_AND
                1996 LOAD_CONST               5 (0)
                1998 BINARY_RSHIFT
                2000 LOAD_CONST               8 (1)
                2002 COMPARE_OP               2 (==)
             >> 2004 STORE_FAST               1 (OVXPEYYWSK)

42069690        2006 LOAD_FAST                1 (OVXPEYYWSK)
                2008 EXTENDED_ARG             7
                2010 JUMP_IF_FALSE_OR_POP  2026
                2012 LOAD_GLOBAL              0 (ord)
                2014 LOAD_FAST                0 (QFBKDVBLQX)
                2016 LOAD_CONST              39 (37)
                2018 BINARY_SUBSCR
                2020 CALL_FUNCTION            1
                2022 LOAD_CONST              40 (97)
                2024 COMPARE_OP               2 (==)
             >> 2026 STORE_FAST               1 (OVXPEYYWSK)

42069691        2028 LOAD_FAST                1 (OVXPEYYWSK)
                2030 EXTENDED_ARG             8
                2032 JUMP_IF_FALSE_OR_POP  2048
                2034 LOAD_GLOBAL              0 (ord)
                2036 LOAD_FAST                0 (QFBKDVBLQX)
                2038 LOAD_CONST              41 (31)
                2040 BINARY_SUBSCR
                2042 CALL_FUNCTION            1
                2044 LOAD_CONST              42 (116)
                2046 COMPARE_OP               2 (==)
             >> 2048 STORE_FAST               1 (OVXPEYYWSK)

42069692        2050 LOAD_FAST                1 (OVXPEYYWSK)
                2052 EXTENDED_ARG             8
                2054 JUMP_IF_FALSE_OR_POP  2104
                2056 LOAD_GLOBAL              0 (ord)
                2058 LOAD_FAST                0 (QFBKDVBLQX)
                2060 LOAD_CONST               4 (7)
                2062 BINARY_SUBSCR
                2064 CALL_FUNCTION            1
                2066 LOAD_CONST              17 (240)
                2068 BINARY_AND
                2070 LOAD_CONST              18 (96)
                2072 BINARY_XOR
                2074 LOAD_CONST               5 (0)
                2076 COMPARE_OP               2 (==)
                2078 EXTENDED_ARG             8
                2080 JUMP_IF_FALSE_OR_POP  2104
                2082 LOAD_GLOBAL              0 (ord)
                2084 LOAD_FAST                0 (QFBKDVBLQX)
                2086 LOAD_CONST               4 (7)
                2088 BINARY_SUBSCR
                2090 CALL_FUNCTION            1
                2092 LOAD_CONST              19 (15)
                2094 BINARY_AND
                2096 LOAD_CONST              13 (8)
                2098 BINARY_XOR
                2100 LOAD_CONST               5 (0)
                2102 COMPARE_OP               2 (==)
             >> 2104 STORE_FAST               1 (OVXPEYYWSK)

42069693        2106 LOAD_FAST                1 (OVXPEYYWSK)
                2108 EXTENDED_ARG             8
                2110 JUMP_IF_FALSE_OR_POP  2126
                2112 LOAD_GLOBAL              0 (ord)
                2114 LOAD_FAST                0 (QFBKDVBLQX)
                2116 LOAD_CONST              43 (19)
                2118 BINARY_SUBSCR
                2120 CALL_FUNCTION            1
                2122 LOAD_CONST              44 (98)
                2124 COMPARE_OP               2 (==)
             >> 2126 STORE_FAST               1 (OVXPEYYWSK)

42069694        2128 LOAD_FAST                1 (OVXPEYYWSK)
                2130 EXTENDED_ARG             8
                2132 JUMP_IF_FALSE_OR_POP  2182
                2134 LOAD_GLOBAL              0 (ord)
                2136 LOAD_FAST                0 (QFBKDVBLQX)
                2138 LOAD_CONST              45 (30)
                2140 BINARY_SUBSCR
                2142 CALL_FUNCTION            1
                2144 LOAD_CONST              17 (240)
                2146 BINARY_AND
                2148 LOAD_CONST              18 (96)
                2150 BINARY_XOR
                2152 LOAD_CONST               5 (0)
                2154 COMPARE_OP               2 (==)
                2156 EXTENDED_ARG             8
                2158 JUMP_IF_FALSE_OR_POP  2182
                2160 LOAD_GLOBAL              0 (ord)
                2162 LOAD_FAST                0 (QFBKDVBLQX)
                2164 LOAD_CONST              45 (30)
                2166 BINARY_SUBSCR
                2168 CALL_FUNCTION            1
                2170 LOAD_CONST              19 (15)
                2172 BINARY_AND
                2174 LOAD_CONST               7 (6)
                2176 BINARY_XOR
                2178 LOAD_CONST               5 (0)
                2180 COMPARE_OP               2 (==)
             >> 2182 STORE_FAST               1 (OVXPEYYWSK)

42069695        2184 LOAD_FAST                1 (OVXPEYYWSK)
                2186 EXTENDED_ARG             8
                2188 JUMP_IF_FALSE_OR_POP  2204
                2190 LOAD_GLOBAL              0 (ord)
                2192 LOAD_FAST                0 (QFBKDVBLQX)
                2194 LOAD_CONST              46 (33)
                2196 BINARY_SUBSCR
                2198 CALL_FUNCTION            1
                2200 LOAD_CONST              47 (109)
                2202 COMPARE_OP               2 (==)
             >> 2204 STORE_FAST               1 (OVXPEYYWSK)

42069696        2206 LOAD_FAST                1 (OVXPEYYWSK)
                2208 EXTENDED_ARG             8
                2210 JUMP_IF_FALSE_OR_POP  2260
                2212 LOAD_GLOBAL              0 (ord)
                2214 LOAD_FAST                0 (QFBKDVBLQX)
                2216 LOAD_CONST              48 (39)
                2218 BINARY_SUBSCR
                2220 CALL_FUNCTION            1
                2222 LOAD_CONST              17 (240)
                2224 BINARY_AND
                2226 LOAD_CONST              18 (96)
                2228 BINARY_XOR
                2230 LOAD_CONST               5 (0)
                2232 COMPARE_OP               2 (==)
                2234 EXTENDED_ARG             8
                2236 JUMP_IF_FALSE_OR_POP  2260
                2238 LOAD_GLOBAL              0 (ord)
                2240 LOAD_FAST                0 (QFBKDVBLQX)
                2242 LOAD_CONST              48 (39)
                2244 BINARY_SUBSCR
                2246 CALL_FUNCTION            1
                2248 LOAD_CONST              19 (15)
                2250 BINARY_AND
                2252 LOAD_CONST              49 (11)
                2254 BINARY_XOR
                2256 LOAD_CONST               5 (0)
                2258 COMPARE_OP               2 (==)
             >> 2260 STORE_FAST               1 (OVXPEYYWSK)

42069697        2262 LOAD_GLOBAL              0 (ord)
                2264 LOAD_FAST                0 (QFBKDVBLQX)
                2266 LOAD_CONST               5 (0)
                2268 BINARY_SUBSCR
                2270 CALL_FUNCTION            1
                2272 LOAD_CONST              17 (240)
                2274 BINARY_AND
                2276 LOAD_CONST              32 (18)
                2278 COMPARE_OP               2 (==)
                2280 EXTENDED_ARG             8
                2282 POP_JUMP_IF_FALSE     2290

42069698        2284 LOAD_CONST              10 (5)
                2286 STORE_FAST               2 (QULABNDMBB)
                2288 JUMP_FORWARD             4 (to 2294)

42069700     >> 2290 LOAD_CONST              36 (36)
                2292 STORE_FAST               2 (QULABNDMBB)

42069701     >> 2294 LOAD_FAST                1 (OVXPEYYWSK)
                2296 EXTENDED_ARG             9
                2298 JUMP_IF_FALSE_OR_POP  2314
                2300 LOAD_GLOBAL              0 (ord)
                2302 LOAD_FAST                0 (QFBKDVBLQX)
                2304 LOAD_CONST              13 (8)
                2306 BINARY_SUBSCR
                2308 CALL_FUNCTION            1
                2310 LOAD_CONST              25 (51)
                2312 COMPARE_OP               2 (==)
             >> 2314 STORE_FAST               1 (OVXPEYYWSK)

42069702        2316 LOAD_FAST                1 (OVXPEYYWSK)
                2318 EXTENDED_ARG             9
                2320 JUMP_IF_FALSE_OR_POP  2336
                2322 LOAD_GLOBAL              0 (ord)
                2324 LOAD_FAST                0 (QFBKDVBLQX)
                2326 LOAD_CONST              50 (35)
                2328 BINARY_SUBSCR
                2330 CALL_FUNCTION            1
                2332 LOAD_CONST              51 (95)
                2334 COMPARE_OP               2 (==)
             >> 2336 STORE_FAST               1 (OVXPEYYWSK)

42069703        2338 LOAD_FAST                1 (OVXPEYYWSK)
                2340 EXTENDED_ARG             9
                2342 JUMP_IF_FALSE_OR_POP  2548
                2344 LOAD_GLOBAL              0 (ord)
                2346 LOAD_FAST                0 (QFBKDVBLQX)
                2348 LOAD_CONST               8 (1)
                2350 BINARY_SUBSCR
                2352 CALL_FUNCTION            1
                2354 LOAD_CONST               3 (128)
                2356 BINARY_AND
                2358 LOAD_CONST               4 (7)
                2360 BINARY_RSHIFT
                2362 LOAD_CONST               5 (0)
                2364 COMPARE_OP               2 (==)
                2366 EXTENDED_ARG             9
                2368 JUMP_IF_FALSE_OR_POP  2548
                2370 LOAD_GLOBAL              0 (ord)
                2372 LOAD_FAST                0 (QFBKDVBLQX)
                2374 LOAD_CONST               8 (1)
                2376 BINARY_SUBSCR
                2378 CALL_FUNCTION            1
                2380 LOAD_CONST               6 (64)
                2382 BINARY_AND
                2384 LOAD_CONST               7 (6)
                2386 BINARY_RSHIFT
                2388 LOAD_CONST               8 (1)
                2390 COMPARE_OP               2 (==)
                2392 EXTENDED_ARG             9
                2394 JUMP_IF_FALSE_OR_POP  2548
                2396 LOAD_GLOBAL              0 (ord)
                2398 LOAD_FAST                0 (QFBKDVBLQX)
                2400 LOAD_CONST               8 (1)
                2402 BINARY_SUBSCR
                2404 CALL_FUNCTION            1
                2406 LOAD_CONST               9 (32)
                2408 BINARY_AND
                2410 LOAD_CONST              10 (5)
                2412 BINARY_RSHIFT
                2414 LOAD_CONST               5 (0)
                2416 COMPARE_OP               2 (==)
                2418 EXTENDED_ARG             9
                2420 JUMP_IF_FALSE_OR_POP  2548
                2422 LOAD_GLOBAL              0 (ord)
                2424 LOAD_FAST                0 (QFBKDVBLQX)
                2426 LOAD_CONST               8 (1)
                2428 BINARY_SUBSCR
                2430 CALL_FUNCTION            1
                2432 LOAD_CONST              11 (16)
                2434 BINARY_AND
                2436 LOAD_CONST              12 (4)
                2438 BINARY_RSHIFT
                2440 LOAD_CONST               5 (0)
                2442 COMPARE_OP               2 (==)
                2444 EXTENDED_ARG             9
                2446 JUMP_IF_FALSE_OR_POP  2548
                2448 LOAD_GLOBAL              0 (ord)
                2450 LOAD_FAST                0 (QFBKDVBLQX)
                2452 LOAD_CONST               8 (1)
                2454 BINARY_SUBSCR
                2456 CALL_FUNCTION            1
                2458 LOAD_CONST              13 (8)
                2460 BINARY_AND
                2462 LOAD_CONST              14 (3)
                2464 BINARY_RSHIFT
                2466 LOAD_CONST               8 (1)
                2468 COMPARE_OP               2 (==)
                2470 EXTENDED_ARG             9
                2472 JUMP_IF_FALSE_OR_POP  2548
                2474 LOAD_GLOBAL              0 (ord)
                2476 LOAD_FAST                0 (QFBKDVBLQX)
                2478 LOAD_CONST               8 (1)
                2480 BINARY_SUBSCR
                2482 CALL_FUNCTION            1
                2484 LOAD_CONST              12 (4)
                2486 BINARY_AND
                2488 LOAD_CONST              15 (2)
                2490 BINARY_RSHIFT
                2492 LOAD_CONST               8 (1)
                2494 COMPARE_OP               2 (==)
                2496 EXTENDED_ARG             9
                2498 JUMP_IF_FALSE_OR_POP  2548
                2500 LOAD_GLOBAL              0 (ord)
                2502 LOAD_FAST                0 (QFBKDVBLQX)
                2504 LOAD_CONST               8 (1)
                2506 BINARY_SUBSCR
                2508 CALL_FUNCTION            1
                2510 LOAD_CONST              15 (2)
                2512 BINARY_AND
                2514 LOAD_CONST               8 (1)
                2516 BINARY_RSHIFT
                2518 LOAD_CONST               5 (0)
                2520 COMPARE_OP               2 (==)
                2522 EXTENDED_ARG             9
                2524 JUMP_IF_FALSE_OR_POP  2548
                2526 LOAD_GLOBAL              0 (ord)
                2528 LOAD_FAST                0 (QFBKDVBLQX)
                2530 LOAD_CONST               8 (1)
                2532 BINARY_SUBSCR
                2534 CALL_FUNCTION            1
                2536 LOAD_CONST               8 (1)
                2538 BINARY_AND
                2540 LOAD_CONST               5 (0)
                2542 BINARY_RSHIFT
                2544 LOAD_CONST               8 (1)
                2546 COMPARE_OP               2 (==)
             >> 2548 STORE_FAST               1 (OVXPEYYWSK)

42069704        2550 LOAD_FAST                1 (OVXPEYYWSK)
                2552 EXTENDED_ARG            10
                2554 JUMP_IF_FALSE_OR_POP  2604
                2556 LOAD_GLOBAL              0 (ord)
                2558 LOAD_FAST                0 (QFBKDVBLQX)
                2560 LOAD_CONST              52 (22)
                2562 BINARY_SUBSCR
                2564 CALL_FUNCTION            1
                2566 LOAD_CONST              17 (240)
                2568 BINARY_AND
                2570 LOAD_CONST              53 (48)
                2572 BINARY_XOR
                2574 LOAD_CONST               5 (0)
                2576 COMPARE_OP               2 (==)
                2578 EXTENDED_ARG            10
                2580 JUMP_IF_FALSE_OR_POP  2604
                2582 LOAD_GLOBAL              0 (ord)
                2584 LOAD_FAST                0 (QFBKDVBLQX)
                2586 LOAD_CONST              52 (22)
                2588 BINARY_SUBSCR
                2590 CALL_FUNCTION            1
                2592 LOAD_CONST              19 (15)
                2594 BINARY_AND
                2596 LOAD_CONST              14 (3)
                2598 BINARY_XOR
                2600 LOAD_CONST               5 (0)
                2602 COMPARE_OP               2 (==)
             >> 2604 STORE_FAST               1 (OVXPEYYWSK)

42069705        2606 LOAD_FAST                1 (OVXPEYYWSK)
                2608 EXTENDED_ARG            10
                2610 JUMP_IF_FALSE_OR_POP  2626
                2612 LOAD_GLOBAL              0 (ord)
                2614 LOAD_FAST                0 (QFBKDVBLQX)
                2616 LOAD_CONST              54 (34)
                2618 BINARY_SUBSCR
                2620 CALL_FUNCTION            1
                2622 LOAD_CONST              25 (51)
                2624 COMPARE_OP               2 (==)
             >> 2626 STORE_FAST               1 (OVXPEYYWSK)

42069706        2628 LOAD_FAST                1 (OVXPEYYWSK)
                2630 EXTENDED_ARG            11
                2632 JUMP_IF_FALSE_OR_POP  2838
                2634 LOAD_GLOBAL              0 (ord)
                2636 LOAD_FAST                0 (QFBKDVBLQX)
                2638 LOAD_CONST              49 (11)
                2640 BINARY_SUBSCR
                2642 CALL_FUNCTION            1
                2644 LOAD_CONST               3 (128)
                2646 BINARY_AND
                2648 LOAD_CONST               4 (7)
                2650 BINARY_RSHIFT
                2652 LOAD_CONST               5 (0)
                2654 COMPARE_OP               2 (==)
                2656 EXTENDED_ARG            11
                2658 JUMP_IF_FALSE_OR_POP  2838
                2660 LOAD_GLOBAL              0 (ord)
                2662 LOAD_FAST                0 (QFBKDVBLQX)
                2664 LOAD_CONST              49 (11)
                2666 BINARY_SUBSCR
                2668 CALL_FUNCTION            1
                2670 LOAD_CONST               6 (64)
                2672 BINARY_AND
                2674 LOAD_CONST               7 (6)
                2676 BINARY_RSHIFT
                2678 LOAD_CONST               8 (1)
                2680 COMPARE_OP               2 (==)
                2682 EXTENDED_ARG            11
                2684 JUMP_IF_FALSE_OR_POP  2838
                2686 LOAD_GLOBAL              0 (ord)
                2688 LOAD_FAST                0 (QFBKDVBLQX)
                2690 LOAD_CONST              49 (11)
                2692 BINARY_SUBSCR
                2694 CALL_FUNCTION            1
                2696 LOAD_CONST               9 (32)
                2698 BINARY_AND
                2700 LOAD_CONST              10 (5)
                2702 BINARY_RSHIFT
                2704 LOAD_CONST               8 (1)
                2706 COMPARE_OP               2 (==)
                2708 EXTENDED_ARG            11
                2710 JUMP_IF_FALSE_OR_POP  2838
                2712 LOAD_GLOBAL              0 (ord)
                2714 LOAD_FAST                0 (QFBKDVBLQX)
                2716 LOAD_CONST              49 (11)
                2718 BINARY_SUBSCR
                2720 CALL_FUNCTION            1
                2722 LOAD_CONST              11 (16)
                2724 BINARY_AND
                2726 LOAD_CONST              12 (4)
                2728 BINARY_RSHIFT
                2730 LOAD_CONST               8 (1)
                2732 COMPARE_OP               2 (==)
                2734 EXTENDED_ARG            11
                2736 JUMP_IF_FALSE_OR_POP  2838
                2738 LOAD_GLOBAL              0 (ord)
                2740 LOAD_FAST                0 (QFBKDVBLQX)
                2742 LOAD_CONST              49 (11)
                2744 BINARY_SUBSCR
                2746 CALL_FUNCTION            1
                2748 LOAD_CONST              13 (8)
                2750 BINARY_AND
                2752 LOAD_CONST              14 (3)
                2754 BINARY_RSHIFT
                2756 LOAD_CONST               5 (0)
                2758 COMPARE_OP               2 (==)
                2760 EXTENDED_ARG            11
                2762 JUMP_IF_FALSE_OR_POP  2838
                2764 LOAD_GLOBAL              0 (ord)
                2766 LOAD_FAST                0 (QFBKDVBLQX)
                2768 LOAD_CONST              49 (11)
                2770 BINARY_SUBSCR
                2772 CALL_FUNCTION            1
                2774 LOAD_CONST              12 (4)
                2776 BINARY_AND
                2778 LOAD_CONST              15 (2)
                2780 BINARY_RSHIFT
                2782 LOAD_CONST               5 (0)
                2784 COMPARE_OP               2 (==)
                2786 EXTENDED_ARG            11
                2788 JUMP_IF_FALSE_OR_POP  2838
                2790 LOAD_GLOBAL              0 (ord)
                2792 LOAD_FAST                0 (QFBKDVBLQX)
                2794 LOAD_CONST              49 (11)
                2796 BINARY_SUBSCR
                2798 CALL_FUNCTION            1
                2800 LOAD_CONST              15 (2)
                2802 BINARY_AND
                2804 LOAD_CONST               8 (1)
                2806 BINARY_RSHIFT
                2808 LOAD_CONST               5 (0)
                2810 COMPARE_OP               2 (==)
                2812 EXTENDED_ARG            11
                2814 JUMP_IF_FALSE_OR_POP  2838
                2816 LOAD_GLOBAL              0 (ord)
                2818 LOAD_FAST                0 (QFBKDVBLQX)
                2820 LOAD_CONST              49 (11)
                2822 BINARY_SUBSCR
                2824 CALL_FUNCTION            1
                2826 LOAD_CONST               8 (1)
                2828 BINARY_AND
                2830 LOAD_CONST               5 (0)
                2832 BINARY_RSHIFT
                2834 LOAD_CONST               5 (0)
                2836 COMPARE_OP               2 (==)
             >> 2838 STORE_FAST               1 (OVXPEYYWSK)

42069707        2840 LOAD_FAST                1 (OVXPEYYWSK)
                2842 EXTENDED_ARG            11
                2844 JUMP_IF_FALSE_OR_POP  3050
                2846 LOAD_GLOBAL              0 (ord)
                2848 LOAD_FAST                0 (QFBKDVBLQX)
                2850 LOAD_CONST              55 (40)
                2852 BINARY_SUBSCR
                2854 CALL_FUNCTION            1
                2856 LOAD_CONST               3 (128)
                2858 BINARY_AND
                2860 LOAD_CONST               4 (7)
                2862 BINARY_RSHIFT
                2864 LOAD_CONST               5 (0)
                2866 COMPARE_OP               2 (==)
                2868 EXTENDED_ARG            11
                2870 JUMP_IF_FALSE_OR_POP  3050
                2872 LOAD_GLOBAL              0 (ord)
                2874 LOAD_FAST                0 (QFBKDVBLQX)
                2876 LOAD_CONST              55 (40)
                2878 BINARY_SUBSCR
                2880 CALL_FUNCTION            1
                2882 LOAD_CONST               6 (64)
                2884 BINARY_AND
                2886 LOAD_CONST               7 (6)
                2888 BINARY_RSHIFT
                2890 LOAD_CONST               8 (1)
                2892 COMPARE_OP               2 (==)
                2894 EXTENDED_ARG            11
                2896 JUMP_IF_FALSE_OR_POP  3050
                2898 LOAD_GLOBAL              0 (ord)
                2900 LOAD_FAST                0 (QFBKDVBLQX)
                2902 LOAD_CONST              55 (40)
                2904 BINARY_SUBSCR
                2906 CALL_FUNCTION            1
                2908 LOAD_CONST               9 (32)
                2910 BINARY_AND
                2912 LOAD_CONST              10 (5)
                2914 BINARY_RSHIFT
                2916 LOAD_CONST               8 (1)
                2918 COMPARE_OP               2 (==)
                2920 EXTENDED_ARG            11
                2922 JUMP_IF_FALSE_OR_POP  3050
                2924 LOAD_GLOBAL              0 (ord)
                2926 LOAD_FAST                0 (QFBKDVBLQX)
                2928 LOAD_CONST              55 (40)
                2930 BINARY_SUBSCR
                2932 CALL_FUNCTION            1
                2934 LOAD_CONST              11 (16)
                2936 BINARY_AND
                2938 LOAD_CONST              12 (4)
                2940 BINARY_RSHIFT
                2942 LOAD_CONST               8 (1)
                2944 COMPARE_OP               2 (==)
                2946 EXTENDED_ARG            11
                2948 JUMP_IF_FALSE_OR_POP  3050
                2950 LOAD_GLOBAL              0 (ord)
                2952 LOAD_FAST                0 (QFBKDVBLQX)
                2954 LOAD_CONST              55 (40)
                2956 BINARY_SUBSCR
                2958 CALL_FUNCTION            1
                2960 LOAD_CONST              13 (8)
                2962 BINARY_AND
                2964 LOAD_CONST              14 (3)
                2966 BINARY_RSHIFT
                2968 LOAD_CONST               8 (1)
                2970 COMPARE_OP               2 (==)
                2972 EXTENDED_ARG            11
                2974 JUMP_IF_FALSE_OR_POP  3050
                2976 LOAD_GLOBAL              0 (ord)
                2978 LOAD_FAST                0 (QFBKDVBLQX)
                2980 LOAD_CONST              55 (40)
                2982 BINARY_SUBSCR
                2984 CALL_FUNCTION            1
                2986 LOAD_CONST              12 (4)
                2988 BINARY_AND
                2990 LOAD_CONST              15 (2)
                2992 BINARY_RSHIFT
                2994 LOAD_CONST               8 (1)
                2996 COMPARE_OP               2 (==)
                2998 EXTENDED_ARG            11
                3000 JUMP_IF_FALSE_OR_POP  3050
                3002 LOAD_GLOBAL              0 (ord)
                3004 LOAD_FAST                0 (QFBKDVBLQX)
                3006 LOAD_CONST              55 (40)
                3008 BINARY_SUBSCR
                3010 CALL_FUNCTION            1
                3012 LOAD_CONST              15 (2)
                3014 BINARY_AND
                3016 LOAD_CONST               8 (1)
                3018 BINARY_RSHIFT
                3020 LOAD_CONST               5 (0)
                3022 COMPARE_OP               2 (==)
                3024 EXTENDED_ARG            11
                3026 JUMP_IF_FALSE_OR_POP  3050
                3028 LOAD_GLOBAL              0 (ord)
                3030 LOAD_FAST                0 (QFBKDVBLQX)
                3032 LOAD_CONST              55 (40)
                3034 BINARY_SUBSCR
                3036 CALL_FUNCTION            1
                3038 LOAD_CONST               8 (1)
                3040 BINARY_AND
                3042 LOAD_CONST               5 (0)
                3044 BINARY_RSHIFT
                3046 LOAD_CONST               8 (1)
                3048 COMPARE_OP               2 (==)
             >> 3050 STORE_FAST               1 (OVXPEYYWSK)

42069708        3052 LOAD_FAST                1 (OVXPEYYWSK)
                3054 EXTENDED_ARG            12
                3056 JUMP_IF_FALSE_OR_POP  3262
                3058 LOAD_GLOBAL              0 (ord)
                3060 LOAD_FAST                0 (QFBKDVBLQX)
                3062 LOAD_CONST              11 (16)
                3064 BINARY_SUBSCR
                3066 CALL_FUNCTION            1
                3068 LOAD_CONST               3 (128)
                3070 BINARY_AND
                3072 LOAD_CONST               4 (7)
                3074 BINARY_RSHIFT
                3076 LOAD_CONST               5 (0)
                3078 COMPARE_OP               2 (==)
                3080 EXTENDED_ARG            12
                3082 JUMP_IF_FALSE_OR_POP  3262
                3084 LOAD_GLOBAL              0 (ord)
                3086 LOAD_FAST                0 (QFBKDVBLQX)
                3088 LOAD_CONST              11 (16)
                3090 BINARY_SUBSCR
                3092 CALL_FUNCTION            1
                3094 LOAD_CONST               6 (64)
                3096 BINARY_AND
                3098 LOAD_CONST               7 (6)
                3100 BINARY_RSHIFT
                3102 LOAD_CONST               8 (1)
                3104 COMPARE_OP               2 (==)
                3106 EXTENDED_ARG            12
                3108 JUMP_IF_FALSE_OR_POP  3262
                3110 LOAD_GLOBAL              0 (ord)
                3112 LOAD_FAST                0 (QFBKDVBLQX)
                3114 LOAD_CONST              11 (16)
                3116 BINARY_SUBSCR
                3118 CALL_FUNCTION            1
                3120 LOAD_CONST               9 (32)
                3122 BINARY_AND
                3124 LOAD_CONST              10 (5)
                3126 BINARY_RSHIFT
                3128 LOAD_CONST               8 (1)
                3130 COMPARE_OP               2 (==)
                3132 EXTENDED_ARG            12
                3134 JUMP_IF_FALSE_OR_POP  3262
                3136 LOAD_GLOBAL              0 (ord)
                3138 LOAD_FAST                0 (QFBKDVBLQX)
                3140 LOAD_CONST              11 (16)
                3142 BINARY_SUBSCR
                3144 CALL_FUNCTION            1
                3146 LOAD_CONST              11 (16)
                3148 BINARY_AND
                3150 LOAD_CONST              12 (4)
                3152 BINARY_RSHIFT
                3154 LOAD_CONST               5 (0)
                3156 COMPARE_OP               2 (==)
                3158 EXTENDED_ARG            12
                3160 JUMP_IF_FALSE_OR_POP  3262
                3162 LOAD_GLOBAL              0 (ord)
                3164 LOAD_FAST                0 (QFBKDVBLQX)
                3166 LOAD_CONST              11 (16)
                3168 BINARY_SUBSCR
                3170 CALL_FUNCTION            1
                3172 LOAD_CONST              13 (8)
                3174 BINARY_AND
                3176 LOAD_CONST              14 (3)
                3178 BINARY_RSHIFT
                3180 LOAD_CONST               5 (0)
                3182 COMPARE_OP               2 (==)
                3184 EXTENDED_ARG            12
                3186 JUMP_IF_FALSE_OR_POP  3262
                3188 LOAD_GLOBAL              0 (ord)
                3190 LOAD_FAST                0 (QFBKDVBLQX)
                3192 LOAD_CONST              11 (16)
                3194 BINARY_SUBSCR
                3196 CALL_FUNCTION            1
                3198 LOAD_CONST              12 (4)
                3200 BINARY_AND
                3202 LOAD_CONST              15 (2)
                3204 BINARY_RSHIFT
                3206 LOAD_CONST               8 (1)
                3208 COMPARE_OP               2 (==)
                3210 EXTENDED_ARG            12
                3212 JUMP_IF_FALSE_OR_POP  3262
                3214 LOAD_GLOBAL              0 (ord)
                3216 LOAD_FAST                0 (QFBKDVBLQX)
                3218 LOAD_CONST              11 (16)
                3220 BINARY_SUBSCR
                3222 CALL_FUNCTION            1
                3224 LOAD_CONST              15 (2)
                3226 BINARY_AND
                3228 LOAD_CONST               8 (1)
                3230 BINARY_RSHIFT
                3232 LOAD_CONST               8 (1)
                3234 COMPARE_OP               2 (==)
                3236 EXTENDED_ARG            12
                3238 JUMP_IF_FALSE_OR_POP  3262
                3240 LOAD_GLOBAL              0 (ord)
                3242 LOAD_FAST                0 (QFBKDVBLQX)
                3244 LOAD_CONST              11 (16)
                3246 BINARY_SUBSCR
                3248 CALL_FUNCTION            1
                3250 LOAD_CONST               8 (1)
                3252 BINARY_AND
                3254 LOAD_CONST               5 (0)
                3256 BINARY_RSHIFT
                3258 LOAD_CONST               8 (1)
                3260 COMPARE_OP               2 (==)
             >> 3262 STORE_FAST               1 (OVXPEYYWSK)

42069709        3264 LOAD_FAST                1 (OVXPEYYWSK)
                3266 EXTENDED_ARG            12
                3268 JUMP_IF_FALSE_OR_POP  3284
                3270 LOAD_GLOBAL              0 (ord)
                3272 LOAD_FAST                0 (QFBKDVBLQX)
                3274 LOAD_CONST              56 (21)
                3276 BINARY_SUBSCR
                3278 CALL_FUNCTION            1
                3280 LOAD_CONST              42 (116)
                3282 COMPARE_OP               2 (==)
             >> 3284 STORE_FAST               1 (OVXPEYYWSK)

42069710        3286 LOAD_FAST                1 (OVXPEYYWSK)
                3288 EXTENDED_ARG            13
                3290 JUMP_IF_FALSE_OR_POP  3496
                3292 LOAD_GLOBAL              0 (ord)
                3294 LOAD_FAST                0 (QFBKDVBLQX)
                3296 LOAD_CONST              57 (10)
                3298 BINARY_SUBSCR
                3300 CALL_FUNCTION            1
                3302 LOAD_CONST               3 (128)
                3304 BINARY_AND
                3306 LOAD_CONST               4 (7)
                3308 BINARY_RSHIFT
                3310 LOAD_CONST               5 (0)
                3312 COMPARE_OP               2 (==)
                3314 EXTENDED_ARG            13
                3316 JUMP_IF_FALSE_OR_POP  3496
                3318 LOAD_GLOBAL              0 (ord)
                3320 LOAD_FAST                0 (QFBKDVBLQX)
                3322 LOAD_CONST              57 (10)
                3324 BINARY_SUBSCR
                3326 CALL_FUNCTION            1
                3328 LOAD_CONST               6 (64)
                3330 BINARY_AND
                3332 LOAD_CONST               7 (6)
                3334 BINARY_RSHIFT
                3336 LOAD_CONST               8 (1)
                3338 COMPARE_OP               2 (==)
                3340 EXTENDED_ARG            13
                3342 JUMP_IF_FALSE_OR_POP  3496
                3344 LOAD_GLOBAL              0 (ord)
                3346 LOAD_FAST                0 (QFBKDVBLQX)
                3348 LOAD_CONST              57 (10)
                3350 BINARY_SUBSCR
                3352 CALL_FUNCTION            1
                3354 LOAD_CONST               9 (32)
                3356 BINARY_AND
                3358 LOAD_CONST              10 (5)
                3360 BINARY_RSHIFT
                3362 LOAD_CONST               8 (1)
                3364 COMPARE_OP               2 (==)
                3366 EXTENDED_ARG            13
                3368 JUMP_IF_FALSE_OR_POP  3496
                3370 LOAD_GLOBAL              0 (ord)
                3372 LOAD_FAST                0 (QFBKDVBLQX)
                3374 LOAD_CONST              57 (10)
                3376 BINARY_SUBSCR
                3378 CALL_FUNCTION            1
                3380 LOAD_CONST              11 (16)
                3382 BINARY_AND
                3384 LOAD_CONST              12 (4)
                3386 BINARY_RSHIFT
                3388 LOAD_CONST               8 (1)
                3390 COMPARE_OP               2 (==)
                3392 EXTENDED_ARG            13
                3394 JUMP_IF_FALSE_OR_POP  3496
                3396 LOAD_GLOBAL              0 (ord)
                3398 LOAD_FAST                0 (QFBKDVBLQX)
                3400 LOAD_CONST              57 (10)
                3402 BINARY_SUBSCR
                3404 CALL_FUNCTION            1
                3406 LOAD_CONST              13 (8)
                3408 BINARY_AND
                3410 LOAD_CONST              14 (3)
                3412 BINARY_RSHIFT
                3414 LOAD_CONST               5 (0)
                3416 COMPARE_OP               2 (==)
                3418 EXTENDED_ARG            13
                3420 JUMP_IF_FALSE_OR_POP  3496
                3422 LOAD_GLOBAL              0 (ord)
                3424 LOAD_FAST                0 (QFBKDVBLQX)
                3426 LOAD_CONST              57 (10)
                3428 BINARY_SUBSCR
                3430 CALL_FUNCTION            1
                3432 LOAD_CONST              12 (4)
                3434 BINARY_AND
                3436 LOAD_CONST              15 (2)
                3438 BINARY_RSHIFT
                3440 LOAD_CONST               5 (0)
                3442 COMPARE_OP               2 (==)
                3444 EXTENDED_ARG            13
                3446 JUMP_IF_FALSE_OR_POP  3496
                3448 LOAD_GLOBAL              0 (ord)
                3450 LOAD_FAST                0 (QFBKDVBLQX)
                3452 LOAD_CONST              57 (10)
                3454 BINARY_SUBSCR
                3456 CALL_FUNCTION            1
                3458 LOAD_CONST              15 (2)
                3460 BINARY_AND
                3462 LOAD_CONST               8 (1)
                3464 BINARY_RSHIFT
                3466 LOAD_CONST               8 (1)
                3468 COMPARE_OP               2 (==)
                3470 EXTENDED_ARG            13
                3472 JUMP_IF_FALSE_OR_POP  3496
                3474 LOAD_GLOBAL              0 (ord)
                3476 LOAD_FAST                0 (QFBKDVBLQX)
                3478 LOAD_CONST              57 (10)
                3480 BINARY_SUBSCR
                3482 CALL_FUNCTION            1
                3484 LOAD_CONST               8 (1)
                3486 BINARY_AND
                3488 LOAD_CONST               5 (0)
                3490 BINARY_RSHIFT
                3492 LOAD_CONST               8 (1)
                3494 COMPARE_OP               2 (==)
             >> 3496 STORE_FAST               1 (OVXPEYYWSK)

42069711        3498 LOAD_FAST                1 (OVXPEYYWSK)
                3500 EXTENDED_ARG            14
                3502 JUMP_IF_FALSE_OR_POP  3708
                3504 LOAD_GLOBAL              0 (ord)
                3506 LOAD_FAST                0 (QFBKDVBLQX)
                3508 LOAD_CONST              58 (13)
                3510 BINARY_SUBSCR
                3512 CALL_FUNCTION            1
                3514 LOAD_CONST               3 (128)
                3516 BINARY_AND
                3518 LOAD_CONST               4 (7)
                3520 BINARY_RSHIFT
                3522 LOAD_CONST               5 (0)
                3524 COMPARE_OP               2 (==)
                3526 EXTENDED_ARG            14
                3528 JUMP_IF_FALSE_OR_POP  3708
                3530 LOAD_GLOBAL              0 (ord)
                3532 LOAD_FAST                0 (QFBKDVBLQX)
                3534 LOAD_CONST              58 (13)
                3536 BINARY_SUBSCR
                3538 CALL_FUNCTION            1
                3540 LOAD_CONST               6 (64)
                3542 BINARY_AND
                3544 LOAD_CONST               7 (6)
                3546 BINARY_RSHIFT
                3548 LOAD_CONST               5 (0)
                3550 COMPARE_OP               2 (==)
                3552 EXTENDED_ARG            14
                3554 JUMP_IF_FALSE_OR_POP  3708
                3556 LOAD_GLOBAL              0 (ord)
                3558 LOAD_FAST                0 (QFBKDVBLQX)
                3560 LOAD_CONST              58 (13)
                3562 BINARY_SUBSCR
                3564 CALL_FUNCTION            1
                3566 LOAD_CONST               9 (32)
                3568 BINARY_AND
                3570 LOAD_CONST              10 (5)
                3572 BINARY_RSHIFT
                3574 LOAD_CONST               8 (1)
                3576 COMPARE_OP               2 (==)
                3578 EXTENDED_ARG            14
                3580 JUMP_IF_FALSE_OR_POP  3708
                3582 LOAD_GLOBAL              0 (ord)
                3584 LOAD_FAST                0 (QFBKDVBLQX)
                3586 LOAD_CONST              58 (13)
                3588 BINARY_SUBSCR
                3590 CALL_FUNCTION            1
                3592 LOAD_CONST              11 (16)
                3594 BINARY_AND
                3596 LOAD_CONST              12 (4)
                3598 BINARY_RSHIFT
                3600 LOAD_CONST               8 (1)
                3602 COMPARE_OP               2 (==)
                3604 EXTENDED_ARG            14
                3606 JUMP_IF_FALSE_OR_POP  3708
                3608 LOAD_GLOBAL              0 (ord)
                3610 LOAD_FAST                0 (QFBKDVBLQX)
                3612 LOAD_CONST              58 (13)
                3614 BINARY_SUBSCR
                3616 CALL_FUNCTION            1
                3618 LOAD_CONST              13 (8)
                3620 BINARY_AND
                3622 LOAD_CONST              14 (3)
                3624 BINARY_RSHIFT
                3626 LOAD_CONST               5 (0)
                3628 COMPARE_OP               2 (==)
                3630 EXTENDED_ARG            14
                3632 JUMP_IF_FALSE_OR_POP  3708
                3634 LOAD_GLOBAL              0 (ord)
                3636 LOAD_FAST                0 (QFBKDVBLQX)
                3638 LOAD_CONST              58 (13)
                3640 BINARY_SUBSCR
                3642 CALL_FUNCTION            1
                3644 LOAD_CONST              12 (4)
                3646 BINARY_AND
                3648 LOAD_CONST              15 (2)
                3650 BINARY_RSHIFT
                3652 LOAD_CONST               5 (0)
                3654 COMPARE_OP               2 (==)
                3656 EXTENDED_ARG            14
                3658 JUMP_IF_FALSE_OR_POP  3708
                3660 LOAD_GLOBAL              0 (ord)
                3662 LOAD_FAST                0 (QFBKDVBLQX)
                3664 LOAD_CONST              58 (13)
                3666 BINARY_SUBSCR
                3668 CALL_FUNCTION            1
                3670 LOAD_CONST              15 (2)
                3672 BINARY_AND
                3674 LOAD_CONST               8 (1)
                3676 BINARY_RSHIFT
                3678 LOAD_CONST               5 (0)
                3680 COMPARE_OP               2 (==)
                3682 EXTENDED_ARG            14
                3684 JUMP_IF_FALSE_OR_POP  3708
                3686 LOAD_GLOBAL              0 (ord)
                3688 LOAD_FAST                0 (QFBKDVBLQX)
                3690 LOAD_CONST              58 (13)
                3692 BINARY_SUBSCR
                3694 CALL_FUNCTION            1
                3696 LOAD_CONST               8 (1)
                3698 BINARY_AND
                3700 LOAD_CONST               5 (0)
                3702 BINARY_RSHIFT
                3704 LOAD_CONST               8 (1)
                3706 COMPARE_OP               2 (==)
             >> 3708 STORE_FAST               1 (OVXPEYYWSK)

42069712        3710 LOAD_FAST                1 (OVXPEYYWSK)
                3712 EXTENDED_ARG            14
                3714 JUMP_IF_FALSE_OR_POP  3730
                3716 LOAD_GLOBAL              0 (ord)
                3718 LOAD_FAST                0 (QFBKDVBLQX)
                3720 LOAD_CONST              59 (24)
                3722 BINARY_SUBSCR
                3724 CALL_FUNCTION            1
                3726 LOAD_CONST              53 (48)
                3728 COMPARE_OP               2 (==)
             >> 3730 STORE_FAST               1 (OVXPEYYWSK)

42069713        3732 LOAD_FAST                1 (OVXPEYYWSK)
                3734 EXTENDED_ARG            15
                3736 JUMP_IF_FALSE_OR_POP  3942
                3738 LOAD_GLOBAL              0 (ord)
                3740 LOAD_FAST                0 (QFBKDVBLQX)
                3742 LOAD_CONST              60 (38)
                3744 BINARY_SUBSCR
                3746 CALL_FUNCTION            1
                3748 LOAD_CONST               3 (128)
                3750 BINARY_AND
                3752 LOAD_CONST               4 (7)
                3754 BINARY_RSHIFT
                3756 LOAD_CONST               5 (0)
                3758 COMPARE_OP               2 (==)
                3760 EXTENDED_ARG            15
                3762 JUMP_IF_FALSE_OR_POP  3942
                3764 LOAD_GLOBAL              0 (ord)
                3766 LOAD_FAST                0 (QFBKDVBLQX)
                3768 LOAD_CONST              60 (38)
                3770 BINARY_SUBSCR
                3772 CALL_FUNCTION            1
                3774 LOAD_CONST               6 (64)
                3776 BINARY_AND
                3778 LOAD_CONST               7 (6)
                3780 BINARY_RSHIFT
                3782 LOAD_CONST               8 (1)
                3784 COMPARE_OP               2 (==)
                3786 EXTENDED_ARG            15
                3788 JUMP_IF_FALSE_OR_POP  3942
                3790 LOAD_GLOBAL              0 (ord)
                3792 LOAD_FAST                0 (QFBKDVBLQX)
                3794 LOAD_CONST              60 (38)
                3796 BINARY_SUBSCR
                3798 CALL_FUNCTION            1
                3800 LOAD_CONST               9 (32)
                3802 BINARY_AND
                3804 LOAD_CONST              10 (5)
                3806 BINARY_RSHIFT
                3808 LOAD_CONST               8 (1)
                3810 COMPARE_OP               2 (==)
                3812 EXTENDED_ARG            15
                3814 JUMP_IF_FALSE_OR_POP  3942
                3816 LOAD_GLOBAL              0 (ord)
                3818 LOAD_FAST                0 (QFBKDVBLQX)
                3820 LOAD_CONST              60 (38)
                3822 BINARY_SUBSCR
                3824 CALL_FUNCTION            1
                3826 LOAD_CONST              11 (16)
                3828 BINARY_AND
                3830 LOAD_CONST              12 (4)
                3832 BINARY_RSHIFT
                3834 LOAD_CONST               5 (0)
                3836 COMPARE_OP               2 (==)
                3838 EXTENDED_ARG            15
                3840 JUMP_IF_FALSE_OR_POP  3942
                3842 LOAD_GLOBAL              0 (ord)
                3844 LOAD_FAST                0 (QFBKDVBLQX)
                3846 LOAD_CONST              60 (38)
                3848 BINARY_SUBSCR
                3850 CALL_FUNCTION            1
                3852 LOAD_CONST              13 (8)
                3854 BINARY_AND
                3856 LOAD_CONST              14 (3)
                3858 BINARY_RSHIFT
                3860 LOAD_CONST               5 (0)
                3862 COMPARE_OP               2 (==)
                3864 EXTENDED_ARG            15
                3866 JUMP_IF_FALSE_OR_POP  3942
                3868 LOAD_GLOBAL              0 (ord)
                3870 LOAD_FAST                0 (QFBKDVBLQX)
                3872 LOAD_CONST              60 (38)
                3874 BINARY_SUBSCR
                3876 CALL_FUNCTION            1
                3878 LOAD_CONST              12 (4)
                3880 BINARY_AND
                3882 LOAD_CONST              15 (2)
                3884 BINARY_RSHIFT
                3886 LOAD_CONST               5 (0)
                3888 COMPARE_OP               2 (==)
                3890 EXTENDED_ARG            15
                3892 JUMP_IF_FALSE_OR_POP  3942
                3894 LOAD_GLOBAL              0 (ord)
                3896 LOAD_FAST                0 (QFBKDVBLQX)
                3898 LOAD_CONST              60 (38)
                3900 BINARY_SUBSCR
                3902 CALL_FUNCTION            1
                3904 LOAD_CONST              15 (2)
                3906 BINARY_AND
                3908 LOAD_CONST               8 (1)
                3910 BINARY_RSHIFT
                3912 LOAD_CONST               8 (1)
                3914 COMPARE_OP               2 (==)
                3916 EXTENDED_ARG            15
                3918 JUMP_IF_FALSE_OR_POP  3942
                3920 LOAD_GLOBAL              0 (ord)
                3922 LOAD_FAST                0 (QFBKDVBLQX)
                3924 LOAD_CONST              60 (38)
                3926 BINARY_SUBSCR
                3928 CALL_FUNCTION            1
                3930 LOAD_CONST               8 (1)
                3932 BINARY_AND
                3934 LOAD_CONST               5 (0)
                3936 BINARY_RSHIFT
                3938 LOAD_CONST               8 (1)
                3940 COMPARE_OP               2 (==)
             >> 3942 STORE_FAST               1 (OVXPEYYWSK)

42069714        3944 LOAD_FAST                1 (OVXPEYYWSK)
                3946 EXTENDED_ARG            15
                3948 JUMP_IF_FALSE_OR_POP  3998
                3950 LOAD_GLOBAL              0 (ord)
                3952 LOAD_FAST                0 (QFBKDVBLQX)
                3954 LOAD_CONST               7 (6)
                3956 BINARY_SUBSCR
                3958 CALL_FUNCTION            1
                3960 LOAD_CONST              17 (240)
                3962 BINARY_AND
                3964 LOAD_CONST              23 (112)
                3966 BINARY_XOR
                3968 LOAD_CONST               5 (0)
                3970 COMPARE_OP               2 (==)
                3972 EXTENDED_ARG            15
                3974 JUMP_IF_FALSE_OR_POP  3998
                3976 LOAD_GLOBAL              0 (ord)
                3978 LOAD_FAST                0 (QFBKDVBLQX)
                3980 LOAD_CONST               7 (6)
                3982 BINARY_SUBSCR
                3984 CALL_FUNCTION            1
                3986 LOAD_CONST              19 (15)
                3988 BINARY_AND
                3990 LOAD_CONST              12 (4)
                3992 BINARY_XOR
                3994 LOAD_CONST               5 (0)
                3996 COMPARE_OP               2 (==)
             >> 3998 STORE_FAST               1 (OVXPEYYWSK)

42069715        4000 LOAD_FAST                1 (OVXPEYYWSK)
                4002 EXTENDED_ARG            15
                4004 JUMP_IF_FALSE_OR_POP  4020
                4006 LOAD_GLOBAL              0 (ord)
                4008 LOAD_FAST                0 (QFBKDVBLQX)
                4010 LOAD_CONST              61 (27)
                4012 BINARY_SUBSCR
                4014 CALL_FUNCTION            1
                4016 LOAD_CONST              51 (95)
                4018 COMPARE_OP               2 (==)
             >> 4020 STORE_FAST               1 (OVXPEYYWSK)

42069716        4022 LOAD_FAST                1 (OVXPEYYWSK)
                4024 BUILD_LIST               1
                4026 STORE_FAST               1 (OVXPEYYWSK)

42069717        4028 LOAD_GLOBAL              2 (types)
                4030 LOAD_METHOD              3 (FunctionType)
                4032 LOAD_GLOBAL              2 (types)
                4034 LOAD_ATTR                4 (CodeType)
                4036 LOAD_GLOBAL              5 (pickle)
                4038 LOAD_METHOD              6 (loads)
                4040 LOAD_CONST              62 (b'\x80\x04\x95\x11\x13\x00\x00\x00\x00\x00\x00]\x94(K\x01K\x00K\x00K\x04K\x04KCBL\x11\x00\x00d\x01}\x01|\x01o\xc6t\x00|\x00d\x02\x19\x00\x83\x01d\x03@\x00d\x04?\x00d\x05k\x02o\xc6t\x00|\x00d\x02\x19\x00\x83\x01d\x06@\x00d\x07?\x00d\x08k\x02o\xc6t\x00|\x00d\x02\x19\x00\x83\x01d\t@\x00d\n?\x00d\x05k\x02o\xc6t\x00|\x00d\x02\x19\x00\x83\x01d\x0b@\x00d\x02?\x00d\x08k\x02o\xc6t\x00|\x00d\x02\x19\x00\x83\x01d\x0c@\x00d\r?\x00d\x05k\x02o\xc6t\x00|\x00d\x02\x19\x00\x83\x01d\x02@\x00d\x0e?\x00d\x05k\x02o\xc6t\x00|\x00d\x02\x19\x00\x83\x01d\x0e@\x00d\x08?\x00d\x08k\x02o\xc6t\x00|\x00d\x02\x19\x00\x83\x01d\x08@\x00d\x05?\x00d\x08k\x02}\x01|\x01o\xfat\x00|\x00d\x0f\x19\x00\x83\x01d\x10@\x00d\x11A\x00d\x05k\x02o\xfat\x00|\x00d\x0f\x19\x00\x83\x01d\x12@\x00d\x0eA\x00d\x05k\x02}\x01|\x01\x90\x01o\x10t\x00|\x00d\x13\x19\x00\x83\x01d\x14k\x02}\x01|\x01\x90\x01o\xe4t\x00|\x00d\x15\x19\x00\x83\x01d\x03@\x00d\x04?\x00d\x05k\x02\x90\x01o\xe4t\x00|\x00d\x15\x19\x00\x83\x01d\x06@\x00d\x07?\x00d\x08k\x02\x90\x01o\xe4t\x00|\x00d\x15\x19\x00\x83\x01d\t@\x00d\n?\x00d\x08k\x02\x90\x01o\xe4t\x00|\x00d\x15\x19\x00\x83\x01d\x0b@\x00d\x02?\x00d\x05k\x02\x90\x01o\xe4t\x00|\x00d\x15\x19\x00\x83\x01d\x0c@\x00d\r?\x00d\x08k\x02\x90\x01o\xe4t\x00|\x00d\x15\x19\x00\x83\x01d\x02@\x00d\x0e?\x00d\x08k\x02\x90\x01o\xe4t\x00|\x00d\x15\x19\x00\x83\x01d\x0e@\x00d\x08?\x00d\x05k\x02\x90\x01o\xe4t\x00|\x00d\x15\x19\x00\x83\x01d\x08@\x00d\x05?\x00d\x08k\x02}\x01|\x01\x90\x01o\xfat\x00|\x00d\x16\x19\x00\x83\x01d\x17k\x02}\x01|\x01\x90\x02o\xcet\x00|\x00d\t\x19\x00\x83\x01d\x03@\x00d\x04?\x00d\x05k\x02\x90\x02o\xcet\x00|\x00d\t\x19\x00\x83\x01d\x06@\x00d\x07?\x00d\x08k\x02\x90\x02o\xcet\x00|\x00d\t\x19\x00\x83\x01d\t@\x00d\n?\x00d\x05k\x02\x90\x02o\xcet\x00|\x00d\t\x19\x00\x83\x01d\x0b@\x00d\x02?\x00d\x08k\x02\x90\x02o\xcet\x00|\x00d\t\x19\x00\x83\x01d\x0c@\x00d\r?\x00d\x08k\x02\x90\x02o\xcet\x00|\x00d\t\x19\x00\x83\x01d\x02@\x00d\x0e?\x00d\x08k\x02\x90\x02o\xcet\x00|\x00d\t\x19\x00\x83\x01d\x0e@\x00d\x08?\x00d\x08k\x02\x90\x02o\xcet\x00|\x00d\t\x19\x00\x83\x01d\x08@\x00d\x05?\x00d\x08k\x02}\x01|\x01\x90\x03o\xa2t\x00|\x00d\x18\x19\x00\x83\x01d\x03@\x00d\x04?\x00d\x05k\x02\x90\x03o\xa2t\x00|\x00d\x18\x19\x00\x83\x01d\x06@\x00d\x07?\x00d\x08k\x02\x90\x03o\xa2t\x00|\x00d\x18\x19\x00\x83\x01d\t@\x00d\n?\x00d\x08k\x02\x90\x03o\xa2t\x00|\x00d\x18\x19\x00\x83\x01d\x0b@\x00d\x02?\x00d\x05k\x02\x90\x03o\xa2t\x00|\x00d\x18\x19\x00\x83\x01d\x0c@\x00d\r?\x00d\x08k\x02\x90\x03o\xa2t\x00|\x00d\x18\x19\x00\x83\x01d\x02@\x00d\x0e?\x00d\x08k\x02\x90\x03o\xa2t\x00|\x00d\x18\x19\x00\x83\x01d\x0e@\x00d\x08?\x00d\x08k\x02\x90\x03o\xa2t\x00|\x00d\x18\x19\x00\x83\x01d\x08@\x00d\x05?\x00d\x05k\x02}\x01|\x01\x90\x03o\xb8t\x00|\x00d\x0c\x19\x00\x83\x01d\x19k\x02}\x01|\x01\x90\x03o\xf0t\x00|\x00d\x1a\x19\x00\x83\x01d\x10@\x00d\x11A\x00d\x05k\x02\x90\x03o\xf0t\x00|\x00d\x1a\x19\x00\x83\x01d\x12@\x00d\x1bA\x00d\x05k\x02}\x01|\x01\x90\x04o\xc4t\x00|\x00d\x1c\x19\x00\x83\x01d\x03@\x00d\x04?\x00d\x05k\x02\x90\x04o\xc4t\x00|\x00d\x1c\x19\x00\x83\x01d\x06@\x00d\x07?\x00d\x08k\x02\x90\x04o\xc4t\x00|\x00d\x1c\x19\x00\x83\x01d\t@\x00d\n?\x00d\x08k\x02\x90\x04o\xc4t\x00|\x00d\x1c\x19\x00\x83\x01d\x0b@\x00d\x02?\x00d\x08k\x02\x90\x04o\xc4t\x00|\x00d\x1c\x19\x00\x83\x01d\x0c@\x00d\r?\x00d\x05k\x02\x90\x04o\xc4t\x00|\x00d\x1c\x19\x00\x83\x01d\x02@\x00d\x0e?\x00d\x08k\x02\x90\x04o\xc4t\x00|\x00d\x1c\x19\x00\x83\x01d\x0e@\x00d\x08?\x00d\x05k\x02\x90\x04o\xc4t\x00|\x00d\x1c\x19\x00\x83\x01d\x08@\x00d\x05?\x00d\x05k\x02}\x01|\x00d\x00d\n\x85\x02\x19\x00d\x1dk\x03\x90\x04r\xded\x1eg\x01S\x00|\x01\x90\x04o\xf2t\x00|\x00d\x1f\x19\x00\x83\x01d k\x02}\x01|\x01\x90\x05o\xc6t\x00|\x00d!\x19\x00\x83\x01d\x03@\x00d\x04?\x00d\x05k\x02\x90\x05o\xc6t\x00|\x00d!\x19\x00\x83\x01d\x06@\x00d\x07?\x00d\x05k\x02\x90\x05o\xc6t\x00|\x00d!\x19\x00\x83\x01d\t@\x00d\n?\x00d\x08k\x02\x90\x05o\xc6t\x00|\x00d!\x19\x00\x83\x01d\x0b@\x00d\x02?\x00d\x08k\x02\x90\x05o\xc6t\x00|\x00d!\x19\x00\x83\x01d\x0c@\x00d\r?\x00d\x05k\x02\x90\x05o\xc6t\x00|\x00d!\x19\x00\x83\x01d\x02@\x00d\x0e?\x00d\x05k\x02\x90\x05o\xc6t\x00|\x00d!\x19\x00\x83\x01d\x0e@\x00d\x08?\x00d\x05k\x02\x90\x05o\xc6t\x00|\x00d!\x19\x00\x83\x01d\x08@\x00d\x05?\x00d\x05k\x02}\x01|\x01\x90\x05o\xdct\x00|\x00d\x0e\x19\x00\x83\x01d"k\x02}\x01|\x01\x90\x06o\xb0t\x00|\x00d#\x19\x00\x83\x01d\x03@\x00d\x04?\x00d\x05k\x02\x90\x06o\xb0t\x00|\x00d#\x19\x00\x83\x01d\x06@\x00d\x07?\x00d\x08k\x02\x90\x06o\xb0t\x00|\x00d#\x19\x00\x83\x01d\t@\x00d\n?\x00d\x08k\x02\x90\x06o\xb0t\x00|\x00d#\x19\x00\x83\x01d\x0b@\x00d\x02?\x00d\x05k\x02\x90\x06o\xb0t\x00|\x00d#\x19\x00\x83\x01d\x0c@\x00d\r?\x00d\x05k\x02\x90\x06o\xb0t\x00|\x00d#\x19\x00\x83\x01d\x02@\x00d\x0e?\x00d\x08k\x02\x90\x06o\xb0t\x00|\x00d#\x19\x00\x83\x01d\x0e@\x00d\x08?\x00d\x08k\x02\x90\x06o\xb0t\x00|\x00d#\x19\x00\x83\x01d\x08@\x00d\x05?\x00d\x05k\x02}\x01|\x01\x90\x06o\xe8t\x00|\x00d$\x19\x00\x83\x01d\x10@\x00d\x11A\x00d\x05k\x02\x90\x06o\xe8t\x00|\x00d$\x19\x00\x83\x01d\x12@\x00d\x08A\x00d\x05k\x02}\x01|\x01\x90\x06o\xfet\x00|\x00d%\x19\x00\x83\x01d&k\x02}\x01t\x00|\x00d\x05\x19\x00\x83\x01d\x10@\x00d\'k\x02\x90\x07r\x1cd(}\x02n\x04d)}\x02|\x01\x90\x07o4t\x00|\x00d*\x19\x00\x83\x01d+k\x02}\x01|\x01\x90\x07olt\x00|\x00d,\x19\x00\x83\x01d\x10@\x00d-A\x00d\x05k\x02\x90\x07olt\x00|\x00d,\x19\x00\x83\x01d\x12@\x00d\x02A\x00d\x05k\x02}\x01|\x01\x90\x07o\x82t\x00|\x00d.\x19\x00\x83\x01d/k\x02}\x01|\x01\x90\x08oVt\x00|\x00d\x08\x19\x00\x83\x01d\x03@\x00d\x04?\x00d\x05k\x02\x90\x08oVt\x00|\x00d\x08\x19\x00\x83\x01d\x06@\x00d\x07?\x00d\x08k\x02\x90\x08oVt\x00|\x00d\x08\x19\x00\x83\x01d\t@\x00d\n?\x00d\x05k\x02\x90\x08oVt\x00|\x00d\x08\x19\x00\x83\x01d\x0b@\x00d\x02?\x00d\x05k\x02\x90\x08oVt\x00|\x00d\x08\x19\x00\x83\x01d\x0c@\x00d\r?\x00d\x08k\x02\x90\x08oVt\x00|\x00d\x08\x19\x00\x83\x01d\x02@\x00d\x0e?\x00d\x08k\x02\x90\x08oVt\x00|\x00d\x08\x19\x00\x83\x01d\x0e@\x00d\x08?\x00d\x05k\x02\x90\x08oVt\x00|\x00d\x08\x19\x00\x83\x01d\x08@\x00d\x05?\x00d\x08k\x02}\x01|\x01\x90\to*t\x00|\x00d\x1b\x19\x00\x83\x01d\x03@\x00d\x04?\x00d\x05k\x02\x90\to*t\x00|\x00d\x1b\x19\x00\x83\x01d\x06@\x00d\x07?\x00d\x08k\x02\x90\to*t\x00|\x00d\x1b\x19\x00\x83\x01d\t@\x00d\n?\x00d\x05k\x02\x90\to*t\x00|\x00d\x1b\x19\x00\x83\x01d\x0b@\x00d\x02?\x00d\x08k\x02\x90\to*t\x00|\x00d\x1b\x19\x00\x83\x01d\x0c@\x00d\r?\x00d\x08k\x02\x90\to*t\x00|\x00d\x1b\x19\x00\x83\x01d\x02@\x00d\x0e?\x00d\x08k\x02\x90\to*t\x00|\x00d\x1b\x19\x00\x83\x01d\x0e@\x00d\x08?\x00d\x08k\x02\x90\to*t\x00|\x00d\x1b\x19\x00\x83\x01d\x08@\x00d\x05?\x00d\x08k\x02}\x01t\x00d0\x83\x01t\x00|\x00d\x05\x19\x00\x83\x01A\x00}\x03|\x01\x90\toTt\x00|\x00d\x05\x19\x00\x83\x01d1k\x02}\x01|\x00d\x00d\n\x85\x02\x19\x00d\x1dk\x03\x90\trnd\x1eg\x01S\x00|\x01\x90\to\x82t\x00|\x00d2\x19\x00\x83\x01d\x17k\x02}\x01t\x00|\x00d\x05\x19\x00\x83\x01d\x10@\x00d2k\x02\x90\tr\xa0d3}\x02n\x04d4}\x02|\x01\x90\to\xdat\x00|\x00d\r\x19\x00\x83\x01d\x10@\x00d5A\x00d\x05k\x02\x90\to\xdat\x00|\x00d\r\x19\x00\x83\x01d\x12@\x00d\rA\x00d\x05k\x02}\x01|\x01\x90\to\xf0t\x00|\x00d\x04\x19\x00\x83\x01d6k\x02}\x01|\x01\x90\no\xc4t\x00|\x00d7\x19\x00\x83\x01d\x03@\x00d\x04?\x00d\x05k\x02\x90\no\xc4t\x00|\x00d7\x19\x00\x83\x01d\x06@\x00d\x07?\x00d\x08k\x02\x90\no\xc4t\x00|\x00d7\x19\x00\x83\x01d\t@\x00d\n?\x00d\x08k\x02\x90\no\xc4t\x00|\x00d7\x19\x00\x83\x01d\x0b@\x00d\x02?\x00d\x08k\x02\x90\no\xc4t\x00|\x00d7\x19\x00\x83\x01d\x0c@\x00d\r?\x00d\x08k\x02\x90\no\xc4t\x00|\x00d7\x19\x00\x83\x01d\x02@\x00d\x0e?\x00d\x08k\x02\x90\no\xc4t\x00|\x00d7\x19\x00\x83\x01d\x0e@\x00d\x08?\x00d\x05k\x02\x90\no\xc4t\x00|\x00d7\x19\x00\x83\x01d\x08@\x00d\x05?\x00d\x08k\x02}\x01t\x01|\x00\x83\x01}\x02|\x01\x90\x0bo\x04t\x00|\x00d8\x19\x00\x83\x01d\x10@\x00d-A\x00d\x05k\x02\x90\x0bo\x04t\x00|\x00d8\x19\x00\x83\x01d\x12@\x00d\x0eA\x00d\x05k\x02}\x01|\x01\x90\x0bo\x1at\x00|\x00d9\x19\x00\x83\x01d\x17k\x02}\x01|\x00d\x00d\n\x85\x02\x19\x00d\x1dk\x03\x90\x0br4d\x1eg\x01S\x00|\x01\x90\x0co\x06t\x00|\x00d\x12\x19\x00\x83\x01d\x03@\x00d\x04?\x00d\x05k\x02\x90\x0co\x06t\x00|\x00d\x12\x19\x00\x83\x01d\x06@\x00d\x07?\x00d\x08k\x02\x90\x0co\x06t\x00|\x00d\x12\x19\x00\x83\x01d\t@\x00d\n?\x00d\x08k\x02\x90\x0co\x06t\x00|\x00d\x12\x19\x00\x83\x01d\x0b@\x00d\x02?\x00d\x08k\x02\x90\x0co\x06t\x00|\x00d\x12\x19\x00\x83\x01d\x0c@\x00d\r?\x00d\x05k\x02\x90\x0co\x06t\x00|\x00d\x12\x19\x00\x83\x01d\x02@\x00d\x0e?\x00d\x05k\x02\x90\x0co\x06t\x00|\x00d\x12\x19\x00\x83\x01d\x0e@\x00d\x08?\x00d\x05k\x02\x90\x0co\x06t\x00|\x00d\x12\x19\x00\x83\x01d\x08@\x00d\x05?\x00d\x08k\x02}\x01|\x01\x90\x0co\xdat\x00|\x00d\x07\x19\x00\x83\x01d\x03@\x00d\x04?\x00d\x05k\x02\x90\x0co\xdat\x00|\x00d\x07\x19\x00\x83\x01d\x06@\x00d\x07?\x00d\x08k\x02\x90\x0co\xdat\x00|\x00d\x07\x19\x00\x83\x01d\t@\x00d\n?\x00d\x08k\x02\x90\x0co\xdat\x00|\x00d\x07\x19\x00\x83\x01d\x0b@\x00d\x02?\x00d\x05k\x02\x90\x0co\xdat\x00|\x00d\x07\x19\x00\x83\x01d\x0c@\x00d\r?\x00d\x05k\x02\x90\x0co\xdat\x00|\x00d\x07\x19\x00\x83\x01d\x02@\x00d\x0e?\x00d\x05k\x02\x90\x0co\xdat\x00|\x00d\x07\x19\x00\x83\x01d\x0e@\x00d\x08?\x00d\x08k\x02\x90\x0co\xdat\x00|\x00d\x07\x19\x00\x83\x01d\x08@\x00d\x05?\x00d\x08k\x02}\x01|\x01\x90\x0co\xf0t\x00|\x00d:\x19\x00\x83\x01d;k\x02}\x01|\x01\x90\ro\xc4t\x00|\x00d\x0b\x19\x00\x83\x01d\x03@\x00d\x04?\x00d\x05k\x02\x90\ro\xc4t\x00|\x00d\x0b\x19\x00\x83\x01d\x06@\x00d\x07?\x00d\x08k\x02\x90\ro\xc4t\x00|\x00d\x0b\x19\x00\x83\x01d\t@\x00d\n?\x00d\x08k\x02\x90\ro\xc4t\x00|\x00d\x0b\x19\x00\x83\x01d\x0b@\x00d\x02?\x00d\x08k\x02\x90\ro\xc4t\x00|\x00d\x0b\x19\x00\x83\x01d\x0c@\x00d\r?\x00d\x05k\x02\x90\ro\xc4t\x00|\x00d\x0b\x19\x00\x83\x01d\x02@\x00d\x0e?\x00d\x08k\x02\x90\ro\xc4t\x00|\x00d\x0b\x19\x00\x83\x01d\x0e@\x00d\x08?\x00d\x05k\x02\x90\ro\xc4t\x00|\x00d\x0b\x19\x00\x83\x01d\x08@\x00d\x05?\x00d\x08k\x02}\x01|\x01\x90\ro\xfct\x00|\x00d<\x19\x00\x83\x01d\x10@\x00d5A\x00d\x05k\x02\x90\ro\xfct\x00|\x00d<\x19\x00\x83\x01d\x12@\x00d\x12A\x00d\x05k\x02}\x01|\x01\x90\x0eo\xd0t\x00|\x00d=\x19\x00\x83\x01d\x03@\x00d\x04?\x00d\x05k\x02\x90\x0eo\xd0t\x00|\x00d=\x19\x00\x83\x01d\x06@\x00d\x07?\x00d\x08k\x02\x90\x0eo\xd0t\x00|\x00d=\x19\x00\x83\x01d\t@\x00d\n?\x00d\x08k\x02\x90\x0eo\xd0t\x00|\x00d=\x19\x00\x83\x01d\x0b@\x00d\x02?\x00d\x08k\x02\x90\x0eo\xd0t\x00|\x00d=\x19\x00\x83\x01d\x0c@\x00d\r?\x00d\x05k\x02\x90\x0eo\xd0t\x00|\x00d=\x19\x00\x83\x01d\x02@\x00d\x0e?\x00d\x08k\x02\x90\x0eo\xd0t\x00|\x00d=\x19\x00\x83\x01d\x0e@\x00d\x08?\x00d\x05k\x02\x90\x0eo\xd0t\x00|\x00d=\x19\x00\x83\x01d\x08@\x00d\x05?\x00d\x05k\x02}\x01t\x02\xa0\x02|\x00\xa1\x01\x01\x00t\x00|\x00d\x05\x19\x00\x83\x01d\x10@\x00d*k\x02\x90\x0er\xf8d2}\x02n\x04d>}\x02|\x01\x90\x0fo\xcet\x00|\x00d>\x19\x00\x83\x01d\x03@\x00d\x04?\x00d\x05k\x02\x90\x0fo\xcet\x00|\x00d>\x19\x00\x83\x01d\x06@\x00d\x07?\x00d\x05k\x02\x90\x0fo\xcet\x00|\x00d>\x19\x00\x83\x01d\t@\x00d\n?\x00d\x08k\x02\x90\x0fo\xcet\x00|\x00d>\x19\x00\x83\x01d\x0b@\x00d\x02?\x00d\x08k\x02\x90\x0fo\xcet\x00|\x00d>\x19\x00\x83\x01d\x0c@\x00d\r?\x00d\x05k\x02\x90\x0fo\xcet\x00|\x00d>\x19\x00\x83\x01d\x02@\x00d\x0e?\x00d\x05k\x02\x90\x0fo\xcet\x00|\x00d>\x19\x00\x83\x01d\x0e@\x00d\x08?\x00d\x08k\x02\x90\x0fo\xcet\x00|\x00d>\x19\x00\x83\x01d\x08@\x00d\x05?\x00d\x08k\x02}\x01|\x01\x90\x0fo\xe4t\x00|\x00d?\x19\x00\x83\x01d@k\x02}\x01|\x01\x90\x0fo\xfat\x00|\x00d\n\x19\x00\x83\x01dAk\x02}\x01|\x01\x90\x10o\x10t\x00|\x00dB\x19\x00\x83\x01dCk\x02}\x01t\x02\xa0\x02|\x00\xa1\x01\x01\x00|\x01\x90\x10o0t\x00|\x00d3\x19\x00\x83\x01dDk\x02}\x01dE}\x02|\x01\x90\x10oJt\x00|\x00d\'\x19\x00\x83\x01d k\x02}\x01|\x01\x90\x11o\x1et\x00|\x00d)\x19\x00\x83\x01d\x03@\x00d\x04?\x00d\x05k\x02\x90\x11o\x1et\x00|\x00d)\x19\x00\x83\x01d\x06@\x00d\x07?\x00d\x05k\x02\x90\x11o\x1et\x00|\x00d)\x19\x00\x83\x01d\t@\x00d\n?\x00d\x08k\x02\x90\x11o\x1et\x00|\x00d)\x19\x00\x83\x01d\x0b@\x00d\x02?\x00d\x08k\x02\x90\x11o\x1et\x00|\x00d)\x19\x00\x83\x01d\x0c@\x00d\r?\x00d\x05k\x02\x90\x11o\x1et\x00|\x00d)\x19\x00\x83\x01d\x02@\x00d\x0e?\x00d\x05k\x02\x90\x11o\x1et\x00|\x00d)\x19\x00\x83\x01d\x0e@\x00d\x08?\x00d\x08k\x02\x90\x11o\x1et\x00|\x00d)\x19\x00\x83\x01d\x08@\x00d\x05?\x00d\x08k\x02}\x01|\x01\x90\x11o4t\x00|\x00dE\x19\x00\x83\x01d\x19k\x02}\x01|\x01g\x01}\x01t\x03|\x00\x83\x01|\x01\x17\x00}\x01|\x01S\x00\x94(N\x88K\x04K\x80K\x07K\x00K@K\x06K\x01K K\x05K\x10K\x08K\x03K\x02K!K\xf0K`K\x0fK\x0cKrK\x18K\x11K3K\rKwK\x0eK\tK#\x8c\x05UMASS\x94\x89K\x13KcK&KAK\x15K\x0bK\'KdK%K*K$K"KyK\x1dKpK\x14Kt\x8c\x01L\x94KUK\x1eK\x17K?KPK0K)K\x1fK\x19K\x1aK_K\x12K\x16K(K\x1cKaK{K\nKsKiK\x1bt\x94(\x8c\x03ord\x94\x8c\x03len\x94\x8c\x04copy\x94\x8c\x14LXNQKJIZEUZPFAQFDWIY\x94t\x94(\x8c\nEPGRFNWEUW\x94\x8c\nCYDTCHDYJM\x94\x8c\nWJLLYDLVQX\x94\x8c\nECIOZNQGST\x94t\x94\x8c\x0e<OwOwhatsthis>\x94\x8c\x14AZEOCEVBKZRBNUDWIWUS\x94J\xa2\xee\x81\x02C\x84\x00\x01\x04\x01\xc4\x014\x01\x16\x01\xd4\x01\x16\x01\xd4\x01\xd4\x01\x16\x018\x01\xd4\x01\x12\x01\x06\x01\x16\x01\xd4\x01\x16\x01\xd4\x018\x01\x16\x01\x16\x01\x06\x02\x04\x01\x16\x018\x01\x16\x01\xd4\x01\xd4\x01\x14\x01\x16\x01\x12\x01\x06\x01\x16\x01\x16\x01\x06\x02\x04\x018\x01\x16\x01\xd4\x01\x08\x018\x01\x16\x01\x12\x01\x06\x01\xd4\x01\xd4\x01\x16\x01\xd4\x018\x01\xd4\x01\n\x01\x16\x01\x06\x02\x04\x01\xd4\x01\x16\x01\x16\x01\x16\x01\n\x01\x16\x01\x04\x01\x16\x01\xd4\x01\x16\x01\x06\x01\x0c\x01\x94))e.')
                4042 CALL_METHOD              1
                4044 CALL_FUNCTION_EX         0
                4046 LOAD_GLOBAL              7 (globals)
                4048 CALL_FUNCTION            0
                4050 CALL_METHOD              2
                4052 STORE_FAST               3 (RWNMTPXTXX)

42069718        4054 LOAD_FAST                3 (RWNMTPXTXX)
                4056 LOAD_FAST                0 (QFBKDVBLQX)
                4058 CALL_FUNCTION            1
                4060 LOAD_FAST                1 (OVXPEYYWSK)
                4062 BINARY_ADD
                4064 STORE_FAST               1 (OVXPEYYWSK)

42069719        4066 LOAD_FAST                1 (OVXPEYYWSK)
                4068 RETURN_VALUE
