42069667           0 LOAD_CONST               1 (True)
                   2 STORE_FAST               1 (CYDTCHDYJM)

42069668           4 LOAD_FAST                1 (CYDTCHDYJM)
                   6 JUMP_IF_FALSE_OR_POP   198
                   8 LOAD_GLOBAL              0 (ord)
                  10 LOAD_FAST                0 (EPGRFNWEUW)
                  12 LOAD_CONST               2 (4)
                  14 BINARY_SUBSCR
                  16 CALL_FUNCTION            1
                  18 LOAD_CONST               3 (128)
                  20 BINARY_AND
                  22 LOAD_CONST               4 (7)
                  24 BINARY_RSHIFT
                  26 LOAD_CONST               5 (0)
                  28 COMPARE_OP               2 (==)
                  30 JUMP_IF_FALSE_OR_POP   198
                  32 LOAD_GLOBAL              0 (ord)
                  34 LOAD_FAST                0 (EPGRFNWEUW)
                  36 LOAD_CONST               2 (4)
                  38 BINARY_SUBSCR
                  40 CALL_FUNCTION            1
                  42 LOAD_CONST               6 (64)
                  44 BINARY_AND
                  46 LOAD_CONST               7 (6)
                  48 BINARY_RSHIFT
                  50 LOAD_CONST               8 (1)
                  52 COMPARE_OP               2 (==)
                  54 JUMP_IF_FALSE_OR_POP   198
                  56 LOAD_GLOBAL              0 (ord)
                  58 LOAD_FAST                0 (EPGRFNWEUW)
                  60 LOAD_CONST               2 (4)
                  62 BINARY_SUBSCR
                  64 CALL_FUNCTION            1
                  66 LOAD_CONST               9 (32)
                  68 BINARY_AND
                  70 LOAD_CONST              10 (5)
                  72 BINARY_RSHIFT
                  74 LOAD_CONST               5 (0)
                  76 COMPARE_OP               2 (==)
                  78 JUMP_IF_FALSE_OR_POP   198
                  80 LOAD_GLOBAL              0 (ord)
                  82 LOAD_FAST                0 (EPGRFNWEUW)
                  84 LOAD_CONST               2 (4)
                  86 BINARY_SUBSCR
                  88 CALL_FUNCTION            1
                  90 LOAD_CONST              11 (16)
                  92 BINARY_AND
                  94 LOAD_CONST               2 (4)
                  96 BINARY_RSHIFT
                  98 LOAD_CONST               8 (1)
                 100 COMPARE_OP               2 (==)
                 102 JUMP_IF_FALSE_OR_POP   198
                 104 LOAD_GLOBAL              0 (ord)
                 106 LOAD_FAST                0 (EPGRFNWEUW)
                 108 LOAD_CONST               2 (4)
                 110 BINARY_SUBSCR
                 112 CALL_FUNCTION            1
                 114 LOAD_CONST              12 (8)
                 116 BINARY_AND
                 118 LOAD_CONST              13 (3)
                 120 BINARY_RSHIFT
                 122 LOAD_CONST               5 (0)
                 124 COMPARE_OP               2 (==)
                 126 JUMP_IF_FALSE_OR_POP   198
                 128 LOAD_GLOBAL              0 (ord)
                 130 LOAD_FAST                0 (EPGRFNWEUW)
                 132 LOAD_CONST               2 (4)
                 134 BINARY_SUBSCR
                 136 CALL_FUNCTION            1
                 138 LOAD_CONST               2 (4)
                 140 BINARY_AND
                 142 LOAD_CONST              14 (2)
                 144 BINARY_RSHIFT
                 146 LOAD_CONST               5 (0)
                 148 COMPARE_OP               2 (==)
                 150 JUMP_IF_FALSE_OR_POP   198
                 152 LOAD_GLOBAL              0 (ord)
                 154 LOAD_FAST                0 (EPGRFNWEUW)
                 156 LOAD_CONST               2 (4)
                 158 BINARY_SUBSCR
                 160 CALL_FUNCTION            1
                 162 LOAD_CONST              14 (2)
                 164 BINARY_AND
                 166 LOAD_CONST               8 (1)
                 168 BINARY_RSHIFT
                 170 LOAD_CONST               8 (1)
                 172 COMPARE_OP               2 (==)
                 174 JUMP_IF_FALSE_OR_POP   198
                 176 LOAD_GLOBAL              0 (ord)
                 178 LOAD_FAST                0 (EPGRFNWEUW)
                 180 LOAD_CONST               2 (4)
                 182 BINARY_SUBSCR
                 184 CALL_FUNCTION            1
                 186 LOAD_CONST               8 (1)
                 188 BINARY_AND
                 190 LOAD_CONST               5 (0)
                 192 BINARY_RSHIFT
                 194 LOAD_CONST               8 (1)
                 196 COMPARE_OP               2 (==)
             >>  198 STORE_FAST               1 (CYDTCHDYJM)

42069669         200 LOAD_FAST                1 (CYDTCHDYJM)
                 202 JUMP_IF_FALSE_OR_POP   250
                 204 LOAD_GLOBAL              0 (ord)
                 206 LOAD_FAST                0 (EPGRFNWEUW)
                 208 LOAD_CONST              15 (33)
                 210 BINARY_SUBSCR
                 212 CALL_FUNCTION            1
                 214 LOAD_CONST              16 (240)
                 216 BINARY_AND
                 218 LOAD_CONST              17 (96)
                 220 BINARY_XOR
                 222 LOAD_CONST               5 (0)
                 224 COMPARE_OP               2 (==)
                 226 JUMP_IF_FALSE_OR_POP   250
                 228 LOAD_GLOBAL              0 (ord)
                 230 LOAD_FAST                0 (EPGRFNWEUW)
                 232 LOAD_CONST              15 (33)
                 234 BINARY_SUBSCR
                 236 CALL_FUNCTION            1
                 238 LOAD_CONST              18 (15)
                 240 BINARY_AND
                 242 LOAD_CONST              14 (2)
                 244 BINARY_XOR
                 246 LOAD_CONST               5 (0)
                 248 COMPARE_OP               2 (==)
             >>  250 STORE_FAST               1 (CYDTCHDYJM)

42069670         252 LOAD_FAST                1 (CYDTCHDYJM)
                 254 EXTENDED_ARG             1
                 256 JUMP_IF_FALSE_OR_POP   272
                 258 LOAD_GLOBAL              0 (ord)
                 260 LOAD_FAST                0 (EPGRFNWEUW)
                 262 LOAD_CONST              19 (12)
                 264 BINARY_SUBSCR
                 266 CALL_FUNCTION            1
                 268 LOAD_CONST              20 (114)
                 270 COMPARE_OP               2 (==)
             >>  272 STORE_FAST               1 (CYDTCHDYJM)

42069671         274 LOAD_FAST                1 (CYDTCHDYJM)
                 276 EXTENDED_ARG             1
                 278 JUMP_IF_FALSE_OR_POP   484
                 280 LOAD_GLOBAL              0 (ord)
                 282 LOAD_FAST                0 (EPGRFNWEUW)
                 284 LOAD_CONST              21 (24)
                 286 BINARY_SUBSCR
                 288 CALL_FUNCTION            1
                 290 LOAD_CONST               3 (128)
                 292 BINARY_AND
                 294 LOAD_CONST               4 (7)
                 296 BINARY_RSHIFT
                 298 LOAD_CONST               5 (0)
                 300 COMPARE_OP               2 (==)
                 302 EXTENDED_ARG             1
                 304 JUMP_IF_FALSE_OR_POP   484
                 306 LOAD_GLOBAL              0 (ord)
                 308 LOAD_FAST                0 (EPGRFNWEUW)
                 310 LOAD_CONST              21 (24)
                 312 BINARY_SUBSCR
                 314 CALL_FUNCTION            1
                 316 LOAD_CONST               6 (64)
                 318 BINARY_AND
                 320 LOAD_CONST               7 (6)
                 322 BINARY_RSHIFT
                 324 LOAD_CONST               8 (1)
                 326 COMPARE_OP               2 (==)
                 328 EXTENDED_ARG             1
                 330 JUMP_IF_FALSE_OR_POP   484
                 332 LOAD_GLOBAL              0 (ord)
                 334 LOAD_FAST                0 (EPGRFNWEUW)
                 336 LOAD_CONST              21 (24)
                 338 BINARY_SUBSCR
                 340 CALL_FUNCTION            1
                 342 LOAD_CONST               9 (32)
                 344 BINARY_AND
                 346 LOAD_CONST              10 (5)
                 348 BINARY_RSHIFT
                 350 LOAD_CONST               8 (1)
                 352 COMPARE_OP               2 (==)
                 354 EXTENDED_ARG             1
                 356 JUMP_IF_FALSE_OR_POP   484
                 358 LOAD_GLOBAL              0 (ord)
                 360 LOAD_FAST                0 (EPGRFNWEUW)
                 362 LOAD_CONST              21 (24)
                 364 BINARY_SUBSCR
                 366 CALL_FUNCTION            1
                 368 LOAD_CONST              11 (16)
                 370 BINARY_AND
                 372 LOAD_CONST               2 (4)
                 374 BINARY_RSHIFT
                 376 LOAD_CONST               5 (0)
                 378 COMPARE_OP               2 (==)
                 380 EXTENDED_ARG             1
                 382 JUMP_IF_FALSE_OR_POP   484
                 384 LOAD_GLOBAL              0 (ord)
                 386 LOAD_FAST                0 (EPGRFNWEUW)
                 388 LOAD_CONST              21 (24)
                 390 BINARY_SUBSCR
                 392 CALL_FUNCTION            1
                 394 LOAD_CONST              12 (8)
                 396 BINARY_AND
                 398 LOAD_CONST              13 (3)
                 400 BINARY_RSHIFT
                 402 LOAD_CONST               8 (1)
                 404 COMPARE_OP               2 (==)
                 406 EXTENDED_ARG             1
                 408 JUMP_IF_FALSE_OR_POP   484
                 410 LOAD_GLOBAL              0 (ord)
                 412 LOAD_FAST                0 (EPGRFNWEUW)
                 414 LOAD_CONST              21 (24)
                 416 BINARY_SUBSCR
                 418 CALL_FUNCTION            1
                 420 LOAD_CONST               2 (4)
                 422 BINARY_AND
                 424 LOAD_CONST              14 (2)
                 426 BINARY_RSHIFT
                 428 LOAD_CONST               8 (1)
                 430 COMPARE_OP               2 (==)
                 432 EXTENDED_ARG             1
                 434 JUMP_IF_FALSE_OR_POP   484
                 436 LOAD_GLOBAL              0 (ord)
                 438 LOAD_FAST                0 (EPGRFNWEUW)
                 440 LOAD_CONST              21 (24)
                 442 BINARY_SUBSCR
                 444 CALL_FUNCTION            1
                 446 LOAD_CONST              14 (2)
                 448 BINARY_AND
                 450 LOAD_CONST               8 (1)
                 452 BINARY_RSHIFT
                 454 LOAD_CONST               5 (0)
                 456 COMPARE_OP               2 (==)
                 458 EXTENDED_ARG             1
                 460 JUMP_IF_FALSE_OR_POP   484
                 462 LOAD_GLOBAL              0 (ord)
                 464 LOAD_FAST                0 (EPGRFNWEUW)
                 466 LOAD_CONST              21 (24)
                 468 BINARY_SUBSCR
                 470 CALL_FUNCTION            1
                 472 LOAD_CONST               8 (1)
                 474 BINARY_AND
                 476 LOAD_CONST               5 (0)
                 478 BINARY_RSHIFT
                 480 LOAD_CONST               8 (1)
                 482 COMPARE_OP               2 (==)
             >>  484 STORE_FAST               1 (CYDTCHDYJM)

42069672         486 LOAD_FAST                1 (CYDTCHDYJM)
                 488 EXTENDED_ARG             1
                 490 JUMP_IF_FALSE_OR_POP   506
                 492 LOAD_GLOBAL              0 (ord)
                 494 LOAD_FAST                0 (EPGRFNWEUW)
                 496 LOAD_CONST              22 (17)
                 498 BINARY_SUBSCR
                 500 CALL_FUNCTION            1
                 502 LOAD_CONST              23 (51)
                 504 COMPARE_OP               2 (==)
             >>  506 STORE_FAST               1 (CYDTCHDYJM)

42069673         508 LOAD_FAST                1 (CYDTCHDYJM)
                 510 EXTENDED_ARG             2
                 512 JUMP_IF_FALSE_OR_POP   718
                 514 LOAD_GLOBAL              0 (ord)
                 516 LOAD_FAST                0 (EPGRFNWEUW)
                 518 LOAD_CONST               9 (32)
                 520 BINARY_SUBSCR
                 522 CALL_FUNCTION            1
                 524 LOAD_CONST               3 (128)
                 526 BINARY_AND
                 528 LOAD_CONST               4 (7)
                 530 BINARY_RSHIFT
                 532 LOAD_CONST               5 (0)
                 534 COMPARE_OP               2 (==)
                 536 EXTENDED_ARG             2
                 538 JUMP_IF_FALSE_OR_POP   718
                 540 LOAD_GLOBAL              0 (ord)
                 542 LOAD_FAST                0 (EPGRFNWEUW)
                 544 LOAD_CONST               9 (32)
                 546 BINARY_SUBSCR
                 548 CALL_FUNCTION            1
                 550 LOAD_CONST               6 (64)
                 552 BINARY_AND
                 554 LOAD_CONST               7 (6)
                 556 BINARY_RSHIFT
                 558 LOAD_CONST               8 (1)
                 560 COMPARE_OP               2 (==)
                 562 EXTENDED_ARG             2
                 564 JUMP_IF_FALSE_OR_POP   718
                 566 LOAD_GLOBAL              0 (ord)
                 568 LOAD_FAST                0 (EPGRFNWEUW)
                 570 LOAD_CONST               9 (32)
                 572 BINARY_SUBSCR
                 574 CALL_FUNCTION            1
                 576 LOAD_CONST               9 (32)
                 578 BINARY_AND
                 580 LOAD_CONST              10 (5)
                 582 BINARY_RSHIFT
                 584 LOAD_CONST               5 (0)
                 586 COMPARE_OP               2 (==)
                 588 EXTENDED_ARG             2
                 590 JUMP_IF_FALSE_OR_POP   718
                 592 LOAD_GLOBAL              0 (ord)
                 594 LOAD_FAST                0 (EPGRFNWEUW)
                 596 LOAD_CONST               9 (32)
                 598 BINARY_SUBSCR
                 600 CALL_FUNCTION            1
                 602 LOAD_CONST              11 (16)
                 604 BINARY_AND
                 606 LOAD_CONST               2 (4)
                 608 BINARY_RSHIFT
                 610 LOAD_CONST               8 (1)
                 612 COMPARE_OP               2 (==)
                 614 EXTENDED_ARG             2
                 616 JUMP_IF_FALSE_OR_POP   718
                 618 LOAD_GLOBAL              0 (ord)
                 620 LOAD_FAST                0 (EPGRFNWEUW)
                 622 LOAD_CONST               9 (32)
                 624 BINARY_SUBSCR
                 626 CALL_FUNCTION            1
                 628 LOAD_CONST              12 (8)
                 630 BINARY_AND
                 632 LOAD_CONST              13 (3)
                 634 BINARY_RSHIFT
                 636 LOAD_CONST               8 (1)
                 638 COMPARE_OP               2 (==)
                 640 EXTENDED_ARG             2
                 642 JUMP_IF_FALSE_OR_POP   718
                 644 LOAD_GLOBAL              0 (ord)
                 646 LOAD_FAST                0 (EPGRFNWEUW)
                 648 LOAD_CONST               9 (32)
                 650 BINARY_SUBSCR
                 652 CALL_FUNCTION            1
                 654 LOAD_CONST               2 (4)
                 656 BINARY_AND
                 658 LOAD_CONST              14 (2)
                 660 BINARY_RSHIFT
                 662 LOAD_CONST               8 (1)
                 664 COMPARE_OP               2 (==)
                 666 EXTENDED_ARG             2
                 668 JUMP_IF_FALSE_OR_POP   718
                 670 LOAD_GLOBAL              0 (ord)
                 672 LOAD_FAST                0 (EPGRFNWEUW)
                 674 LOAD_CONST               9 (32)
                 676 BINARY_SUBSCR
                 678 CALL_FUNCTION            1
                 680 LOAD_CONST              14 (2)
                 682 BINARY_AND
                 684 LOAD_CONST               8 (1)
                 686 BINARY_RSHIFT
                 688 LOAD_CONST               8 (1)
                 690 COMPARE_OP               2 (==)
                 692 EXTENDED_ARG             2
                 694 JUMP_IF_FALSE_OR_POP   718
                 696 LOAD_GLOBAL              0 (ord)
                 698 LOAD_FAST                0 (EPGRFNWEUW)
                 700 LOAD_CONST               9 (32)
                 702 BINARY_SUBSCR
                 704 CALL_FUNCTION            1
                 706 LOAD_CONST               8 (1)
                 708 BINARY_AND
                 710 LOAD_CONST               5 (0)
                 712 BINARY_RSHIFT
                 714 LOAD_CONST               8 (1)
                 716 COMPARE_OP               2 (==)
             >>  718 STORE_FAST               1 (CYDTCHDYJM)

42069674         720 LOAD_FAST                1 (CYDTCHDYJM)
                 722 EXTENDED_ARG             3
                 724 JUMP_IF_FALSE_OR_POP   930
                 726 LOAD_GLOBAL              0 (ord)
                 728 LOAD_FAST                0 (EPGRFNWEUW)
                 730 LOAD_CONST              24 (13)
                 732 BINARY_SUBSCR
                 734 CALL_FUNCTION            1
                 736 LOAD_CONST               3 (128)
                 738 BINARY_AND
                 740 LOAD_CONST               4 (7)
                 742 BINARY_RSHIFT
                 744 LOAD_CONST               5 (0)
                 746 COMPARE_OP               2 (==)
                 748 EXTENDED_ARG             3
                 750 JUMP_IF_FALSE_OR_POP   930
                 752 LOAD_GLOBAL              0 (ord)
                 754 LOAD_FAST                0 (EPGRFNWEUW)
                 756 LOAD_CONST              24 (13)
                 758 BINARY_SUBSCR
                 760 CALL_FUNCTION            1
                 762 LOAD_CONST               6 (64)
                 764 BINARY_AND
                 766 LOAD_CONST               7 (6)
                 768 BINARY_RSHIFT
                 770 LOAD_CONST               8 (1)
                 772 COMPARE_OP               2 (==)
                 774 EXTENDED_ARG             3
                 776 JUMP_IF_FALSE_OR_POP   930
                 778 LOAD_GLOBAL              0 (ord)
                 780 LOAD_FAST                0 (EPGRFNWEUW)
                 782 LOAD_CONST              24 (13)
                 784 BINARY_SUBSCR
                 786 CALL_FUNCTION            1
                 788 LOAD_CONST               9 (32)
                 790 BINARY_AND
                 792 LOAD_CONST              10 (5)
                 794 BINARY_RSHIFT
                 796 LOAD_CONST               8 (1)
                 798 COMPARE_OP               2 (==)
                 800 EXTENDED_ARG             3
                 802 JUMP_IF_FALSE_OR_POP   930
                 804 LOAD_GLOBAL              0 (ord)
                 806 LOAD_FAST                0 (EPGRFNWEUW)
                 808 LOAD_CONST              24 (13)
                 810 BINARY_SUBSCR
                 812 CALL_FUNCTION            1
                 814 LOAD_CONST              11 (16)
                 816 BINARY_AND
                 818 LOAD_CONST               2 (4)
                 820 BINARY_RSHIFT
                 822 LOAD_CONST               5 (0)
                 824 COMPARE_OP               2 (==)
                 826 EXTENDED_ARG             3
                 828 JUMP_IF_FALSE_OR_POP   930
                 830 LOAD_GLOBAL              0 (ord)
                 832 LOAD_FAST                0 (EPGRFNWEUW)
                 834 LOAD_CONST              24 (13)
                 836 BINARY_SUBSCR
                 838 CALL_FUNCTION            1
                 840 LOAD_CONST              12 (8)
                 842 BINARY_AND
                 844 LOAD_CONST              13 (3)
                 846 BINARY_RSHIFT
                 848 LOAD_CONST               8 (1)
                 850 COMPARE_OP               2 (==)
                 852 EXTENDED_ARG             3
                 854 JUMP_IF_FALSE_OR_POP   930
                 856 LOAD_GLOBAL              0 (ord)
                 858 LOAD_FAST                0 (EPGRFNWEUW)
                 860 LOAD_CONST              24 (13)
                 862 BINARY_SUBSCR
                 864 CALL_FUNCTION            1
                 866 LOAD_CONST               2 (4)
                 868 BINARY_AND
                 870 LOAD_CONST              14 (2)
                 872 BINARY_RSHIFT
                 874 LOAD_CONST               8 (1)
                 876 COMPARE_OP               2 (==)
                 878 EXTENDED_ARG             3
                 880 JUMP_IF_FALSE_OR_POP   930
                 882 LOAD_GLOBAL              0 (ord)
                 884 LOAD_FAST                0 (EPGRFNWEUW)
                 886 LOAD_CONST              24 (13)
                 888 BINARY_SUBSCR
                 890 CALL_FUNCTION            1
                 892 LOAD_CONST              14 (2)
                 894 BINARY_AND
                 896 LOAD_CONST               8 (1)
                 898 BINARY_RSHIFT
                 900 LOAD_CONST               8 (1)
                 902 COMPARE_OP               2 (==)
                 904 EXTENDED_ARG             3
                 906 JUMP_IF_FALSE_OR_POP   930
                 908 LOAD_GLOBAL              0 (ord)
                 910 LOAD_FAST                0 (EPGRFNWEUW)
                 912 LOAD_CONST              24 (13)
                 914 BINARY_SUBSCR
                 916 CALL_FUNCTION            1
                 918 LOAD_CONST               8 (1)
                 920 BINARY_AND
                 922 LOAD_CONST               5 (0)
                 924 BINARY_RSHIFT
                 926 LOAD_CONST               5 (0)
                 928 COMPARE_OP               2 (==)
             >>  930 STORE_FAST               1 (CYDTCHDYJM)

42069675         932 LOAD_FAST                1 (CYDTCHDYJM)
                 934 EXTENDED_ARG             3
                 936 JUMP_IF_FALSE_OR_POP   952
                 938 LOAD_GLOBAL              0 (ord)
                 940 LOAD_FAST                0 (EPGRFNWEUW)
                 942 LOAD_CONST              12 (8)
                 944 BINARY_SUBSCR
                 946 CALL_FUNCTION            1
                 948 LOAD_CONST              25 (119)
                 950 COMPARE_OP               2 (==)
             >>  952 STORE_FAST               1 (CYDTCHDYJM)

42069676         954 LOAD_FAST                1 (CYDTCHDYJM)
                 956 EXTENDED_ARG             3
                 958 JUMP_IF_FALSE_OR_POP  1008
                 960 LOAD_GLOBAL              0 (ord)
                 962 LOAD_FAST                0 (EPGRFNWEUW)
                 964 LOAD_CONST              26 (14)
                 966 BINARY_SUBSCR
                 968 CALL_FUNCTION            1
                 970 LOAD_CONST              16 (240)
                 972 BINARY_AND
                 974 LOAD_CONST              17 (96)
                 976 BINARY_XOR
                 978 LOAD_CONST               5 (0)
                 980 COMPARE_OP               2 (==)
                 982 EXTENDED_ARG             3
                 984 JUMP_IF_FALSE_OR_POP  1008
                 986 LOAD_GLOBAL              0 (ord)
                 988 LOAD_FAST                0 (EPGRFNWEUW)
                 990 LOAD_CONST              26 (14)
                 992 BINARY_SUBSCR
                 994 CALL_FUNCTION            1
                 996 LOAD_CONST              18 (15)
                 998 BINARY_AND
                1000 LOAD_CONST              27 (9)
                1002 BINARY_XOR
                1004 LOAD_CONST               5 (0)
                1006 COMPARE_OP               2 (==)
             >> 1008 STORE_FAST               1 (CYDTCHDYJM)

42069677        1010 LOAD_FAST                1 (CYDTCHDYJM)
                1012 EXTENDED_ARG             4
                1014 JUMP_IF_FALSE_OR_POP  1220
                1016 LOAD_GLOBAL              0 (ord)
                1018 LOAD_FAST                0 (EPGRFNWEUW)
                1020 LOAD_CONST              28 (35)
                1022 BINARY_SUBSCR
                1024 CALL_FUNCTION            1
                1026 LOAD_CONST               3 (128)
                1028 BINARY_AND
                1030 LOAD_CONST               4 (7)
                1032 BINARY_RSHIFT
                1034 LOAD_CONST               5 (0)
                1036 COMPARE_OP               2 (==)
                1038 EXTENDED_ARG             4
                1040 JUMP_IF_FALSE_OR_POP  1220
                1042 LOAD_GLOBAL              0 (ord)
                1044 LOAD_FAST                0 (EPGRFNWEUW)
                1046 LOAD_CONST              28 (35)
                1048 BINARY_SUBSCR
                1050 CALL_FUNCTION            1
                1052 LOAD_CONST               6 (64)
                1054 BINARY_AND
                1056 LOAD_CONST               7 (6)
                1058 BINARY_RSHIFT
                1060 LOAD_CONST               8 (1)
                1062 COMPARE_OP               2 (==)
                1064 EXTENDED_ARG             4
                1066 JUMP_IF_FALSE_OR_POP  1220
                1068 LOAD_GLOBAL              0 (ord)
                1070 LOAD_FAST                0 (EPGRFNWEUW)
                1072 LOAD_CONST              28 (35)
                1074 BINARY_SUBSCR
                1076 CALL_FUNCTION            1
                1078 LOAD_CONST               9 (32)
                1080 BINARY_AND
                1082 LOAD_CONST              10 (5)
                1084 BINARY_RSHIFT
                1086 LOAD_CONST               8 (1)
                1088 COMPARE_OP               2 (==)
                1090 EXTENDED_ARG             4
                1092 JUMP_IF_FALSE_OR_POP  1220
                1094 LOAD_GLOBAL              0 (ord)
                1096 LOAD_FAST                0 (EPGRFNWEUW)
                1098 LOAD_CONST              28 (35)
                1100 BINARY_SUBSCR
                1102 CALL_FUNCTION            1
                1104 LOAD_CONST              11 (16)
                1106 BINARY_AND
                1108 LOAD_CONST               2 (4)
                1110 BINARY_RSHIFT
                1112 LOAD_CONST               8 (1)
                1114 COMPARE_OP               2 (==)
                1116 EXTENDED_ARG             4
                1118 JUMP_IF_FALSE_OR_POP  1220
                1120 LOAD_GLOBAL              0 (ord)
                1122 LOAD_FAST                0 (EPGRFNWEUW)
                1124 LOAD_CONST              28 (35)
                1126 BINARY_SUBSCR
                1128 CALL_FUNCTION            1
                1130 LOAD_CONST              12 (8)
                1132 BINARY_AND
                1134 LOAD_CONST              13 (3)
                1136 BINARY_RSHIFT
                1138 LOAD_CONST               5 (0)
                1140 COMPARE_OP               2 (==)
                1142 EXTENDED_ARG             4
                1144 JUMP_IF_FALSE_OR_POP  1220
                1146 LOAD_GLOBAL              0 (ord)
                1148 LOAD_FAST                0 (EPGRFNWEUW)
                1150 LOAD_CONST              28 (35)
                1152 BINARY_SUBSCR
                1154 CALL_FUNCTION            1
                1156 LOAD_CONST               2 (4)
                1158 BINARY_AND
                1160 LOAD_CONST              14 (2)
                1162 BINARY_RSHIFT
                1164 LOAD_CONST               8 (1)
                1166 COMPARE_OP               2 (==)
                1168 EXTENDED_ARG             4
                1170 JUMP_IF_FALSE_OR_POP  1220
                1172 LOAD_GLOBAL              0 (ord)
                1174 LOAD_FAST                0 (EPGRFNWEUW)
                1176 LOAD_CONST              28 (35)
                1178 BINARY_SUBSCR
                1180 CALL_FUNCTION            1
                1182 LOAD_CONST              14 (2)
                1184 BINARY_AND
                1186 LOAD_CONST               8 (1)
                1188 BINARY_RSHIFT
                1190 LOAD_CONST               5 (0)
                1192 COMPARE_OP               2 (==)
                1194 EXTENDED_ARG             4
                1196 JUMP_IF_FALSE_OR_POP  1220
                1198 LOAD_GLOBAL              0 (ord)
                1200 LOAD_FAST                0 (EPGRFNWEUW)
                1202 LOAD_CONST              28 (35)
                1204 BINARY_SUBSCR
                1206 CALL_FUNCTION            1
                1208 LOAD_CONST               8 (1)
                1210 BINARY_AND
                1212 LOAD_CONST               5 (0)
                1214 BINARY_RSHIFT
                1216 LOAD_CONST               5 (0)
                1218 COMPARE_OP               2 (==)
             >> 1220 STORE_FAST               1 (CYDTCHDYJM)

42069678        1222 LOAD_FAST                0 (EPGRFNWEUW)
                1224 LOAD_CONST               0 (None)
                1226 LOAD_CONST              10 (5)
                1228 BUILD_SLICE              2
                1230 BINARY_SUBSCR
                1232 LOAD_CONST              29 ('UMASS')
                1234 COMPARE_OP               3 (!=)
                1236 EXTENDED_ARG             4
                1238 POP_JUMP_IF_FALSE     1246

42069679        1240 LOAD_CONST              30 (False)
                1242 BUILD_LIST               1
                1244 RETURN_VALUE

42069680     >> 1246 LOAD_FAST                1 (CYDTCHDYJM)
                1248 EXTENDED_ARG             4
                1250 JUMP_IF_FALSE_OR_POP  1266
                1252 LOAD_GLOBAL              0 (ord)
                1254 LOAD_FAST                0 (EPGRFNWEUW)
                1256 LOAD_CONST              31 (19)
                1258 BINARY_SUBSCR
                1260 CALL_FUNCTION            1
                1262 LOAD_CONST              32 (99)
                1264 COMPARE_OP               2 (==)
             >> 1266 STORE_FAST               1 (CYDTCHDYJM)

42069681        1268 LOAD_FAST                1 (CYDTCHDYJM)
                1270 EXTENDED_ARG             5
                1272 JUMP_IF_FALSE_OR_POP  1478
                1274 LOAD_GLOBAL              0 (ord)
                1276 LOAD_FAST                0 (EPGRFNWEUW)
                1278 LOAD_CONST              33 (38)
                1280 BINARY_SUBSCR
                1282 CALL_FUNCTION            1
                1284 LOAD_CONST               3 (128)
                1286 BINARY_AND
                1288 LOAD_CONST               4 (7)
                1290 BINARY_RSHIFT
                1292 LOAD_CONST               5 (0)
                1294 COMPARE_OP               2 (==)
                1296 EXTENDED_ARG             5
                1298 JUMP_IF_FALSE_OR_POP  1478
                1300 LOAD_GLOBAL              0 (ord)
                1302 LOAD_FAST                0 (EPGRFNWEUW)
                1304 LOAD_CONST              33 (38)
                1306 BINARY_SUBSCR
                1308 CALL_FUNCTION            1
                1310 LOAD_CONST               6 (64)
                1312 BINARY_AND
                1314 LOAD_CONST               7 (6)
                1316 BINARY_RSHIFT
                1318 LOAD_CONST               5 (0)
                1320 COMPARE_OP               2 (==)
                1322 EXTENDED_ARG             5
                1324 JUMP_IF_FALSE_OR_POP  1478
                1326 LOAD_GLOBAL              0 (ord)
                1328 LOAD_FAST                0 (EPGRFNWEUW)
                1330 LOAD_CONST              33 (38)
                1332 BINARY_SUBSCR
                1334 CALL_FUNCTION            1
                1336 LOAD_CONST               9 (32)
                1338 BINARY_AND
                1340 LOAD_CONST              10 (5)
                1342 BINARY_RSHIFT
                1344 LOAD_CONST               8 (1)
                1346 COMPARE_OP               2 (==)
                1348 EXTENDED_ARG             5
                1350 JUMP_IF_FALSE_OR_POP  1478
                1352 LOAD_GLOBAL              0 (ord)
                1354 LOAD_FAST                0 (EPGRFNWEUW)
                1356 LOAD_CONST              33 (38)
                1358 BINARY_SUBSCR
                1360 CALL_FUNCTION            1
                1362 LOAD_CONST              11 (16)
                1364 BINARY_AND
                1366 LOAD_CONST               2 (4)
                1368 BINARY_RSHIFT
                1370 LOAD_CONST               8 (1)
                1372 COMPARE_OP               2 (==)
                1374 EXTENDED_ARG             5
                1376 JUMP_IF_FALSE_OR_POP  1478
                1378 LOAD_GLOBAL              0 (ord)
                1380 LOAD_FAST                0 (EPGRFNWEUW)
                1382 LOAD_CONST              33 (38)
                1384 BINARY_SUBSCR
                1386 CALL_FUNCTION            1
                1388 LOAD_CONST              12 (8)
                1390 BINARY_AND
                1392 LOAD_CONST              13 (3)
                1394 BINARY_RSHIFT
                1396 LOAD_CONST               5 (0)
                1398 COMPARE_OP               2 (==)
                1400 EXTENDED_ARG             5
                1402 JUMP_IF_FALSE_OR_POP  1478
                1404 LOAD_GLOBAL              0 (ord)
                1406 LOAD_FAST                0 (EPGRFNWEUW)
                1408 LOAD_CONST              33 (38)
                1410 BINARY_SUBSCR
                1412 CALL_FUNCTION            1
                1414 LOAD_CONST               2 (4)
                1416 BINARY_AND
                1418 LOAD_CONST              14 (2)
                1420 BINARY_RSHIFT
                1422 LOAD_CONST               5 (0)
                1424 COMPARE_OP               2 (==)
                1426 EXTENDED_ARG             5
                1428 JUMP_IF_FALSE_OR_POP  1478
                1430 LOAD_GLOBAL              0 (ord)
                1432 LOAD_FAST                0 (EPGRFNWEUW)
                1434 LOAD_CONST              33 (38)
                1436 BINARY_SUBSCR
                1438 CALL_FUNCTION            1
                1440 LOAD_CONST              14 (2)
                1442 BINARY_AND
                1444 LOAD_CONST               8 (1)
                1446 BINARY_RSHIFT
                1448 LOAD_CONST               5 (0)
                1450 COMPARE_OP               2 (==)
                1452 EXTENDED_ARG             5
                1454 JUMP_IF_FALSE_OR_POP  1478
                1456 LOAD_GLOBAL              0 (ord)
                1458 LOAD_FAST                0 (EPGRFNWEUW)
                1460 LOAD_CONST              33 (38)
                1462 BINARY_SUBSCR
                1464 CALL_FUNCTION            1
                1466 LOAD_CONST               8 (1)
                1468 BINARY_AND
                1470 LOAD_CONST               5 (0)
                1472 BINARY_RSHIFT
                1474 LOAD_CONST               5 (0)
                1476 COMPARE_OP               2 (==)
             >> 1478 STORE_FAST               1 (CYDTCHDYJM)

42069682        1480 LOAD_FAST                1 (CYDTCHDYJM)
                1482 EXTENDED_ARG             5
                1484 JUMP_IF_FALSE_OR_POP  1500
                1486 LOAD_GLOBAL              0 (ord)
                1488 LOAD_FAST                0 (EPGRFNWEUW)
                1490 LOAD_CONST              14 (2)
                1492 BINARY_SUBSCR
                1494 CALL_FUNCTION            1
                1496 LOAD_CONST              34 (65)
                1498 COMPARE_OP               2 (==)
             >> 1500 STORE_FAST               1 (CYDTCHDYJM)

42069683        1502 LOAD_FAST                1 (CYDTCHDYJM)
                1504 EXTENDED_ARG             6
                1506 JUMP_IF_FALSE_OR_POP  1712
                1508 LOAD_GLOBAL              0 (ord)
                1510 LOAD_FAST                0 (EPGRFNWEUW)
                1512 LOAD_CONST              35 (21)
                1514 BINARY_SUBSCR
                1516 CALL_FUNCTION            1
                1518 LOAD_CONST               3 (128)
                1520 BINARY_AND
                1522 LOAD_CONST               4 (7)
                1524 BINARY_RSHIFT
                1526 LOAD_CONST               5 (0)
                1528 COMPARE_OP               2 (==)
                1530 EXTENDED_ARG             6
                1532 JUMP_IF_FALSE_OR_POP  1712
                1534 LOAD_GLOBAL              0 (ord)
                1536 LOAD_FAST                0 (EPGRFNWEUW)
                1538 LOAD_CONST              35 (21)
                1540 BINARY_SUBSCR
                1542 CALL_FUNCTION            1
                1544 LOAD_CONST               6 (64)
                1546 BINARY_AND
                1548 LOAD_CONST               7 (6)
                1550 BINARY_RSHIFT
                1552 LOAD_CONST               8 (1)
                1554 COMPARE_OP               2 (==)
                1556 EXTENDED_ARG             6
                1558 JUMP_IF_FALSE_OR_POP  1712
                1560 LOAD_GLOBAL              0 (ord)
                1562 LOAD_FAST                0 (EPGRFNWEUW)
                1564 LOAD_CONST              35 (21)
                1566 BINARY_SUBSCR
                1568 CALL_FUNCTION            1
                1570 LOAD_CONST               9 (32)
                1572 BINARY_AND
                1574 LOAD_CONST              10 (5)
                1576 BINARY_RSHIFT
                1578 LOAD_CONST               8 (1)
                1580 COMPARE_OP               2 (==)
                1582 EXTENDED_ARG             6
                1584 JUMP_IF_FALSE_OR_POP  1712
                1586 LOAD_GLOBAL              0 (ord)
                1588 LOAD_FAST                0 (EPGRFNWEUW)
                1590 LOAD_CONST              35 (21)
                1592 BINARY_SUBSCR
                1594 CALL_FUNCTION            1
                1596 LOAD_CONST              11 (16)
                1598 BINARY_AND
                1600 LOAD_CONST               2 (4)
                1602 BINARY_RSHIFT
                1604 LOAD_CONST               5 (0)
                1606 COMPARE_OP               2 (==)
                1608 EXTENDED_ARG             6
                1610 JUMP_IF_FALSE_OR_POP  1712
                1612 LOAD_GLOBAL              0 (ord)
                1614 LOAD_FAST                0 (EPGRFNWEUW)
                1616 LOAD_CONST              35 (21)
                1618 BINARY_SUBSCR
                1620 CALL_FUNCTION            1
                1622 LOAD_CONST              12 (8)
                1624 BINARY_AND
                1626 LOAD_CONST              13 (3)
                1628 BINARY_RSHIFT
                1630 LOAD_CONST               5 (0)
                1632 COMPARE_OP               2 (==)
                1634 EXTENDED_ARG             6
                1636 JUMP_IF_FALSE_OR_POP  1712
                1638 LOAD_GLOBAL              0 (ord)
                1640 LOAD_FAST                0 (EPGRFNWEUW)
                1642 LOAD_CONST              35 (21)
                1644 BINARY_SUBSCR
                1646 CALL_FUNCTION            1
                1648 LOAD_CONST               2 (4)
                1650 BINARY_AND
                1652 LOAD_CONST              14 (2)
                1654 BINARY_RSHIFT
                1656 LOAD_CONST               8 (1)
                1658 COMPARE_OP               2 (==)
                1660 EXTENDED_ARG             6
                1662 JUMP_IF_FALSE_OR_POP  1712
                1664 LOAD_GLOBAL              0 (ord)
                1666 LOAD_FAST                0 (EPGRFNWEUW)
                1668 LOAD_CONST              35 (21)
                1670 BINARY_SUBSCR
                1672 CALL_FUNCTION            1
                1674 LOAD_CONST              14 (2)
                1676 BINARY_AND
                1678 LOAD_CONST               8 (1)
                1680 BINARY_RSHIFT
                1682 LOAD_CONST               8 (1)
                1684 COMPARE_OP               2 (==)
                1686 EXTENDED_ARG             6
                1688 JUMP_IF_FALSE_OR_POP  1712
                1690 LOAD_GLOBAL              0 (ord)
                1692 LOAD_FAST                0 (EPGRFNWEUW)
                1694 LOAD_CONST              35 (21)
                1696 BINARY_SUBSCR
                1698 CALL_FUNCTION            1
                1700 LOAD_CONST               8 (1)
                1702 BINARY_AND
                1704 LOAD_CONST               5 (0)
                1706 BINARY_RSHIFT
                1708 LOAD_CONST               5 (0)
                1710 COMPARE_OP               2 (==)
             >> 1712 STORE_FAST               1 (CYDTCHDYJM)

42069684        1714 LOAD_FAST                1 (CYDTCHDYJM)
                1716 EXTENDED_ARG             6
                1718 JUMP_IF_FALSE_OR_POP  1768
                1720 LOAD_GLOBAL              0 (ord)
                1722 LOAD_FAST                0 (EPGRFNWEUW)
                1724 LOAD_CONST              36 (11)
                1726 BINARY_SUBSCR
                1728 CALL_FUNCTION            1
                1730 LOAD_CONST              16 (240)
                1732 BINARY_AND
                1734 LOAD_CONST              17 (96)
                1736 BINARY_XOR
                1738 LOAD_CONST               5 (0)
                1740 COMPARE_OP               2 (==)
                1742 EXTENDED_ARG             6
                1744 JUMP_IF_FALSE_OR_POP  1768
                1746 LOAD_GLOBAL              0 (ord)
                1748 LOAD_FAST                0 (EPGRFNWEUW)
                1750 LOAD_CONST              36 (11)
                1752 BINARY_SUBSCR
                1754 CALL_FUNCTION            1
                1756 LOAD_CONST              18 (15)
                1758 BINARY_AND
                1760 LOAD_CONST               8 (1)
                1762 BINARY_XOR
                1764 LOAD_CONST               5 (0)
                1766 COMPARE_OP               2 (==)
             >> 1768 STORE_FAST               1 (CYDTCHDYJM)

42069685        1770 LOAD_FAST                1 (CYDTCHDYJM)
                1772 EXTENDED_ARG             6
                1774 JUMP_IF_FALSE_OR_POP  1790
                1776 LOAD_GLOBAL              0 (ord)
                1778 LOAD_FAST                0 (EPGRFNWEUW)
                1780 LOAD_CONST              37 (39)
                1782 BINARY_SUBSCR
                1784 CALL_FUNCTION            1
                1786 LOAD_CONST              38 (100)
                1788 COMPARE_OP               2 (==)
             >> 1790 STORE_FAST               1 (CYDTCHDYJM)

42069686        1792 LOAD_GLOBAL              0 (ord)
                1794 LOAD_FAST                0 (EPGRFNWEUW)
                1796 LOAD_CONST               5 (0)
                1798 BINARY_SUBSCR
                1800 CALL_FUNCTION            1
                1802 LOAD_CONST              16 (240)
                1804 BINARY_AND
                1806 LOAD_CONST              39 (37)
                1808 COMPARE_OP               2 (==)
                1810 EXTENDED_ARG             7
                1812 POP_JUMP_IF_FALSE     1820

42069687        1814 LOAD_CONST              40 (42)
                1816 STORE_FAST               2 (WJLLYDLVQX)
                1818 JUMP_FORWARD             4 (to 1824)

42069689     >> 1820 LOAD_CONST              41 (36)
                1822 STORE_FAST               2 (WJLLYDLVQX)

42069690     >> 1824 LOAD_FAST                1 (CYDTCHDYJM)
                1826 EXTENDED_ARG             7
                1828 JUMP_IF_FALSE_OR_POP  1844
                1830 LOAD_GLOBAL              0 (ord)
                1832 LOAD_FAST                0 (EPGRFNWEUW)
                1834 LOAD_CONST              42 (34)
                1836 BINARY_SUBSCR
                1838 CALL_FUNCTION            1
                1840 LOAD_CONST              43 (121)
                1842 COMPARE_OP               2 (==)
             >> 1844 STORE_FAST               1 (CYDTCHDYJM)

42069691        1846 LOAD_FAST                1 (CYDTCHDYJM)
                1848 EXTENDED_ARG             7
                1850 JUMP_IF_FALSE_OR_POP  1900
                1852 LOAD_GLOBAL              0 (ord)
                1854 LOAD_FAST                0 (EPGRFNWEUW)
                1856 LOAD_CONST              44 (29)
                1858 BINARY_SUBSCR
                1860 CALL_FUNCTION            1
                1862 LOAD_CONST              16 (240)
                1864 BINARY_AND
                1866 LOAD_CONST              45 (112)
                1868 BINARY_XOR
                1870 LOAD_CONST               5 (0)
                1872 COMPARE_OP               2 (==)
                1874 EXTENDED_ARG             7
                1876 JUMP_IF_FALSE_OR_POP  1900
                1878 LOAD_GLOBAL              0 (ord)
                1880 LOAD_FAST                0 (EPGRFNWEUW)
                1882 LOAD_CONST              44 (29)
                1884 BINARY_SUBSCR
                1886 CALL_FUNCTION            1
                1888 LOAD_CONST              18 (15)
                1890 BINARY_AND
                1892 LOAD_CONST               2 (4)
                1894 BINARY_XOR
                1896 LOAD_CONST               5 (0)
                1898 COMPARE_OP               2 (==)
             >> 1900 STORE_FAST               1 (CYDTCHDYJM)

42069692        1902 LOAD_FAST                1 (CYDTCHDYJM)
                1904 EXTENDED_ARG             7
                1906 JUMP_IF_FALSE_OR_POP  1922
                1908 LOAD_GLOBAL              0 (ord)
                1910 LOAD_FAST                0 (EPGRFNWEUW)
                1912 LOAD_CONST              46 (20)
                1914 BINARY_SUBSCR
                1916 CALL_FUNCTION            1
                1918 LOAD_CONST              47 (116)
                1920 COMPARE_OP               2 (==)
             >> 1922 STORE_FAST               1 (CYDTCHDYJM)

42069693        1924 LOAD_FAST                1 (CYDTCHDYJM)
                1926 EXTENDED_ARG             8
                1928 JUMP_IF_FALSE_OR_POP  2134
                1930 LOAD_GLOBAL              0 (ord)
                1932 LOAD_FAST                0 (EPGRFNWEUW)
                1934 LOAD_CONST               8 (1)
                1936 BINARY_SUBSCR
                1938 CALL_FUNCTION            1
                1940 LOAD_CONST               3 (128)
                1942 BINARY_AND
                1944 LOAD_CONST               4 (7)
                1946 BINARY_RSHIFT
                1948 LOAD_CONST               5 (0)
                1950 COMPARE_OP               2 (==)
                1952 EXTENDED_ARG             8
                1954 JUMP_IF_FALSE_OR_POP  2134
                1956 LOAD_GLOBAL              0 (ord)
                1958 LOAD_FAST                0 (EPGRFNWEUW)
                1960 LOAD_CONST               8 (1)
                1962 BINARY_SUBSCR
                1964 CALL_FUNCTION            1
                1966 LOAD_CONST               6 (64)
                1968 BINARY_AND
                1970 LOAD_CONST               7 (6)
                1972 BINARY_RSHIFT
                1974 LOAD_CONST               8 (1)
                1976 COMPARE_OP               2 (==)
                1978 EXTENDED_ARG             8
                1980 JUMP_IF_FALSE_OR_POP  2134
                1982 LOAD_GLOBAL              0 (ord)
                1984 LOAD_FAST                0 (EPGRFNWEUW)
                1986 LOAD_CONST               8 (1)
                1988 BINARY_SUBSCR
                1990 CALL_FUNCTION            1
                1992 LOAD_CONST               9 (32)
                1994 BINARY_AND
                1996 LOAD_CONST              10 (5)
                1998 BINARY_RSHIFT
                2000 LOAD_CONST               5 (0)
                2002 COMPARE_OP               2 (==)
                2004 EXTENDED_ARG             8
                2006 JUMP_IF_FALSE_OR_POP  2134
                2008 LOAD_GLOBAL              0 (ord)
                2010 LOAD_FAST                0 (EPGRFNWEUW)
                2012 LOAD_CONST               8 (1)
                2014 BINARY_SUBSCR
                2016 CALL_FUNCTION            1
                2018 LOAD_CONST              11 (16)
                2020 BINARY_AND
                2022 LOAD_CONST               2 (4)
                2024 BINARY_RSHIFT
                2026 LOAD_CONST               5 (0)
                2028 COMPARE_OP               2 (==)
                2030 EXTENDED_ARG             8
                2032 JUMP_IF_FALSE_OR_POP  2134
                2034 LOAD_GLOBAL              0 (ord)
                2036 LOAD_FAST                0 (EPGRFNWEUW)
                2038 LOAD_CONST               8 (1)
                2040 BINARY_SUBSCR
                2042 CALL_FUNCTION            1
                2044 LOAD_CONST              12 (8)
                2046 BINARY_AND
                2048 LOAD_CONST              13 (3)
                2050 BINARY_RSHIFT
                2052 LOAD_CONST               8 (1)
                2054 COMPARE_OP               2 (==)
                2056 EXTENDED_ARG             8
                2058 JUMP_IF_FALSE_OR_POP  2134
                2060 LOAD_GLOBAL              0 (ord)
                2062 LOAD_FAST                0 (EPGRFNWEUW)
                2064 LOAD_CONST               8 (1)
                2066 BINARY_SUBSCR
                2068 CALL_FUNCTION            1
                2070 LOAD_CONST               2 (4)
                2072 BINARY_AND
                2074 LOAD_CONST              14 (2)
                2076 BINARY_RSHIFT
                2078 LOAD_CONST               8 (1)
                2080 COMPARE_OP               2 (==)
                2082 EXTENDED_ARG             8
                2084 JUMP_IF_FALSE_OR_POP  2134
                2086 LOAD_GLOBAL              0 (ord)
                2088 LOAD_FAST                0 (EPGRFNWEUW)
                2090 LOAD_CONST               8 (1)
                2092 BINARY_SUBSCR
                2094 CALL_FUNCTION            1
                2096 LOAD_CONST              14 (2)
                2098 BINARY_AND
                2100 LOAD_CONST               8 (1)
                2102 BINARY_RSHIFT
                2104 LOAD_CONST               5 (0)
                2106 COMPARE_OP               2 (==)
                2108 EXTENDED_ARG             8
                2110 JUMP_IF_FALSE_OR_POP  2134
                2112 LOAD_GLOBAL              0 (ord)
                2114 LOAD_FAST                0 (EPGRFNWEUW)
                2116 LOAD_CONST               8 (1)
                2118 BINARY_SUBSCR
                2120 CALL_FUNCTION            1
                2122 LOAD_CONST               8 (1)
                2124 BINARY_AND
                2126 LOAD_CONST               5 (0)
                2128 BINARY_RSHIFT
                2130 LOAD_CONST               8 (1)
                2132 COMPARE_OP               2 (==)
             >> 2134 STORE_FAST               1 (CYDTCHDYJM)

42069694        2136 LOAD_FAST                1 (CYDTCHDYJM)
                2138 EXTENDED_ARG             9
                2140 JUMP_IF_FALSE_OR_POP  2346
                2142 LOAD_GLOBAL              0 (ord)
                2144 LOAD_FAST                0 (EPGRFNWEUW)
                2146 LOAD_CONST              27 (9)
                2148 BINARY_SUBSCR
                2150 CALL_FUNCTION            1
                2152 LOAD_CONST               3 (128)
                2154 BINARY_AND
                2156 LOAD_CONST               4 (7)
                2158 BINARY_RSHIFT
                2160 LOAD_CONST               5 (0)
                2162 COMPARE_OP               2 (==)
                2164 EXTENDED_ARG             9
                2166 JUMP_IF_FALSE_OR_POP  2346
                2168 LOAD_GLOBAL              0 (ord)
                2170 LOAD_FAST                0 (EPGRFNWEUW)
                2172 LOAD_CONST              27 (9)
                2174 BINARY_SUBSCR
                2176 CALL_FUNCTION            1
                2178 LOAD_CONST               6 (64)
                2180 BINARY_AND
                2182 LOAD_CONST               7 (6)
                2184 BINARY_RSHIFT
                2186 LOAD_CONST               8 (1)
                2188 COMPARE_OP               2 (==)
                2190 EXTENDED_ARG             9
                2192 JUMP_IF_FALSE_OR_POP  2346
                2194 LOAD_GLOBAL              0 (ord)
                2196 LOAD_FAST                0 (EPGRFNWEUW)
                2198 LOAD_CONST              27 (9)
                2200 BINARY_SUBSCR
                2202 CALL_FUNCTION            1
                2204 LOAD_CONST               9 (32)
                2206 BINARY_AND
                2208 LOAD_CONST              10 (5)
                2210 BINARY_RSHIFT
                2212 LOAD_CONST               5 (0)
                2214 COMPARE_OP               2 (==)
                2216 EXTENDED_ARG             9
                2218 JUMP_IF_FALSE_OR_POP  2346
                2220 LOAD_GLOBAL              0 (ord)
                2222 LOAD_FAST                0 (EPGRFNWEUW)
                2224 LOAD_CONST              27 (9)
                2226 BINARY_SUBSCR
                2228 CALL_FUNCTION            1
                2230 LOAD_CONST              11 (16)
                2232 BINARY_AND
                2234 LOAD_CONST               2 (4)
                2236 BINARY_RSHIFT
                2238 LOAD_CONST               8 (1)
                2240 COMPARE_OP               2 (==)
                2242 EXTENDED_ARG             9
                2244 JUMP_IF_FALSE_OR_POP  2346
                2246 LOAD_GLOBAL              0 (ord)
                2248 LOAD_FAST                0 (EPGRFNWEUW)
                2250 LOAD_CONST              27 (9)
                2252 BINARY_SUBSCR
                2254 CALL_FUNCTION            1
                2256 LOAD_CONST              12 (8)
                2258 BINARY_AND
                2260 LOAD_CONST              13 (3)
                2262 BINARY_RSHIFT
                2264 LOAD_CONST               8 (1)
                2266 COMPARE_OP               2 (==)
                2268 EXTENDED_ARG             9
                2270 JUMP_IF_FALSE_OR_POP  2346
                2272 LOAD_GLOBAL              0 (ord)
                2274 LOAD_FAST                0 (EPGRFNWEUW)
                2276 LOAD_CONST              27 (9)
                2278 BINARY_SUBSCR
                2280 CALL_FUNCTION            1
                2282 LOAD_CONST               2 (4)
                2284 BINARY_AND
                2286 LOAD_CONST              14 (2)
                2288 BINARY_RSHIFT
                2290 LOAD_CONST               8 (1)
                2292 COMPARE_OP               2 (==)
                2294 EXTENDED_ARG             9
                2296 JUMP_IF_FALSE_OR_POP  2346
                2298 LOAD_GLOBAL              0 (ord)
                2300 LOAD_FAST                0 (EPGRFNWEUW)
                2302 LOAD_CONST              27 (9)
                2304 BINARY_SUBSCR
                2306 CALL_FUNCTION            1
                2308 LOAD_CONST              14 (2)
                2310 BINARY_AND
                2312 LOAD_CONST               8 (1)
                2314 BINARY_RSHIFT
                2316 LOAD_CONST               8 (1)
                2318 COMPARE_OP               2 (==)
                2320 EXTENDED_ARG             9
                2322 JUMP_IF_FALSE_OR_POP  2346
                2324 LOAD_GLOBAL              0 (ord)
                2326 LOAD_FAST                0 (EPGRFNWEUW)
                2328 LOAD_CONST              27 (9)
                2330 BINARY_SUBSCR
                2332 CALL_FUNCTION            1
                2334 LOAD_CONST               8 (1)
                2336 BINARY_AND
                2338 LOAD_CONST               5 (0)
                2340 BINARY_RSHIFT
                2342 LOAD_CONST               8 (1)
                2344 COMPARE_OP               2 (==)
             >> 2346 STORE_FAST               1 (CYDTCHDYJM)

42069695        2348 LOAD_GLOBAL              0 (ord)
                2350 LOAD_CONST              48 ('L')
                2352 CALL_FUNCTION            1
                2354 LOAD_GLOBAL              0 (ord)
                2356 LOAD_FAST                0 (EPGRFNWEUW)
                2358 LOAD_CONST               5 (0)
                2360 BINARY_SUBSCR
                2362 CALL_FUNCTION            1
                2364 BINARY_XOR
                2366 STORE_FAST               3 (ECIOZNQGST)

42069696        2368 LOAD_FAST                1 (CYDTCHDYJM)
                2370 EXTENDED_ARG             9
                2372 JUMP_IF_FALSE_OR_POP  2388
                2374 LOAD_GLOBAL              0 (ord)
                2376 LOAD_FAST                0 (EPGRFNWEUW)
                2378 LOAD_CONST               5 (0)
                2380 BINARY_SUBSCR
                2382 CALL_FUNCTION            1
                2384 LOAD_CONST              49 (85)
                2386 COMPARE_OP               2 (==)
             >> 2388 STORE_FAST               1 (CYDTCHDYJM)

42069697        2390 LOAD_FAST                0 (EPGRFNWEUW)
                2392 LOAD_CONST               0 (None)
                2394 LOAD_CONST              10 (5)
                2396 BUILD_SLICE              2
                2398 BINARY_SUBSCR
                2400 LOAD_CONST              29 ('UMASS')
                2402 COMPARE_OP               3 (!=)
                2404 EXTENDED_ARG             9
                2406 POP_JUMP_IF_FALSE     2414

42069698        2408 LOAD_CONST              30 (False)
                2410 BUILD_LIST               1
                2412 RETURN_VALUE

42069699     >> 2414 LOAD_FAST                1 (CYDTCHDYJM)
                2416 EXTENDED_ARG             9
                2418 JUMP_IF_FALSE_OR_POP  2434
                2420 LOAD_GLOBAL              0 (ord)
                2422 LOAD_FAST                0 (EPGRFNWEUW)
                2424 LOAD_CONST              50 (30)
                2426 BINARY_SUBSCR
                2428 CALL_FUNCTION            1
                2430 LOAD_CONST              23 (51)
                2432 COMPARE_OP               2 (==)
             >> 2434 STORE_FAST               1 (CYDTCHDYJM)

42069700        2436 LOAD_GLOBAL              0 (ord)
                2438 LOAD_FAST                0 (EPGRFNWEUW)
                2440 LOAD_CONST               5 (0)
                2442 BINARY_SUBSCR
                2444 CALL_FUNCTION            1
                2446 LOAD_CONST              16 (240)
                2448 BINARY_AND
                2450 LOAD_CONST              50 (30)
                2452 COMPARE_OP               2 (==)
                2454 EXTENDED_ARG             9
                2456 POP_JUMP_IF_FALSE     2464

42069701        2458 LOAD_CONST              51 (23)
                2460 STORE_FAST               2 (WJLLYDLVQX)
                2462 JUMP_FORWARD             4 (to 2468)

42069703     >> 2464 LOAD_CONST              52 (63)
                2466 STORE_FAST               2 (WJLLYDLVQX)

42069704     >> 2468 LOAD_FAST                1 (CYDTCHDYJM)
                2470 EXTENDED_ARG             9
                2472 JUMP_IF_FALSE_OR_POP  2522
                2474 LOAD_GLOBAL              0 (ord)
                2476 LOAD_FAST                0 (EPGRFNWEUW)
                2478 LOAD_CONST              13 (3)
                2480 BINARY_SUBSCR
                2482 CALL_FUNCTION            1
                2484 LOAD_CONST              16 (240)
                2486 BINARY_AND
                2488 LOAD_CONST              53 (80)
                2490 BINARY_XOR
                2492 LOAD_CONST               5 (0)
                2494 COMPARE_OP               2 (==)
                2496 EXTENDED_ARG             9
                2498 JUMP_IF_FALSE_OR_POP  2522
                2500 LOAD_GLOBAL              0 (ord)
                2502 LOAD_FAST                0 (EPGRFNWEUW)
                2504 LOAD_CONST              13 (3)
                2506 BINARY_SUBSCR
                2508 CALL_FUNCTION            1
                2510 LOAD_CONST              18 (15)
                2512 BINARY_AND
                2514 LOAD_CONST              13 (3)
                2516 BINARY_XOR
                2518 LOAD_CONST               5 (0)
                2520 COMPARE_OP               2 (==)
             >> 2522 STORE_FAST               1 (CYDTCHDYJM)

42069705        2524 LOAD_FAST                1 (CYDTCHDYJM)
                2526 EXTENDED_ARG             9
                2528 JUMP_IF_FALSE_OR_POP  2544
                2530 LOAD_GLOBAL              0 (ord)
                2532 LOAD_FAST                0 (EPGRFNWEUW)
                2534 LOAD_CONST               4 (7)
                2536 BINARY_SUBSCR
                2538 CALL_FUNCTION            1
                2540 LOAD_CONST              54 (48)
                2542 COMPARE_OP               2 (==)
             >> 2544 STORE_FAST               1 (CYDTCHDYJM)

42069706        2546 LOAD_FAST                1 (CYDTCHDYJM)
                2548 EXTENDED_ARG            10
                2550 JUMP_IF_FALSE_OR_POP  2756
                2552 LOAD_GLOBAL              0 (ord)
                2554 LOAD_FAST                0 (EPGRFNWEUW)
                2556 LOAD_CONST              55 (41)
                2558 BINARY_SUBSCR
                2560 CALL_FUNCTION            1
                2562 LOAD_CONST               3 (128)
                2564 BINARY_AND
                2566 LOAD_CONST               4 (7)
                2568 BINARY_RSHIFT
                2570 LOAD_CONST               5 (0)
                2572 COMPARE_OP               2 (==)
                2574 EXTENDED_ARG            10
                2576 JUMP_IF_FALSE_OR_POP  2756
                2578 LOAD_GLOBAL              0 (ord)
                2580 LOAD_FAST                0 (EPGRFNWEUW)
                2582 LOAD_CONST              55 (41)
                2584 BINARY_SUBSCR
                2586 CALL_FUNCTION            1
                2588 LOAD_CONST               6 (64)
                2590 BINARY_AND
                2592 LOAD_CONST               7 (6)
                2594 BINARY_RSHIFT
                2596 LOAD_CONST               8 (1)
                2598 COMPARE_OP               2 (==)
                2600 EXTENDED_ARG            10
                2602 JUMP_IF_FALSE_OR_POP  2756
                2604 LOAD_GLOBAL              0 (ord)
                2606 LOAD_FAST                0 (EPGRFNWEUW)
                2608 LOAD_CONST              55 (41)
                2610 BINARY_SUBSCR
                2612 CALL_FUNCTION            1
                2614 LOAD_CONST               9 (32)
                2616 BINARY_AND
                2618 LOAD_CONST              10 (5)
                2620 BINARY_RSHIFT
                2622 LOAD_CONST               8 (1)
                2624 COMPARE_OP               2 (==)
                2626 EXTENDED_ARG            10
                2628 JUMP_IF_FALSE_OR_POP  2756
                2630 LOAD_GLOBAL              0 (ord)
                2632 LOAD_FAST                0 (EPGRFNWEUW)
                2634 LOAD_CONST              55 (41)
                2636 BINARY_SUBSCR
                2638 CALL_FUNCTION            1
                2640 LOAD_CONST              11 (16)
                2642 BINARY_AND
                2644 LOAD_CONST               2 (4)
                2646 BINARY_RSHIFT
                2648 LOAD_CONST               8 (1)
                2650 COMPARE_OP               2 (==)
                2652 EXTENDED_ARG            10
                2654 JUMP_IF_FALSE_OR_POP  2756
                2656 LOAD_GLOBAL              0 (ord)
                2658 LOAD_FAST                0 (EPGRFNWEUW)
                2660 LOAD_CONST              55 (41)
                2662 BINARY_SUBSCR
                2664 CALL_FUNCTION            1
                2666 LOAD_CONST              12 (8)
                2668 BINARY_AND
                2670 LOAD_CONST              13 (3)
                2672 BINARY_RSHIFT
                2674 LOAD_CONST               8 (1)
                2676 COMPARE_OP               2 (==)
                2678 EXTENDED_ARG            10
                2680 JUMP_IF_FALSE_OR_POP  2756
                2682 LOAD_GLOBAL              0 (ord)
                2684 LOAD_FAST                0 (EPGRFNWEUW)
                2686 LOAD_CONST              55 (41)
                2688 BINARY_SUBSCR
                2690 CALL_FUNCTION            1
                2692 LOAD_CONST               2 (4)
                2694 BINARY_AND
                2696 LOAD_CONST              14 (2)
                2698 BINARY_RSHIFT
                2700 LOAD_CONST               8 (1)
                2702 COMPARE_OP               2 (==)
                2704 EXTENDED_ARG            10
                2706 JUMP_IF_FALSE_OR_POP  2756
                2708 LOAD_GLOBAL              0 (ord)
                2710 LOAD_FAST                0 (EPGRFNWEUW)
                2712 LOAD_CONST              55 (41)
                2714 BINARY_SUBSCR
                2716 CALL_FUNCTION            1
                2718 LOAD_CONST              14 (2)
                2720 BINARY_AND
                2722 LOAD_CONST               8 (1)
                2724 BINARY_RSHIFT
                2726 LOAD_CONST               5 (0)
                2728 COMPARE_OP               2 (==)
                2730 EXTENDED_ARG            10
                2732 JUMP_IF_FALSE_OR_POP  2756
                2734 LOAD_GLOBAL              0 (ord)
                2736 LOAD_FAST                0 (EPGRFNWEUW)
                2738 LOAD_CONST              55 (41)
                2740 BINARY_SUBSCR
                2742 CALL_FUNCTION            1
                2744 LOAD_CONST               8 (1)
                2746 BINARY_AND
                2748 LOAD_CONST               5 (0)
                2750 BINARY_RSHIFT
                2752 LOAD_CONST               8 (1)
                2754 COMPARE_OP               2 (==)
             >> 2756 STORE_FAST               1 (CYDTCHDYJM)

42069707        2758 LOAD_GLOBAL              1 (len)
                2760 LOAD_FAST                0 (EPGRFNWEUW)
                2762 CALL_FUNCTION            1
                2764 STORE_FAST               2 (WJLLYDLVQX)

42069708        2766 LOAD_FAST                1 (CYDTCHDYJM)
                2768 EXTENDED_ARG            11
                2770 JUMP_IF_FALSE_OR_POP  2820
                2772 LOAD_GLOBAL              0 (ord)
                2774 LOAD_FAST                0 (EPGRFNWEUW)
                2776 LOAD_CONST              56 (31)
                2778 BINARY_SUBSCR
                2780 CALL_FUNCTION            1
                2782 LOAD_CONST              16 (240)
                2784 BINARY_AND
                2786 LOAD_CONST              45 (112)
                2788 BINARY_XOR
                2790 LOAD_CONST               5 (0)
                2792 COMPARE_OP               2 (==)
                2794 EXTENDED_ARG            11
                2796 JUMP_IF_FALSE_OR_POP  2820
                2798 LOAD_GLOBAL              0 (ord)
                2800 LOAD_FAST                0 (EPGRFNWEUW)
                2802 LOAD_CONST              56 (31)
                2804 BINARY_SUBSCR
                2806 CALL_FUNCTION            1
                2808 LOAD_CONST              18 (15)
                2810 BINARY_AND
                2812 LOAD_CONST              14 (2)
                2814 BINARY_XOR
                2816 LOAD_CONST               5 (0)
                2818 COMPARE_OP               2 (==)
             >> 2820 STORE_FAST               1 (CYDTCHDYJM)

42069709        2822 LOAD_FAST                1 (CYDTCHDYJM)
                2824 EXTENDED_ARG            11
                2826 JUMP_IF_FALSE_OR_POP  2842
                2828 LOAD_GLOBAL              0 (ord)
                2830 LOAD_FAST                0 (EPGRFNWEUW)
                2832 LOAD_CONST              57 (25)
                2834 BINARY_SUBSCR
                2836 CALL_FUNCTION            1
                2838 LOAD_CONST              23 (51)
                2840 COMPARE_OP               2 (==)
             >> 2842 STORE_FAST               1 (CYDTCHDYJM)

42069710        2844 LOAD_FAST                0 (EPGRFNWEUW)
                2846 LOAD_CONST               0 (None)
                2848 LOAD_CONST              10 (5)
                2850 BUILD_SLICE              2
                2852 BINARY_SUBSCR
                2854 LOAD_CONST              29 ('UMASS')
                2856 COMPARE_OP               3 (!=)
                2858 EXTENDED_ARG            11
                2860 POP_JUMP_IF_FALSE     2868

42069711        2862 LOAD_CONST              30 (False)
                2864 BUILD_LIST               1
                2866 RETURN_VALUE

42069712     >> 2868 LOAD_FAST                1 (CYDTCHDYJM)
                2870 EXTENDED_ARG            12
                2872 JUMP_IF_FALSE_OR_POP  3078
                2874 LOAD_GLOBAL              0 (ord)
                2876 LOAD_FAST                0 (EPGRFNWEUW)
                2878 LOAD_CONST              18 (15)
                2880 BINARY_SUBSCR
                2882 CALL_FUNCTION            1
                2884 LOAD_CONST               3 (128)
                2886 BINARY_AND
                2888 LOAD_CONST               4 (7)
                2890 BINARY_RSHIFT
                2892 LOAD_CONST               5 (0)
                2894 COMPARE_OP               2 (==)
                2896 EXTENDED_ARG            12
                2898 JUMP_IF_FALSE_OR_POP  3078
                2900 LOAD_GLOBAL              0 (ord)
                2902 LOAD_FAST                0 (EPGRFNWEUW)
                2904 LOAD_CONST              18 (15)
                2906 BINARY_SUBSCR
                2908 CALL_FUNCTION            1
                2910 LOAD_CONST               6 (64)
                2912 BINARY_AND
                2914 LOAD_CONST               7 (6)
                2916 BINARY_RSHIFT
                2918 LOAD_CONST               8 (1)
                2920 COMPARE_OP               2 (==)
                2922 EXTENDED_ARG            12
                2924 JUMP_IF_FALSE_OR_POP  3078
                2926 LOAD_GLOBAL              0 (ord)
                2928 LOAD_FAST                0 (EPGRFNWEUW)
                2930 LOAD_CONST              18 (15)
                2932 BINARY_SUBSCR
                2934 CALL_FUNCTION            1
                2936 LOAD_CONST               9 (32)
                2938 BINARY_AND
                2940 LOAD_CONST              10 (5)
                2942 BINARY_RSHIFT
                2944 LOAD_CONST               8 (1)
                2946 COMPARE_OP               2 (==)
                2948 EXTENDED_ARG            12
                2950 JUMP_IF_FALSE_OR_POP  3078
                2952 LOAD_GLOBAL              0 (ord)
                2954 LOAD_FAST                0 (EPGRFNWEUW)
                2956 LOAD_CONST              18 (15)
                2958 BINARY_SUBSCR
                2960 CALL_FUNCTION            1
                2962 LOAD_CONST              11 (16)
                2964 BINARY_AND
                2966 LOAD_CONST               2 (4)
                2968 BINARY_RSHIFT
                2970 LOAD_CONST               8 (1)
                2972 COMPARE_OP               2 (==)
                2974 EXTENDED_ARG            12
                2976 JUMP_IF_FALSE_OR_POP  3078
                2978 LOAD_GLOBAL              0 (ord)
                2980 LOAD_FAST                0 (EPGRFNWEUW)
                2982 LOAD_CONST              18 (15)
                2984 BINARY_SUBSCR
                2986 CALL_FUNCTION            1
                2988 LOAD_CONST              12 (8)
                2990 BINARY_AND
                2992 LOAD_CONST              13 (3)
                2994 BINARY_RSHIFT
                2996 LOAD_CONST               5 (0)
                2998 COMPARE_OP               2 (==)
                3000 EXTENDED_ARG            12
                3002 JUMP_IF_FALSE_OR_POP  3078
                3004 LOAD_GLOBAL              0 (ord)
                3006 LOAD_FAST                0 (EPGRFNWEUW)
                3008 LOAD_CONST              18 (15)
                3010 BINARY_SUBSCR
                3012 CALL_FUNCTION            1
                3014 LOAD_CONST               2 (4)
                3016 BINARY_AND
                3018 LOAD_CONST              14 (2)
                3020 BINARY_RSHIFT
                3022 LOAD_CONST               5 (0)
                3024 COMPARE_OP               2 (==)
                3026 EXTENDED_ARG            12
                3028 JUMP_IF_FALSE_OR_POP  3078
                3030 LOAD_GLOBAL              0 (ord)
                3032 LOAD_FAST                0 (EPGRFNWEUW)
                3034 LOAD_CONST              18 (15)
                3036 BINARY_SUBSCR
                3038 CALL_FUNCTION            1
                3040 LOAD_CONST              14 (2)
                3042 BINARY_AND
                3044 LOAD_CONST               8 (1)
                3046 BINARY_RSHIFT
                3048 LOAD_CONST               5 (0)
                3050 COMPARE_OP               2 (==)
                3052 EXTENDED_ARG            12
                3054 JUMP_IF_FALSE_OR_POP  3078
                3056 LOAD_GLOBAL              0 (ord)
                3058 LOAD_FAST                0 (EPGRFNWEUW)
                3060 LOAD_CONST              18 (15)
                3062 BINARY_SUBSCR
                3064 CALL_FUNCTION            1
                3066 LOAD_CONST               8 (1)
                3068 BINARY_AND
                3070 LOAD_CONST               5 (0)
                3072 BINARY_RSHIFT
                3074 LOAD_CONST               8 (1)
                3076 COMPARE_OP               2 (==)
             >> 3078 STORE_FAST               1 (CYDTCHDYJM)

42069713        3080 LOAD_FAST                1 (CYDTCHDYJM)
                3082 EXTENDED_ARG            12
                3084 JUMP_IF_FALSE_OR_POP  3290
                3086 LOAD_GLOBAL              0 (ord)
                3088 LOAD_FAST                0 (EPGRFNWEUW)
                3090 LOAD_CONST               7 (6)
                3092 BINARY_SUBSCR
                3094 CALL_FUNCTION            1
                3096 LOAD_CONST               3 (128)
                3098 BINARY_AND
                3100 LOAD_CONST               4 (7)
                3102 BINARY_RSHIFT
                3104 LOAD_CONST               5 (0)
                3106 COMPARE_OP               2 (==)
                3108 EXTENDED_ARG            12
                3110 JUMP_IF_FALSE_OR_POP  3290
                3112 LOAD_GLOBAL              0 (ord)
                3114 LOAD_FAST                0 (EPGRFNWEUW)
                3116 LOAD_CONST               7 (6)
                3118 BINARY_SUBSCR
                3120 CALL_FUNCTION            1
                3122 LOAD_CONST               6 (64)
                3124 BINARY_AND
                3126 LOAD_CONST               7 (6)
                3128 BINARY_RSHIFT
                3130 LOAD_CONST               8 (1)
                3132 COMPARE_OP               2 (==)
                3134 EXTENDED_ARG            12
                3136 JUMP_IF_FALSE_OR_POP  3290
                3138 LOAD_GLOBAL              0 (ord)
                3140 LOAD_FAST                0 (EPGRFNWEUW)
                3142 LOAD_CONST               7 (6)
                3144 BINARY_SUBSCR
                3146 CALL_FUNCTION            1
                3148 LOAD_CONST               9 (32)
                3150 BINARY_AND
                3152 LOAD_CONST              10 (5)
                3154 BINARY_RSHIFT
                3156 LOAD_CONST               8 (1)
                3158 COMPARE_OP               2 (==)
                3160 EXTENDED_ARG            12
                3162 JUMP_IF_FALSE_OR_POP  3290
                3164 LOAD_GLOBAL              0 (ord)
                3166 LOAD_FAST                0 (EPGRFNWEUW)
                3168 LOAD_CONST               7 (6)
                3170 BINARY_SUBSCR
                3172 CALL_FUNCTION            1
                3174 LOAD_CONST              11 (16)
                3176 BINARY_AND
                3178 LOAD_CONST               2 (4)
                3180 BINARY_RSHIFT
                3182 LOAD_CONST               5 (0)
                3184 COMPARE_OP               2 (==)
                3186 EXTENDED_ARG            12
                3188 JUMP_IF_FALSE_OR_POP  3290
                3190 LOAD_GLOBAL              0 (ord)
                3192 LOAD_FAST                0 (EPGRFNWEUW)
                3194 LOAD_CONST               7 (6)
                3196 BINARY_SUBSCR
                3198 CALL_FUNCTION            1
                3200 LOAD_CONST              12 (8)
                3202 BINARY_AND
                3204 LOAD_CONST              13 (3)
                3206 BINARY_RSHIFT
                3208 LOAD_CONST               5 (0)
                3210 COMPARE_OP               2 (==)
                3212 EXTENDED_ARG            12
                3214 JUMP_IF_FALSE_OR_POP  3290
                3216 LOAD_GLOBAL              0 (ord)
                3218 LOAD_FAST                0 (EPGRFNWEUW)
                3220 LOAD_CONST               7 (6)
                3222 BINARY_SUBSCR
                3224 CALL_FUNCTION            1
                3226 LOAD_CONST               2 (4)
                3228 BINARY_AND
                3230 LOAD_CONST              14 (2)
                3232 BINARY_RSHIFT
                3234 LOAD_CONST               5 (0)
                3236 COMPARE_OP               2 (==)
                3238 EXTENDED_ARG            12
                3240 JUMP_IF_FALSE_OR_POP  3290
                3242 LOAD_GLOBAL              0 (ord)
                3244 LOAD_FAST                0 (EPGRFNWEUW)
                3246 LOAD_CONST               7 (6)
                3248 BINARY_SUBSCR
                3250 CALL_FUNCTION            1
                3252 LOAD_CONST              14 (2)
                3254 BINARY_AND
                3256 LOAD_CONST               8 (1)
                3258 BINARY_RSHIFT
                3260 LOAD_CONST               8 (1)
                3262 COMPARE_OP               2 (==)
                3264 EXTENDED_ARG            12
                3266 JUMP_IF_FALSE_OR_POP  3290
                3268 LOAD_GLOBAL              0 (ord)
                3270 LOAD_FAST                0 (EPGRFNWEUW)
                3272 LOAD_CONST               7 (6)
                3274 BINARY_SUBSCR
                3276 CALL_FUNCTION            1
                3278 LOAD_CONST               8 (1)
                3280 BINARY_AND
                3282 LOAD_CONST               5 (0)
                3284 BINARY_RSHIFT
                3286 LOAD_CONST               8 (1)
                3288 COMPARE_OP               2 (==)
             >> 3290 STORE_FAST               1 (CYDTCHDYJM)

42069714        3292 LOAD_FAST                1 (CYDTCHDYJM)
                3294 EXTENDED_ARG            12
                3296 JUMP_IF_FALSE_OR_POP  3312
                3298 LOAD_GLOBAL              0 (ord)
                3300 LOAD_FAST                0 (EPGRFNWEUW)
                3302 LOAD_CONST              58 (26)
                3304 BINARY_SUBSCR
                3306 CALL_FUNCTION            1
                3308 LOAD_CONST              59 (95)
                3310 COMPARE_OP               2 (==)
             >> 3312 STORE_FAST               1 (CYDTCHDYJM)

42069715        3314 LOAD_FAST                1 (CYDTCHDYJM)
                3316 EXTENDED_ARG            13
                3318 JUMP_IF_FALSE_OR_POP  3524
                3320 LOAD_GLOBAL              0 (ord)
                3322 LOAD_FAST                0 (EPGRFNWEUW)
                3324 LOAD_CONST              11 (16)
                3326 BINARY_SUBSCR
                3328 CALL_FUNCTION            1
                3330 LOAD_CONST               3 (128)
                3332 BINARY_AND
                3334 LOAD_CONST               4 (7)
                3336 BINARY_RSHIFT
                3338 LOAD_CONST               5 (0)
                3340 COMPARE_OP               2 (==)
                3342 EXTENDED_ARG            13
                3344 JUMP_IF_FALSE_OR_POP  3524
                3346 LOAD_GLOBAL              0 (ord)
                3348 LOAD_FAST                0 (EPGRFNWEUW)
                3350 LOAD_CONST              11 (16)
                3352 BINARY_SUBSCR
                3354 CALL_FUNCTION            1
                3356 LOAD_CONST               6 (64)
                3358 BINARY_AND
                3360 LOAD_CONST               7 (6)
                3362 BINARY_RSHIFT
                3364 LOAD_CONST               8 (1)
                3366 COMPARE_OP               2 (==)
                3368 EXTENDED_ARG            13
                3370 JUMP_IF_FALSE_OR_POP  3524
                3372 LOAD_GLOBAL              0 (ord)
                3374 LOAD_FAST                0 (EPGRFNWEUW)
                3376 LOAD_CONST              11 (16)
                3378 BINARY_SUBSCR
                3380 CALL_FUNCTION            1
                3382 LOAD_CONST               9 (32)
                3384 BINARY_AND
                3386 LOAD_CONST              10 (5)
                3388 BINARY_RSHIFT
                3390 LOAD_CONST               8 (1)
                3392 COMPARE_OP               2 (==)
                3394 EXTENDED_ARG            13
                3396 JUMP_IF_FALSE_OR_POP  3524
                3398 LOAD_GLOBAL              0 (ord)
                3400 LOAD_FAST                0 (EPGRFNWEUW)
                3402 LOAD_CONST              11 (16)
                3404 BINARY_SUBSCR
                3406 CALL_FUNCTION            1
                3408 LOAD_CONST              11 (16)
                3410 BINARY_AND
                3412 LOAD_CONST               2 (4)
                3414 BINARY_RSHIFT
                3416 LOAD_CONST               8 (1)
                3418 COMPARE_OP               2 (==)
                3420 EXTENDED_ARG            13
                3422 JUMP_IF_FALSE_OR_POP  3524
                3424 LOAD_GLOBAL              0 (ord)
                3426 LOAD_FAST                0 (EPGRFNWEUW)
                3428 LOAD_CONST              11 (16)
                3430 BINARY_SUBSCR
                3432 CALL_FUNCTION            1
                3434 LOAD_CONST              12 (8)
                3436 BINARY_AND
                3438 LOAD_CONST              13 (3)
                3440 BINARY_RSHIFT
                3442 LOAD_CONST               5 (0)
                3444 COMPARE_OP               2 (==)
                3446 EXTENDED_ARG            13
                3448 JUMP_IF_FALSE_OR_POP  3524
                3450 LOAD_GLOBAL              0 (ord)
                3452 LOAD_FAST                0 (EPGRFNWEUW)
                3454 LOAD_CONST              11 (16)
                3456 BINARY_SUBSCR
                3458 CALL_FUNCTION            1
                3460 LOAD_CONST               2 (4)
                3462 BINARY_AND
                3464 LOAD_CONST              14 (2)
                3466 BINARY_RSHIFT
                3468 LOAD_CONST               8 (1)
                3470 COMPARE_OP               2 (==)
                3472 EXTENDED_ARG            13
                3474 JUMP_IF_FALSE_OR_POP  3524
                3476 LOAD_GLOBAL              0 (ord)
                3478 LOAD_FAST                0 (EPGRFNWEUW)
                3480 LOAD_CONST              11 (16)
                3482 BINARY_SUBSCR
                3484 CALL_FUNCTION            1
                3486 LOAD_CONST              14 (2)
                3488 BINARY_AND
                3490 LOAD_CONST               8 (1)
                3492 BINARY_RSHIFT
                3494 LOAD_CONST               5 (0)
                3496 COMPARE_OP               2 (==)
                3498 EXTENDED_ARG            13
                3500 JUMP_IF_FALSE_OR_POP  3524
                3502 LOAD_GLOBAL              0 (ord)
                3504 LOAD_FAST                0 (EPGRFNWEUW)
                3506 LOAD_CONST              11 (16)
                3508 BINARY_SUBSCR
                3510 CALL_FUNCTION            1
                3512 LOAD_CONST               8 (1)
                3514 BINARY_AND
                3516 LOAD_CONST               5 (0)
                3518 BINARY_RSHIFT
                3520 LOAD_CONST               8 (1)
                3522 COMPARE_OP               2 (==)
             >> 3524 STORE_FAST               1 (CYDTCHDYJM)

42069716        3526 LOAD_FAST                1 (CYDTCHDYJM)
                3528 EXTENDED_ARG            13
                3530 JUMP_IF_FALSE_OR_POP  3580
                3532 LOAD_GLOBAL              0 (ord)
                3534 LOAD_FAST                0 (EPGRFNWEUW)
                3536 LOAD_CONST              60 (18)
                3538 BINARY_SUBSCR
                3540 CALL_FUNCTION            1
                3542 LOAD_CONST              16 (240)
                3544 BINARY_AND
                3546 LOAD_CONST              53 (80)
                3548 BINARY_XOR
                3550 LOAD_CONST               5 (0)
                3552 COMPARE_OP               2 (==)
                3554 EXTENDED_ARG            13
                3556 JUMP_IF_FALSE_OR_POP  3580
                3558 LOAD_GLOBAL              0 (ord)
                3560 LOAD_FAST                0 (EPGRFNWEUW)
                3562 LOAD_CONST              60 (18)
                3564 BINARY_SUBSCR
                3566 CALL_FUNCTION            1
                3568 LOAD_CONST              18 (15)
                3570 BINARY_AND
                3572 LOAD_CONST              18 (15)
                3574 BINARY_XOR
                3576 LOAD_CONST               5 (0)
                3578 COMPARE_OP               2 (==)
             >> 3580 STORE_FAST               1 (CYDTCHDYJM)

42069717        3582 LOAD_FAST                1 (CYDTCHDYJM)
                3584 EXTENDED_ARG            14
                3586 JUMP_IF_FALSE_OR_POP  3792
                3588 LOAD_GLOBAL              0 (ord)
                3590 LOAD_FAST                0 (EPGRFNWEUW)
                3592 LOAD_CONST              61 (22)
                3594 BINARY_SUBSCR
                3596 CALL_FUNCTION            1
                3598 LOAD_CONST               3 (128)
                3600 BINARY_AND
                3602 LOAD_CONST               4 (7)
                3604 BINARY_RSHIFT
                3606 LOAD_CONST               5 (0)
                3608 COMPARE_OP               2 (==)
                3610 EXTENDED_ARG            14
                3612 JUMP_IF_FALSE_OR_POP  3792
                3614 LOAD_GLOBAL              0 (ord)
                3616 LOAD_FAST                0 (EPGRFNWEUW)
                3618 LOAD_CONST              61 (22)
                3620 BINARY_SUBSCR
                3622 CALL_FUNCTION            1
                3624 LOAD_CONST               6 (64)
                3626 BINARY_AND
                3628 LOAD_CONST               7 (6)
                3630 BINARY_RSHIFT
                3632 LOAD_CONST               8 (1)
                3634 COMPARE_OP               2 (==)
                3636 EXTENDED_ARG            14
                3638 JUMP_IF_FALSE_OR_POP  3792
                3640 LOAD_GLOBAL              0 (ord)
                3642 LOAD_FAST                0 (EPGRFNWEUW)
                3644 LOAD_CONST              61 (22)
                3646 BINARY_SUBSCR
                3648 CALL_FUNCTION            1
                3650 LOAD_CONST               9 (32)
                3652 BINARY_AND
                3654 LOAD_CONST              10 (5)
                3656 BINARY_RSHIFT
                3658 LOAD_CONST               8 (1)
                3660 COMPARE_OP               2 (==)
                3662 EXTENDED_ARG            14
                3664 JUMP_IF_FALSE_OR_POP  3792
                3666 LOAD_GLOBAL              0 (ord)
                3668 LOAD_FAST                0 (EPGRFNWEUW)
                3670 LOAD_CONST              61 (22)
                3672 BINARY_SUBSCR
                3674 CALL_FUNCTION            1
                3676 LOAD_CONST              11 (16)
                3678 BINARY_AND
                3680 LOAD_CONST               2 (4)
                3682 BINARY_RSHIFT
                3684 LOAD_CONST               8 (1)
                3686 COMPARE_OP               2 (==)
                3688 EXTENDED_ARG            14
                3690 JUMP_IF_FALSE_OR_POP  3792
                3692 LOAD_GLOBAL              0 (ord)
                3694 LOAD_FAST                0 (EPGRFNWEUW)
                3696 LOAD_CONST              61 (22)
                3698 BINARY_SUBSCR
                3700 CALL_FUNCTION            1
                3702 LOAD_CONST              12 (8)
                3704 BINARY_AND
                3706 LOAD_CONST              13 (3)
                3708 BINARY_RSHIFT
                3710 LOAD_CONST               5 (0)
                3712 COMPARE_OP               2 (==)
                3714 EXTENDED_ARG            14
                3716 JUMP_IF_FALSE_OR_POP  3792
                3718 LOAD_GLOBAL              0 (ord)
                3720 LOAD_FAST                0 (EPGRFNWEUW)
                3722 LOAD_CONST              61 (22)
                3724 BINARY_SUBSCR
                3726 CALL_FUNCTION            1
                3728 LOAD_CONST               2 (4)
                3730 BINARY_AND
                3732 LOAD_CONST              14 (2)
                3734 BINARY_RSHIFT
                3736 LOAD_CONST               8 (1)
                3738 COMPARE_OP               2 (==)
                3740 EXTENDED_ARG            14
                3742 JUMP_IF_FALSE_OR_POP  3792
                3744 LOAD_GLOBAL              0 (ord)
                3746 LOAD_FAST                0 (EPGRFNWEUW)
                3748 LOAD_CONST              61 (22)
                3750 BINARY_SUBSCR
                3752 CALL_FUNCTION            1
                3754 LOAD_CONST              14 (2)
                3756 BINARY_AND
                3758 LOAD_CONST               8 (1)
                3760 BINARY_RSHIFT
                3762 LOAD_CONST               5 (0)
                3764 COMPARE_OP               2 (==)
                3766 EXTENDED_ARG            14
                3768 JUMP_IF_FALSE_OR_POP  3792
                3770 LOAD_GLOBAL              0 (ord)
                3772 LOAD_FAST                0 (EPGRFNWEUW)
                3774 LOAD_CONST              61 (22)
                3776 BINARY_SUBSCR
                3778 CALL_FUNCTION            1
                3780 LOAD_CONST               8 (1)
                3782 BINARY_AND
                3784 LOAD_CONST               5 (0)
                3786 BINARY_RSHIFT
                3788 LOAD_CONST               5 (0)
                3790 COMPARE_OP               2 (==)
             >> 3792 STORE_FAST               1 (CYDTCHDYJM)

42069718        3794 LOAD_GLOBAL              2 (copy)
                3796 LOAD_METHOD              2 (copy)
                3798 LOAD_FAST                0 (EPGRFNWEUW)
                3800 CALL_METHOD              1
                3802 POP_TOP

42069719        3804 LOAD_GLOBAL              0 (ord)
                3806 LOAD_FAST                0 (EPGRFNWEUW)
                3808 LOAD_CONST               5 (0)
                3810 BINARY_SUBSCR
                3812 CALL_FUNCTION            1
                3814 LOAD_CONST              16 (240)
                3816 BINARY_AND
                3818 LOAD_CONST              42 (34)
                3820 COMPARE_OP               2 (==)
                3822 EXTENDED_ARG            14
                3824 POP_JUMP_IF_FALSE     3832

42069720        3826 LOAD_CONST              50 (30)
                3828 STORE_FAST               2 (WJLLYDLVQX)
                3830 JUMP_FORWARD             4 (to 3836)

42069722     >> 3832 LOAD_CONST              62 (40)
                3834 STORE_FAST               2 (WJLLYDLVQX)

42069723     >> 3836 LOAD_FAST                1 (CYDTCHDYJM)
                3838 EXTENDED_ARG            15
                3840 JUMP_IF_FALSE_OR_POP  4046
                3842 LOAD_GLOBAL              0 (ord)
                3844 LOAD_FAST                0 (EPGRFNWEUW)
                3846 LOAD_CONST              62 (40)
                3848 BINARY_SUBSCR
                3850 CALL_FUNCTION            1
                3852 LOAD_CONST               3 (128)
                3854 BINARY_AND
                3856 LOAD_CONST               4 (7)
                3858 BINARY_RSHIFT
                3860 LOAD_CONST               5 (0)
                3862 COMPARE_OP               2 (==)
                3864 EXTENDED_ARG            15
                3866 JUMP_IF_FALSE_OR_POP  4046
                3868 LOAD_GLOBAL              0 (ord)
                3870 LOAD_FAST                0 (EPGRFNWEUW)
                3872 LOAD_CONST              62 (40)
                3874 BINARY_SUBSCR
                3876 CALL_FUNCTION            1
                3878 LOAD_CONST               6 (64)
                3880 BINARY_AND
                3882 LOAD_CONST               7 (6)
                3884 BINARY_RSHIFT
                3886 LOAD_CONST               5 (0)
                3888 COMPARE_OP               2 (==)
                3890 EXTENDED_ARG            15
                3892 JUMP_IF_FALSE_OR_POP  4046
                3894 LOAD_GLOBAL              0 (ord)
                3896 LOAD_FAST                0 (EPGRFNWEUW)
                3898 LOAD_CONST              62 (40)
                3900 BINARY_SUBSCR
                3902 CALL_FUNCTION            1
                3904 LOAD_CONST               9 (32)
                3906 BINARY_AND
                3908 LOAD_CONST              10 (5)
                3910 BINARY_RSHIFT
                3912 LOAD_CONST               8 (1)
                3914 COMPARE_OP               2 (==)
                3916 EXTENDED_ARG            15
                3918 JUMP_IF_FALSE_OR_POP  4046
                3920 LOAD_GLOBAL              0 (ord)
                3922 LOAD_FAST                0 (EPGRFNWEUW)
                3924 LOAD_CONST              62 (40)
                3926 BINARY_SUBSCR
                3928 CALL_FUNCTION            1
                3930 LOAD_CONST              11 (16)
                3932 BINARY_AND
                3934 LOAD_CONST               2 (4)
                3936 BINARY_RSHIFT
                3938 LOAD_CONST               8 (1)
                3940 COMPARE_OP               2 (==)
                3942 EXTENDED_ARG            15
                3944 JUMP_IF_FALSE_OR_POP  4046
                3946 LOAD_GLOBAL              0 (ord)
                3948 LOAD_FAST                0 (EPGRFNWEUW)
                3950 LOAD_CONST              62 (40)
                3952 BINARY_SUBSCR
                3954 CALL_FUNCTION            1
                3956 LOAD_CONST              12 (8)
                3958 BINARY_AND
                3960 LOAD_CONST              13 (3)
                3962 BINARY_RSHIFT
                3964 LOAD_CONST               5 (0)
                3966 COMPARE_OP               2 (==)
                3968 EXTENDED_ARG            15
                3970 JUMP_IF_FALSE_OR_POP  4046
                3972 LOAD_GLOBAL              0 (ord)
                3974 LOAD_FAST                0 (EPGRFNWEUW)
                3976 LOAD_CONST              62 (40)
                3978 BINARY_SUBSCR
                3980 CALL_FUNCTION            1
                3982 LOAD_CONST               2 (4)
                3984 BINARY_AND
                3986 LOAD_CONST              14 (2)
                3988 BINARY_RSHIFT
                3990 LOAD_CONST               5 (0)
                3992 COMPARE_OP               2 (==)
                3994 EXTENDED_ARG            15
                3996 JUMP_IF_FALSE_OR_POP  4046
                3998 LOAD_GLOBAL              0 (ord)
                4000 LOAD_FAST                0 (EPGRFNWEUW)
                4002 LOAD_CONST              62 (40)
                4004 BINARY_SUBSCR
                4006 CALL_FUNCTION            1
                4008 LOAD_CONST              14 (2)
                4010 BINARY_AND
                4012 LOAD_CONST               8 (1)
                4014 BINARY_RSHIFT
                4016 LOAD_CONST               8 (1)
                4018 COMPARE_OP               2 (==)
                4020 EXTENDED_ARG            15
                4022 JUMP_IF_FALSE_OR_POP  4046
                4024 LOAD_GLOBAL              0 (ord)
                4026 LOAD_FAST                0 (EPGRFNWEUW)
                4028 LOAD_CONST              62 (40)
                4030 BINARY_SUBSCR
                4032 CALL_FUNCTION            1
                4034 LOAD_CONST               8 (1)
                4036 BINARY_AND
                4038 LOAD_CONST               5 (0)
                4040 BINARY_RSHIFT
                4042 LOAD_CONST               8 (1)
                4044 COMPARE_OP               2 (==)
             >> 4046 STORE_FAST               1 (CYDTCHDYJM)

42069724        4048 LOAD_FAST                1 (CYDTCHDYJM)
                4050 EXTENDED_ARG            15
                4052 JUMP_IF_FALSE_OR_POP  4068
                4054 LOAD_GLOBAL              0 (ord)
                4056 LOAD_FAST                0 (EPGRFNWEUW)
                4058 LOAD_CONST              63 (28)
                4060 BINARY_SUBSCR
                4062 CALL_FUNCTION            1
                4064 LOAD_CONST              64 (97)
                4066 COMPARE_OP               2 (==)
             >> 4068 STORE_FAST               1 (CYDTCHDYJM)

42069725        4070 LOAD_FAST                1 (CYDTCHDYJM)
                4072 EXTENDED_ARG            15
                4074 JUMP_IF_FALSE_OR_POP  4090
                4076 LOAD_GLOBAL              0 (ord)
                4078 LOAD_FAST                0 (EPGRFNWEUW)
                4080 LOAD_CONST              10 (5)
                4082 BINARY_SUBSCR
                4084 CALL_FUNCTION            1
                4086 LOAD_CONST              65 (123)
                4088 COMPARE_OP               2 (==)
             >> 4090 STORE_FAST               1 (CYDTCHDYJM)

42069726        4092 LOAD_FAST                1 (CYDTCHDYJM)
                4094 EXTENDED_ARG            16
                4096 JUMP_IF_FALSE_OR_POP  4112
                4098 LOAD_GLOBAL              0 (ord)
                4100 LOAD_FAST                0 (EPGRFNWEUW)
                4102 LOAD_CONST              66 (10)
                4104 BINARY_SUBSCR
                4106 CALL_FUNCTION            1
                4108 LOAD_CONST              67 (115)
                4110 COMPARE_OP               2 (==)
             >> 4112 STORE_FAST               1 (CYDTCHDYJM)

42069727        4114 LOAD_GLOBAL              2 (copy)
                4116 LOAD_METHOD              2 (copy)
                4118 LOAD_FAST                0 (EPGRFNWEUW)
                4120 CALL_METHOD              1
                4122 POP_TOP

42069728        4124 LOAD_FAST                1 (CYDTCHDYJM)
                4126 EXTENDED_ARG            16
                4128 JUMP_IF_FALSE_OR_POP  4144
                4130 LOAD_GLOBAL              0 (ord)
                4132 LOAD_FAST                0 (EPGRFNWEUW)
                4134 LOAD_CONST              51 (23)
                4136 BINARY_SUBSCR
                4138 CALL_FUNCTION            1
                4140 LOAD_CONST              68 (105)
                4142 COMPARE_OP               2 (==)
             >> 4144 STORE_FAST               1 (CYDTCHDYJM)

42069729        4146 LOAD_CONST              69 (27)
                4148 STORE_FAST               2 (WJLLYDLVQX)

42069730        4150 LOAD_FAST                1 (CYDTCHDYJM)
                4152 EXTENDED_ARG            16
                4154 JUMP_IF_FALSE_OR_POP  4170
                4156 LOAD_GLOBAL              0 (ord)
                4158 LOAD_FAST                0 (EPGRFNWEUW)
                4160 LOAD_CONST              39 (37)
                4162 BINARY_SUBSCR
                4164 CALL_FUNCTION            1
                4166 LOAD_CONST              32 (99)
                4168 COMPARE_OP               2 (==)
             >> 4170 STORE_FAST               1 (CYDTCHDYJM)

42069731        4172 LOAD_FAST                1 (CYDTCHDYJM)
                4174 EXTENDED_ARG            17
                4176 JUMP_IF_FALSE_OR_POP  4382
                4178 LOAD_GLOBAL              0 (ord)
                4180 LOAD_FAST                0 (EPGRFNWEUW)
                4182 LOAD_CONST              41 (36)
                4184 BINARY_SUBSCR
                4186 CALL_FUNCTION            1
                4188 LOAD_CONST               3 (128)
                4190 BINARY_AND
                4192 LOAD_CONST               4 (7)
                4194 BINARY_RSHIFT
                4196 LOAD_CONST               5 (0)
                4198 COMPARE_OP               2 (==)
                4200 EXTENDED_ARG            17
                4202 JUMP_IF_FALSE_OR_POP  4382
                4204 LOAD_GLOBAL              0 (ord)
                4206 LOAD_FAST                0 (EPGRFNWEUW)
                4208 LOAD_CONST              41 (36)
                4210 BINARY_SUBSCR
                4212 CALL_FUNCTION            1
                4214 LOAD_CONST               6 (64)
                4216 BINARY_AND
                4218 LOAD_CONST               7 (6)
                4220 BINARY_RSHIFT
                4222 LOAD_CONST               5 (0)
                4224 COMPARE_OP               2 (==)
                4226 EXTENDED_ARG            17
                4228 JUMP_IF_FALSE_OR_POP  4382
                4230 LOAD_GLOBAL              0 (ord)
                4232 LOAD_FAST                0 (EPGRFNWEUW)
                4234 LOAD_CONST              41 (36)
                4236 BINARY_SUBSCR
                4238 CALL_FUNCTION            1
                4240 LOAD_CONST               9 (32)
                4242 BINARY_AND
                4244 LOAD_CONST              10 (5)
                4246 BINARY_RSHIFT
                4248 LOAD_CONST               8 (1)
                4250 COMPARE_OP               2 (==)
                4252 EXTENDED_ARG            17
                4254 JUMP_IF_FALSE_OR_POP  4382
                4256 LOAD_GLOBAL              0 (ord)
                4258 LOAD_FAST                0 (EPGRFNWEUW)
                4260 LOAD_CONST              41 (36)
                4262 BINARY_SUBSCR
                4264 CALL_FUNCTION            1
                4266 LOAD_CONST              11 (16)
                4268 BINARY_AND
                4270 LOAD_CONST               2 (4)
                4272 BINARY_RSHIFT
                4274 LOAD_CONST               8 (1)
                4276 COMPARE_OP               2 (==)
                4278 EXTENDED_ARG            17
                4280 JUMP_IF_FALSE_OR_POP  4382
                4282 LOAD_GLOBAL              0 (ord)
                4284 LOAD_FAST                0 (EPGRFNWEUW)
                4286 LOAD_CONST              41 (36)
                4288 BINARY_SUBSCR
                4290 CALL_FUNCTION            1
                4292 LOAD_CONST              12 (8)
                4294 BINARY_AND
                4296 LOAD_CONST              13 (3)
                4298 BINARY_RSHIFT
                4300 LOAD_CONST               5 (0)
                4302 COMPARE_OP               2 (==)
                4304 EXTENDED_ARG            17
                4306 JUMP_IF_FALSE_OR_POP  4382
                4308 LOAD_GLOBAL              0 (ord)
                4310 LOAD_FAST                0 (EPGRFNWEUW)
                4312 LOAD_CONST              41 (36)
                4314 BINARY_SUBSCR
                4316 CALL_FUNCTION            1
                4318 LOAD_CONST               2 (4)
                4320 BINARY_AND
                4322 LOAD_CONST              14 (2)
                4324 BINARY_RSHIFT
                4326 LOAD_CONST               5 (0)
                4328 COMPARE_OP               2 (==)
                4330 EXTENDED_ARG            17
                4332 JUMP_IF_FALSE_OR_POP  4382
                4334 LOAD_GLOBAL              0 (ord)
                4336 LOAD_FAST                0 (EPGRFNWEUW)
                4338 LOAD_CONST              41 (36)
                4340 BINARY_SUBSCR
                4342 CALL_FUNCTION            1
                4344 LOAD_CONST              14 (2)
                4346 BINARY_AND
                4348 LOAD_CONST               8 (1)
                4350 BINARY_RSHIFT
                4352 LOAD_CONST               8 (1)
                4354 COMPARE_OP               2 (==)
                4356 EXTENDED_ARG            17
                4358 JUMP_IF_FALSE_OR_POP  4382
                4360 LOAD_GLOBAL              0 (ord)
                4362 LOAD_FAST                0 (EPGRFNWEUW)
                4364 LOAD_CONST              41 (36)
                4366 BINARY_SUBSCR
                4368 CALL_FUNCTION            1
                4370 LOAD_CONST               8 (1)
                4372 BINARY_AND
                4374 LOAD_CONST               5 (0)
                4376 BINARY_RSHIFT
                4378 LOAD_CONST               8 (1)
                4380 COMPARE_OP               2 (==)
             >> 4382 STORE_FAST               1 (CYDTCHDYJM)

42069732        4384 LOAD_FAST                1 (CYDTCHDYJM)
                4386 EXTENDED_ARG            17
                4388 JUMP_IF_FALSE_OR_POP  4404
                4390 LOAD_GLOBAL              0 (ord)
                4392 LOAD_FAST                0 (EPGRFNWEUW)
                4394 LOAD_CONST              69 (27)
                4396 BINARY_SUBSCR
                4398 CALL_FUNCTION            1
                4400 LOAD_CONST              25 (119)
                4402 COMPARE_OP               2 (==)
             >> 4404 STORE_FAST               1 (CYDTCHDYJM)

42069733        4406 LOAD_FAST                1 (CYDTCHDYJM)
                4408 BUILD_LIST               1
                4410 STORE_FAST               1 (CYDTCHDYJM)

42069734        4412 LOAD_GLOBAL              3 (LXNQKJIZEUZPFAQFDWIY)
                4414 LOAD_FAST                0 (EPGRFNWEUW)
                4416 CALL_FUNCTION            1
                4418 LOAD_FAST                1 (CYDTCHDYJM)
                4420 BINARY_ADD
                4422 STORE_FAST               1 (CYDTCHDYJM)

42069735        4424 LOAD_FAST                1 (CYDTCHDYJM)
                4426 RETURN_VALUE
