42069667           0 LOAD_CONST               1 (True)
                   2 STORE_FAST               1 (BJYLPQQYPV)

42069668           4 LOAD_FAST                1 (BJYLPQQYPV)
                   6 JUMP_IF_FALSE_OR_POP   198
                   8 LOAD_GLOBAL              0 (ord)
                  10 LOAD_FAST                0 (NYYZYQYFTG)
                  12 LOAD_CONST               2 (19)
                  14 BINARY_SUBSCR
                  16 CALL_FUNCTION            1
                  18 LOAD_CONST               3 (128)
                  20 BINARY_AND
                  22 LOAD_CONST               4 (7)
                  24 BINARY_RSHIFT
                  26 LOAD_CONST               5 (0)
                  28 COMPARE_OP               2 (==)
                  30 JUMP_IF_FALSE_OR_POP   198
                  32 LOAD_GLOBAL              0 (ord)
                  34 LOAD_FAST                0 (NYYZYQYFTG)
                  36 LOAD_CONST               2 (19)
                  38 BINARY_SUBSCR
                  40 CALL_FUNCTION            1
                  42 LOAD_CONST               6 (64)
                  44 BINARY_AND
                  46 LOAD_CONST               7 (6)
                  48 BINARY_RSHIFT
                  50 LOAD_CONST               8 (1)
                  52 COMPARE_OP               2 (==)
                  54 JUMP_IF_FALSE_OR_POP   198
                  56 LOAD_GLOBAL              0 (ord)
                  58 LOAD_FAST                0 (NYYZYQYFTG)
                  60 LOAD_CONST               2 (19)
                  62 BINARY_SUBSCR
                  64 CALL_FUNCTION            1
                  66 LOAD_CONST               9 (32)
                  68 BINARY_AND
                  70 LOAD_CONST              10 (5)
                  72 BINARY_RSHIFT
                  74 LOAD_CONST               5 (0)
                  76 COMPARE_OP               2 (==)
                  78 JUMP_IF_FALSE_OR_POP   198
                  80 LOAD_GLOBAL              0 (ord)
                  82 LOAD_FAST                0 (NYYZYQYFTG)
                  84 LOAD_CONST               2 (19)
                  86 BINARY_SUBSCR
                  88 CALL_FUNCTION            1
                  90 LOAD_CONST              11 (16)
                  92 BINARY_AND
                  94 LOAD_CONST              12 (4)
                  96 BINARY_RSHIFT
                  98 LOAD_CONST               8 (1)
                 100 COMPARE_OP               2 (==)
                 102 JUMP_IF_FALSE_OR_POP   198
                 104 LOAD_GLOBAL              0 (ord)
                 106 LOAD_FAST                0 (NYYZYQYFTG)
                 108 LOAD_CONST               2 (19)
                 110 BINARY_SUBSCR
                 112 CALL_FUNCTION            1
                 114 LOAD_CONST              13 (8)
                 116 BINARY_AND
                 118 LOAD_CONST              14 (3)
                 120 BINARY_RSHIFT
                 122 LOAD_CONST               8 (1)
                 124 COMPARE_OP               2 (==)
                 126 JUMP_IF_FALSE_OR_POP   198
                 128 LOAD_GLOBAL              0 (ord)
                 130 LOAD_FAST                0 (NYYZYQYFTG)
                 132 LOAD_CONST               2 (19)
                 134 BINARY_SUBSCR
                 136 CALL_FUNCTION            1
                 138 LOAD_CONST              12 (4)
                 140 BINARY_AND
                 142 LOAD_CONST              15 (2)
                 144 BINARY_RSHIFT
                 146 LOAD_CONST               8 (1)
                 148 COMPARE_OP               2 (==)
                 150 JUMP_IF_FALSE_OR_POP   198
                 152 LOAD_GLOBAL              0 (ord)
                 154 LOAD_FAST                0 (NYYZYQYFTG)
                 156 LOAD_CONST               2 (19)
                 158 BINARY_SUBSCR
                 160 CALL_FUNCTION            1
                 162 LOAD_CONST              15 (2)
                 164 BINARY_AND
                 166 LOAD_CONST               8 (1)
                 168 BINARY_RSHIFT
                 170 LOAD_CONST               8 (1)
                 172 COMPARE_OP               2 (==)
                 174 JUMP_IF_FALSE_OR_POP   198
                 176 LOAD_GLOBAL              0 (ord)
                 178 LOAD_FAST                0 (NYYZYQYFTG)
                 180 LOAD_CONST               2 (19)
                 182 BINARY_SUBSCR
                 184 CALL_FUNCTION            1
                 186 LOAD_CONST               8 (1)
                 188 BINARY_AND
                 190 LOAD_CONST               5 (0)
                 192 BINARY_RSHIFT
                 194 LOAD_CONST               8 (1)
                 196 COMPARE_OP               2 (==)
             >>  198 STORE_FAST               1 (BJYLPQQYPV)

42069669         200 LOAD_FAST                1 (BJYLPQQYPV)
                 202 EXTENDED_ARG             1
                 204 JUMP_IF_FALSE_OR_POP   410
                 206 LOAD_GLOBAL              0 (ord)
                 208 LOAD_FAST                0 (NYYZYQYFTG)
                 210 LOAD_CONST              16 (12)
                 212 BINARY_SUBSCR
                 214 CALL_FUNCTION            1
                 216 LOAD_CONST               3 (128)
                 218 BINARY_AND
                 220 LOAD_CONST               4 (7)
                 222 BINARY_RSHIFT
                 224 LOAD_CONST               5 (0)
                 226 COMPARE_OP               2 (==)
                 228 EXTENDED_ARG             1
                 230 JUMP_IF_FALSE_OR_POP   410
                 232 LOAD_GLOBAL              0 (ord)
                 234 LOAD_FAST                0 (NYYZYQYFTG)
                 236 LOAD_CONST              16 (12)
                 238 BINARY_SUBSCR
                 240 CALL_FUNCTION            1
                 242 LOAD_CONST               6 (64)
                 244 BINARY_AND
                 246 LOAD_CONST               7 (6)
                 248 BINARY_RSHIFT
                 250 LOAD_CONST               8 (1)
                 252 COMPARE_OP               2 (==)
                 254 EXTENDED_ARG             1
                 256 JUMP_IF_FALSE_OR_POP   410
                 258 LOAD_GLOBAL              0 (ord)
                 260 LOAD_FAST                0 (NYYZYQYFTG)
                 262 LOAD_CONST              16 (12)
                 264 BINARY_SUBSCR
                 266 CALL_FUNCTION            1
                 268 LOAD_CONST               9 (32)
                 270 BINARY_AND
                 272 LOAD_CONST              10 (5)
                 274 BINARY_RSHIFT
                 276 LOAD_CONST               8 (1)
                 278 COMPARE_OP               2 (==)
                 280 EXTENDED_ARG             1
                 282 JUMP_IF_FALSE_OR_POP   410
                 284 LOAD_GLOBAL              0 (ord)
                 286 LOAD_FAST                0 (NYYZYQYFTG)
                 288 LOAD_CONST              16 (12)
                 290 BINARY_SUBSCR
                 292 CALL_FUNCTION            1
                 294 LOAD_CONST              11 (16)
                 296 BINARY_AND
                 298 LOAD_CONST              12 (4)
                 300 BINARY_RSHIFT
                 302 LOAD_CONST               5 (0)
                 304 COMPARE_OP               2 (==)
                 306 EXTENDED_ARG             1
                 308 JUMP_IF_FALSE_OR_POP   410
                 310 LOAD_GLOBAL              0 (ord)
                 312 LOAD_FAST                0 (NYYZYQYFTG)
                 314 LOAD_CONST              16 (12)
                 316 BINARY_SUBSCR
                 318 CALL_FUNCTION            1
                 320 LOAD_CONST              13 (8)
                 322 BINARY_AND
                 324 LOAD_CONST              14 (3)
                 326 BINARY_RSHIFT
                 328 LOAD_CONST               5 (0)
                 330 COMPARE_OP               2 (==)
                 332 EXTENDED_ARG             1
                 334 JUMP_IF_FALSE_OR_POP   410
                 336 LOAD_GLOBAL              0 (ord)
                 338 LOAD_FAST                0 (NYYZYQYFTG)
                 340 LOAD_CONST              16 (12)
                 342 BINARY_SUBSCR
                 344 CALL_FUNCTION            1
                 346 LOAD_CONST              12 (4)
                 348 BINARY_AND
                 350 LOAD_CONST              15 (2)
                 352 BINARY_RSHIFT
                 354 LOAD_CONST               5 (0)
                 356 COMPARE_OP               2 (==)
                 358 EXTENDED_ARG             1
                 360 JUMP_IF_FALSE_OR_POP   410
                 362 LOAD_GLOBAL              0 (ord)
                 364 LOAD_FAST                0 (NYYZYQYFTG)
                 366 LOAD_CONST              16 (12)
                 368 BINARY_SUBSCR
                 370 CALL_FUNCTION            1
                 372 LOAD_CONST              15 (2)
                 374 BINARY_AND
                 376 LOAD_CONST               8 (1)
                 378 BINARY_RSHIFT
                 380 LOAD_CONST               8 (1)
                 382 COMPARE_OP               2 (==)
                 384 EXTENDED_ARG             1
                 386 JUMP_IF_FALSE_OR_POP   410
                 388 LOAD_GLOBAL              0 (ord)
                 390 LOAD_FAST                0 (NYYZYQYFTG)
                 392 LOAD_CONST              16 (12)
                 394 BINARY_SUBSCR
                 396 CALL_FUNCTION            1
                 398 LOAD_CONST               8 (1)
                 400 BINARY_AND
                 402 LOAD_CONST               5 (0)
                 404 BINARY_RSHIFT
                 406 LOAD_CONST               5 (0)
                 408 COMPARE_OP               2 (==)
             >>  410 STORE_FAST               1 (BJYLPQQYPV)

42069670         412 LOAD_GLOBAL              1 (len)
                 414 LOAD_FAST                0 (NYYZYQYFTG)
                 416 CALL_FUNCTION            1
                 418 STORE_FAST               2 (SEMCZBFUBY)

42069671         420 LOAD_FAST                1 (BJYLPQQYPV)
                 422 EXTENDED_ARG             2
                 424 JUMP_IF_FALSE_OR_POP   630
                 426 LOAD_GLOBAL              0 (ord)
                 428 LOAD_FAST                0 (NYYZYQYFTG)
                 430 LOAD_CONST              17 (17)
                 432 BINARY_SUBSCR
                 434 CALL_FUNCTION            1
                 436 LOAD_CONST               3 (128)
                 438 BINARY_AND
                 440 LOAD_CONST               4 (7)
                 442 BINARY_RSHIFT
                 444 LOAD_CONST               5 (0)
                 446 COMPARE_OP               2 (==)
                 448 EXTENDED_ARG             2
                 450 JUMP_IF_FALSE_OR_POP   630
                 452 LOAD_GLOBAL              0 (ord)
                 454 LOAD_FAST                0 (NYYZYQYFTG)
                 456 LOAD_CONST              17 (17)
                 458 BINARY_SUBSCR
                 460 CALL_FUNCTION            1
                 462 LOAD_CONST               6 (64)
                 464 BINARY_AND
                 466 LOAD_CONST               7 (6)
                 468 BINARY_RSHIFT
                 470 LOAD_CONST               8 (1)
                 472 COMPARE_OP               2 (==)
                 474 EXTENDED_ARG             2
                 476 JUMP_IF_FALSE_OR_POP   630
                 478 LOAD_GLOBAL              0 (ord)
                 480 LOAD_FAST                0 (NYYZYQYFTG)
                 482 LOAD_CONST              17 (17)
                 484 BINARY_SUBSCR
                 486 CALL_FUNCTION            1
                 488 LOAD_CONST               9 (32)
                 490 BINARY_AND
                 492 LOAD_CONST              10 (5)
                 494 BINARY_RSHIFT
                 496 LOAD_CONST               8 (1)
                 498 COMPARE_OP               2 (==)
                 500 EXTENDED_ARG             2
                 502 JUMP_IF_FALSE_OR_POP   630
                 504 LOAD_GLOBAL              0 (ord)
                 506 LOAD_FAST                0 (NYYZYQYFTG)
                 508 LOAD_CONST              17 (17)
                 510 BINARY_SUBSCR
                 512 CALL_FUNCTION            1
                 514 LOAD_CONST              11 (16)
                 516 BINARY_AND
                 518 LOAD_CONST              12 (4)
                 520 BINARY_RSHIFT
                 522 LOAD_CONST               5 (0)
                 524 COMPARE_OP               2 (==)
                 526 EXTENDED_ARG             2
                 528 JUMP_IF_FALSE_OR_POP   630
                 530 LOAD_GLOBAL              0 (ord)
                 532 LOAD_FAST                0 (NYYZYQYFTG)
                 534 LOAD_CONST              17 (17)
                 536 BINARY_SUBSCR
                 538 CALL_FUNCTION            1
                 540 LOAD_CONST              13 (8)
                 542 BINARY_AND
                 544 LOAD_CONST              14 (3)
                 546 BINARY_RSHIFT
                 548 LOAD_CONST               5 (0)
                 550 COMPARE_OP               2 (==)
                 552 EXTENDED_ARG             2
                 554 JUMP_IF_FALSE_OR_POP   630
                 556 LOAD_GLOBAL              0 (ord)
                 558 LOAD_FAST                0 (NYYZYQYFTG)
                 560 LOAD_CONST              17 (17)
                 562 BINARY_SUBSCR
                 564 CALL_FUNCTION            1
                 566 LOAD_CONST              12 (4)
                 568 BINARY_AND
                 570 LOAD_CONST              15 (2)
                 572 BINARY_RSHIFT
                 574 LOAD_CONST               5 (0)
                 576 COMPARE_OP               2 (==)
                 578 EXTENDED_ARG             2
                 580 JUMP_IF_FALSE_OR_POP   630
                 582 LOAD_GLOBAL              0 (ord)
                 584 LOAD_FAST                0 (NYYZYQYFTG)
                 586 LOAD_CONST              17 (17)
                 588 BINARY_SUBSCR
                 590 CALL_FUNCTION            1
                 592 LOAD_CONST              15 (2)
                 594 BINARY_AND
                 596 LOAD_CONST               8 (1)
                 598 BINARY_RSHIFT
                 600 LOAD_CONST               5 (0)
                 602 COMPARE_OP               2 (==)
                 604 EXTENDED_ARG             2
                 606 JUMP_IF_FALSE_OR_POP   630
                 608 LOAD_GLOBAL              0 (ord)
                 610 LOAD_FAST                0 (NYYZYQYFTG)
                 612 LOAD_CONST              17 (17)
                 614 BINARY_SUBSCR
                 616 CALL_FUNCTION            1
                 618 LOAD_CONST               8 (1)
                 620 BINARY_AND
                 622 LOAD_CONST               5 (0)
                 624 BINARY_RSHIFT
                 626 LOAD_CONST               8 (1)
                 628 COMPARE_OP               2 (==)
             >>  630 STORE_FAST               1 (BJYLPQQYPV)

42069672         632 LOAD_FAST                1 (BJYLPQQYPV)
                 634 EXTENDED_ARG             3
                 636 JUMP_IF_FALSE_OR_POP   842
                 638 LOAD_GLOBAL              0 (ord)
                 640 LOAD_FAST                0 (NYYZYQYFTG)
                 642 LOAD_CONST              18 (29)
                 644 BINARY_SUBSCR
                 646 CALL_FUNCTION            1
                 648 LOAD_CONST               3 (128)
                 650 BINARY_AND
                 652 LOAD_CONST               4 (7)
                 654 BINARY_RSHIFT
                 656 LOAD_CONST               5 (0)
                 658 COMPARE_OP               2 (==)
                 660 EXTENDED_ARG             3
                 662 JUMP_IF_FALSE_OR_POP   842
                 664 LOAD_GLOBAL              0 (ord)
                 666 LOAD_FAST                0 (NYYZYQYFTG)
                 668 LOAD_CONST              18 (29)
                 670 BINARY_SUBSCR
                 672 CALL_FUNCTION            1
                 674 LOAD_CONST               6 (64)
                 676 BINARY_AND
                 678 LOAD_CONST               7 (6)
                 680 BINARY_RSHIFT
                 682 LOAD_CONST               8 (1)
                 684 COMPARE_OP               2 (==)
                 686 EXTENDED_ARG             3
                 688 JUMP_IF_FALSE_OR_POP   842
                 690 LOAD_GLOBAL              0 (ord)
                 692 LOAD_FAST                0 (NYYZYQYFTG)
                 694 LOAD_CONST              18 (29)
                 696 BINARY_SUBSCR
                 698 CALL_FUNCTION            1
                 700 LOAD_CONST               9 (32)
                 702 BINARY_AND
                 704 LOAD_CONST              10 (5)
                 706 BINARY_RSHIFT
                 708 LOAD_CONST               8 (1)
                 710 COMPARE_OP               2 (==)
                 712 EXTENDED_ARG             3
                 714 JUMP_IF_FALSE_OR_POP   842
                 716 LOAD_GLOBAL              0 (ord)
                 718 LOAD_FAST                0 (NYYZYQYFTG)
                 720 LOAD_CONST              18 (29)
                 722 BINARY_SUBSCR
                 724 CALL_FUNCTION            1
                 726 LOAD_CONST              11 (16)
                 728 BINARY_AND
                 730 LOAD_CONST              12 (4)
                 732 BINARY_RSHIFT
                 734 LOAD_CONST               5 (0)
                 736 COMPARE_OP               2 (==)
                 738 EXTENDED_ARG             3
                 740 JUMP_IF_FALSE_OR_POP   842
                 742 LOAD_GLOBAL              0 (ord)
                 744 LOAD_FAST                0 (NYYZYQYFTG)
                 746 LOAD_CONST              18 (29)
                 748 BINARY_SUBSCR
                 750 CALL_FUNCTION            1
                 752 LOAD_CONST              13 (8)
                 754 BINARY_AND
                 756 LOAD_CONST              14 (3)
                 758 BINARY_RSHIFT
                 760 LOAD_CONST               5 (0)
                 762 COMPARE_OP               2 (==)
                 764 EXTENDED_ARG             3
                 766 JUMP_IF_FALSE_OR_POP   842
                 768 LOAD_GLOBAL              0 (ord)
                 770 LOAD_FAST                0 (NYYZYQYFTG)
                 772 LOAD_CONST              18 (29)
                 774 BINARY_SUBSCR
                 776 CALL_FUNCTION            1
                 778 LOAD_CONST              12 (4)
                 780 BINARY_AND
                 782 LOAD_CONST              15 (2)
                 784 BINARY_RSHIFT
                 786 LOAD_CONST               8 (1)
                 788 COMPARE_OP               2 (==)
                 790 EXTENDED_ARG             3
                 792 JUMP_IF_FALSE_OR_POP   842
                 794 LOAD_GLOBAL              0 (ord)
                 796 LOAD_FAST                0 (NYYZYQYFTG)
                 798 LOAD_CONST              18 (29)
                 800 BINARY_SUBSCR
                 802 CALL_FUNCTION            1
                 804 LOAD_CONST              15 (2)
                 806 BINARY_AND
                 808 LOAD_CONST               8 (1)
                 810 BINARY_RSHIFT
                 812 LOAD_CONST               5 (0)
                 814 COMPARE_OP               2 (==)
                 816 EXTENDED_ARG             3
                 818 JUMP_IF_FALSE_OR_POP   842
                 820 LOAD_GLOBAL              0 (ord)
                 822 LOAD_FAST                0 (NYYZYQYFTG)
                 824 LOAD_CONST              18 (29)
                 826 BINARY_SUBSCR
                 828 CALL_FUNCTION            1
                 830 LOAD_CONST               8 (1)
                 832 BINARY_AND
                 834 LOAD_CONST               5 (0)
                 836 BINARY_RSHIFT
                 838 LOAD_CONST               5 (0)
                 840 COMPARE_OP               2 (==)
             >>  842 STORE_FAST               1 (BJYLPQQYPV)

42069673         844 LOAD_FAST                1 (BJYLPQQYPV)
                 846 EXTENDED_ARG             4
                 848 JUMP_IF_FALSE_OR_POP  1054
                 850 LOAD_GLOBAL              0 (ord)
                 852 LOAD_FAST                0 (NYYZYQYFTG)
                 854 LOAD_CONST              19 (23)
                 856 BINARY_SUBSCR
                 858 CALL_FUNCTION            1
                 860 LOAD_CONST               3 (128)
                 862 BINARY_AND
                 864 LOAD_CONST               4 (7)
                 866 BINARY_RSHIFT
                 868 LOAD_CONST               5 (0)
                 870 COMPARE_OP               2 (==)
                 872 EXTENDED_ARG             4
                 874 JUMP_IF_FALSE_OR_POP  1054
                 876 LOAD_GLOBAL              0 (ord)
                 878 LOAD_FAST                0 (NYYZYQYFTG)
                 880 LOAD_CONST              19 (23)
                 882 BINARY_SUBSCR
                 884 CALL_FUNCTION            1
                 886 LOAD_CONST               6 (64)
                 888 BINARY_AND
                 890 LOAD_CONST               7 (6)
                 892 BINARY_RSHIFT
                 894 LOAD_CONST               5 (0)
                 896 COMPARE_OP               2 (==)
                 898 EXTENDED_ARG             4
                 900 JUMP_IF_FALSE_OR_POP  1054
                 902 LOAD_GLOBAL              0 (ord)
                 904 LOAD_FAST                0 (NYYZYQYFTG)
                 906 LOAD_CONST              19 (23)
                 908 BINARY_SUBSCR
                 910 CALL_FUNCTION            1
                 912 LOAD_CONST               9 (32)
                 914 BINARY_AND
                 916 LOAD_CONST              10 (5)
                 918 BINARY_RSHIFT
                 920 LOAD_CONST               8 (1)
                 922 COMPARE_OP               2 (==)
                 924 EXTENDED_ARG             4
                 926 JUMP_IF_FALSE_OR_POP  1054
                 928 LOAD_GLOBAL              0 (ord)
                 930 LOAD_FAST                0 (NYYZYQYFTG)
                 932 LOAD_CONST              19 (23)
                 934 BINARY_SUBSCR
                 936 CALL_FUNCTION            1
                 938 LOAD_CONST              11 (16)
                 940 BINARY_AND
                 942 LOAD_CONST              12 (4)
                 944 BINARY_RSHIFT
                 946 LOAD_CONST               8 (1)
                 948 COMPARE_OP               2 (==)
                 950 EXTENDED_ARG             4
                 952 JUMP_IF_FALSE_OR_POP  1054
                 954 LOAD_GLOBAL              0 (ord)
                 956 LOAD_FAST                0 (NYYZYQYFTG)
                 958 LOAD_CONST              19 (23)
                 960 BINARY_SUBSCR
                 962 CALL_FUNCTION            1
                 964 LOAD_CONST              13 (8)
                 966 BINARY_AND
                 968 LOAD_CONST              14 (3)
                 970 BINARY_RSHIFT
                 972 LOAD_CONST               5 (0)
                 974 COMPARE_OP               2 (==)
                 976 EXTENDED_ARG             4
                 978 JUMP_IF_FALSE_OR_POP  1054
                 980 LOAD_GLOBAL              0 (ord)
                 982 LOAD_FAST                0 (NYYZYQYFTG)
                 984 LOAD_CONST              19 (23)
                 986 BINARY_SUBSCR
                 988 CALL_FUNCTION            1
                 990 LOAD_CONST              12 (4)
                 992 BINARY_AND
                 994 LOAD_CONST              15 (2)
                 996 BINARY_RSHIFT
                 998 LOAD_CONST               5 (0)
                1000 COMPARE_OP               2 (==)
                1002 EXTENDED_ARG             4
                1004 JUMP_IF_FALSE_OR_POP  1054
                1006 LOAD_GLOBAL              0 (ord)
                1008 LOAD_FAST                0 (NYYZYQYFTG)
                1010 LOAD_CONST              19 (23)
                1012 BINARY_SUBSCR
                1014 CALL_FUNCTION            1
                1016 LOAD_CONST              15 (2)
                1018 BINARY_AND
                1020 LOAD_CONST               8 (1)
                1022 BINARY_RSHIFT
                1024 LOAD_CONST               5 (0)
                1026 COMPARE_OP               2 (==)
                1028 EXTENDED_ARG             4
                1030 JUMP_IF_FALSE_OR_POP  1054
                1032 LOAD_GLOBAL              0 (ord)
                1034 LOAD_FAST                0 (NYYZYQYFTG)
                1036 LOAD_CONST              19 (23)
                1038 BINARY_SUBSCR
                1040 CALL_FUNCTION            1
                1042 LOAD_CONST               8 (1)
                1044 BINARY_AND
                1046 LOAD_CONST               5 (0)
                1048 BINARY_RSHIFT
                1050 LOAD_CONST               8 (1)
                1052 COMPARE_OP               2 (==)
             >> 1054 STORE_FAST               1 (BJYLPQQYPV)

42069674        1056 LOAD_FAST                1 (BJYLPQQYPV)
                1058 EXTENDED_ARG             4
                1060 JUMP_IF_FALSE_OR_POP  1110
                1062 LOAD_GLOBAL              0 (ord)
                1064 LOAD_FAST                0 (NYYZYQYFTG)
                1066 LOAD_CONST              20 (35)
                1068 BINARY_SUBSCR
                1070 CALL_FUNCTION            1
                1072 LOAD_CONST              21 (240)
                1074 BINARY_AND
                1076 LOAD_CONST              22 (96)
                1078 BINARY_XOR
                1080 LOAD_CONST               5 (0)
                1082 COMPARE_OP               2 (==)
                1084 EXTENDED_ARG             4
                1086 JUMP_IF_FALSE_OR_POP  1110
                1088 LOAD_GLOBAL              0 (ord)
                1090 LOAD_FAST                0 (NYYZYQYFTG)
                1092 LOAD_CONST              20 (35)
                1094 BINARY_SUBSCR
                1096 CALL_FUNCTION            1
                1098 LOAD_CONST              23 (15)
                1100 BINARY_AND
                1102 LOAD_CONST               4 (7)
                1104 BINARY_XOR
                1106 LOAD_CONST               5 (0)
                1108 COMPARE_OP               2 (==)
             >> 1110 STORE_FAST               1 (BJYLPQQYPV)

42069675        1112 LOAD_FAST                1 (BJYLPQQYPV)
                1114 EXTENDED_ARG             5
                1116 JUMP_IF_FALSE_OR_POP  1322
                1118 LOAD_GLOBAL              0 (ord)
                1120 LOAD_FAST                0 (NYYZYQYFTG)
                1122 LOAD_CONST              24 (13)
                1124 BINARY_SUBSCR
                1126 CALL_FUNCTION            1
                1128 LOAD_CONST               3 (128)
                1130 BINARY_AND
                1132 LOAD_CONST               4 (7)
                1134 BINARY_RSHIFT
                1136 LOAD_CONST               5 (0)
                1138 COMPARE_OP               2 (==)
                1140 EXTENDED_ARG             5
                1142 JUMP_IF_FALSE_OR_POP  1322
                1144 LOAD_GLOBAL              0 (ord)
                1146 LOAD_FAST                0 (NYYZYQYFTG)
                1148 LOAD_CONST              24 (13)
                1150 BINARY_SUBSCR
                1152 CALL_FUNCTION            1
                1154 LOAD_CONST               6 (64)
                1156 BINARY_AND
                1158 LOAD_CONST               7 (6)
                1160 BINARY_RSHIFT
                1162 LOAD_CONST               8 (1)
                1164 COMPARE_OP               2 (==)
                1166 EXTENDED_ARG             5
                1168 JUMP_IF_FALSE_OR_POP  1322
                1170 LOAD_GLOBAL              0 (ord)
                1172 LOAD_FAST                0 (NYYZYQYFTG)
                1174 LOAD_CONST              24 (13)
                1176 BINARY_SUBSCR
                1178 CALL_FUNCTION            1
                1180 LOAD_CONST               9 (32)
                1182 BINARY_AND
                1184 LOAD_CONST              10 (5)
                1186 BINARY_RSHIFT
                1188 LOAD_CONST               5 (0)
                1190 COMPARE_OP               2 (==)
                1192 EXTENDED_ARG             5
                1194 JUMP_IF_FALSE_OR_POP  1322
                1196 LOAD_GLOBAL              0 (ord)
                1198 LOAD_FAST                0 (NYYZYQYFTG)
                1200 LOAD_CONST              24 (13)
                1202 BINARY_SUBSCR
                1204 CALL_FUNCTION            1
                1206 LOAD_CONST              11 (16)
                1208 BINARY_AND
                1210 LOAD_CONST              12 (4)
                1212 BINARY_RSHIFT
                1214 LOAD_CONST               8 (1)
                1216 COMPARE_OP               2 (==)
                1218 EXTENDED_ARG             5
                1220 JUMP_IF_FALSE_OR_POP  1322
                1222 LOAD_GLOBAL              0 (ord)
                1224 LOAD_FAST                0 (NYYZYQYFTG)
                1226 LOAD_CONST              24 (13)
                1228 BINARY_SUBSCR
                1230 CALL_FUNCTION            1
                1232 LOAD_CONST              13 (8)
                1234 BINARY_AND
                1236 LOAD_CONST              14 (3)
                1238 BINARY_RSHIFT
                1240 LOAD_CONST               8 (1)
                1242 COMPARE_OP               2 (==)
                1244 EXTENDED_ARG             5
                1246 JUMP_IF_FALSE_OR_POP  1322
                1248 LOAD_GLOBAL              0 (ord)
                1250 LOAD_FAST                0 (NYYZYQYFTG)
                1252 LOAD_CONST              24 (13)
                1254 BINARY_SUBSCR
                1256 CALL_FUNCTION            1
                1258 LOAD_CONST              12 (4)
                1260 BINARY_AND
                1262 LOAD_CONST              15 (2)
                1264 BINARY_RSHIFT
                1266 LOAD_CONST               8 (1)
                1268 COMPARE_OP               2 (==)
                1270 EXTENDED_ARG             5
                1272 JUMP_IF_FALSE_OR_POP  1322
                1274 LOAD_GLOBAL              0 (ord)
                1276 LOAD_FAST                0 (NYYZYQYFTG)
                1278 LOAD_CONST              24 (13)
                1280 BINARY_SUBSCR
                1282 CALL_FUNCTION            1
                1284 LOAD_CONST              15 (2)
                1286 BINARY_AND
                1288 LOAD_CONST               8 (1)
                1290 BINARY_RSHIFT
                1292 LOAD_CONST               8 (1)
                1294 COMPARE_OP               2 (==)
                1296 EXTENDED_ARG             5
                1298 JUMP_IF_FALSE_OR_POP  1322
                1300 LOAD_GLOBAL              0 (ord)
                1302 LOAD_FAST                0 (NYYZYQYFTG)
                1304 LOAD_CONST              24 (13)
                1306 BINARY_SUBSCR
                1308 CALL_FUNCTION            1
                1310 LOAD_CONST               8 (1)
                1312 BINARY_AND
                1314 LOAD_CONST               5 (0)
                1316 BINARY_RSHIFT
                1318 LOAD_CONST               8 (1)
                1320 COMPARE_OP               2 (==)
             >> 1322 STORE_FAST               1 (BJYLPQQYPV)

42069676        1324 LOAD_FAST                1 (BJYLPQQYPV)
                1326 EXTENDED_ARG             5
                1328 JUMP_IF_FALSE_OR_POP  1344
                1330 LOAD_GLOBAL              0 (ord)
                1332 LOAD_FAST                0 (NYYZYQYFTG)
                1334 LOAD_CONST              25 (14)
                1336 BINARY_SUBSCR
                1338 CALL_FUNCTION            1
                1340 LOAD_CONST              26 (99)
                1342 COMPARE_OP               2 (==)
             >> 1344 STORE_FAST               1 (BJYLPQQYPV)

42069677        1346 LOAD_FAST                0 (NYYZYQYFTG)
                1348 LOAD_CONST               0 (None)
                1350 LOAD_CONST              10 (5)
                1352 BUILD_SLICE              2
                1354 BINARY_SUBSCR
                1356 LOAD_CONST              27 ('UMASS')
                1358 COMPARE_OP               3 (!=)
                1360 EXTENDED_ARG             5
                1362 POP_JUMP_IF_FALSE     1370

42069678        1364 LOAD_CONST              28 (False)
                1366 BUILD_LIST               1
                1368 RETURN_VALUE

42069679     >> 1370 LOAD_FAST                1 (BJYLPQQYPV)
                1372 EXTENDED_ARG             5
                1374 JUMP_IF_FALSE_OR_POP  1424
                1376 LOAD_GLOBAL              0 (ord)
                1378 LOAD_FAST                0 (NYYZYQYFTG)
                1380 LOAD_CONST              29 (30)
                1382 BINARY_SUBSCR
                1384 CALL_FUNCTION            1
                1386 LOAD_CONST              21 (240)
                1388 BINARY_AND
                1390 LOAD_CONST              22 (96)
                1392 BINARY_XOR
                1394 LOAD_CONST               5 (0)
                1396 COMPARE_OP               2 (==)
                1398 EXTENDED_ARG             5
                1400 JUMP_IF_FALSE_OR_POP  1424
                1402 LOAD_GLOBAL              0 (ord)
                1404 LOAD_FAST                0 (NYYZYQYFTG)
                1406 LOAD_CONST              29 (30)
                1408 BINARY_SUBSCR
                1410 CALL_FUNCTION            1
                1412 LOAD_CONST              23 (15)
                1414 BINARY_AND
                1416 LOAD_CONST              30 (9)
                1418 BINARY_XOR
                1420 LOAD_CONST               5 (0)
                1422 COMPARE_OP               2 (==)
             >> 1424 STORE_FAST               1 (BJYLPQQYPV)

42069680        1426 LOAD_FAST                1 (BJYLPQQYPV)
                1428 EXTENDED_ARG             5
                1430 JUMP_IF_FALSE_OR_POP  1480
                1432 LOAD_GLOBAL              0 (ord)
                1434 LOAD_FAST                0 (NYYZYQYFTG)
                1436 LOAD_CONST              31 (26)
                1438 BINARY_SUBSCR
                1440 CALL_FUNCTION            1
                1442 LOAD_CONST              21 (240)
                1444 BINARY_AND
                1446 LOAD_CONST              22 (96)
                1448 BINARY_XOR
                1450 LOAD_CONST               5 (0)
                1452 COMPARE_OP               2 (==)
                1454 EXTENDED_ARG             5
                1456 JUMP_IF_FALSE_OR_POP  1480
                1458 LOAD_GLOBAL              0 (ord)
                1460 LOAD_FAST                0 (NYYZYQYFTG)
                1462 LOAD_CONST              31 (26)
                1464 BINARY_SUBSCR
                1466 CALL_FUNCTION            1
                1468 LOAD_CONST              23 (15)
                1470 BINARY_AND
                1472 LOAD_CONST               4 (7)
                1474 BINARY_XOR
                1476 LOAD_CONST               5 (0)
                1478 COMPARE_OP               2 (==)
             >> 1480 STORE_FAST               1 (BJYLPQQYPV)

42069681        1482 LOAD_FAST                1 (BJYLPQQYPV)
                1484 EXTENDED_ARG             6
                1486 JUMP_IF_FALSE_OR_POP  1536
                1488 LOAD_GLOBAL              0 (ord)
                1490 LOAD_FAST                0 (NYYZYQYFTG)
                1492 LOAD_CONST               5 (0)
                1494 BINARY_SUBSCR
                1496 CALL_FUNCTION            1
                1498 LOAD_CONST              21 (240)
                1500 BINARY_AND
                1502 LOAD_CONST              32 (80)
                1504 BINARY_XOR
                1506 LOAD_CONST               5 (0)
                1508 COMPARE_OP               2 (==)
                1510 EXTENDED_ARG             6
                1512 JUMP_IF_FALSE_OR_POP  1536
                1514 LOAD_GLOBAL              0 (ord)
                1516 LOAD_FAST                0 (NYYZYQYFTG)
                1518 LOAD_CONST               5 (0)
                1520 BINARY_SUBSCR
                1522 CALL_FUNCTION            1
                1524 LOAD_CONST              23 (15)
                1526 BINARY_AND
                1528 LOAD_CONST              10 (5)
                1530 BINARY_XOR
                1532 LOAD_CONST               5 (0)
                1534 COMPARE_OP               2 (==)
             >> 1536 STORE_FAST               1 (BJYLPQQYPV)

42069682        1538 LOAD_GLOBAL              0 (ord)
                1540 LOAD_FAST                0 (NYYZYQYFTG)
                1542 LOAD_CONST               5 (0)
                1544 BINARY_SUBSCR
                1546 CALL_FUNCTION            1
                1548 LOAD_CONST              21 (240)
                1550 BINARY_AND
                1552 LOAD_CONST              33 (47)
                1554 COMPARE_OP               2 (==)
                1556 EXTENDED_ARG             6
                1558 POP_JUMP_IF_FALSE     1566

42069683        1560 LOAD_CONST              11 (16)
                1562 STORE_FAST               2 (SEMCZBFUBY)
                1564 JUMP_FORWARD             4 (to 1570)

42069685     >> 1566 LOAD_CONST              19 (23)
                1568 STORE_FAST               2 (SEMCZBFUBY)

42069686     >> 1570 LOAD_FAST                1 (BJYLPQQYPV)
                1572 EXTENDED_ARG             6
                1574 JUMP_IF_FALSE_OR_POP  1780
                1576 LOAD_GLOBAL              0 (ord)
                1578 LOAD_FAST                0 (NYYZYQYFTG)
                1580 LOAD_CONST              10 (5)
                1582 BINARY_SUBSCR
                1584 CALL_FUNCTION            1
                1586 LOAD_CONST               3 (128)
                1588 BINARY_AND
                1590 LOAD_CONST               4 (7)
                1592 BINARY_RSHIFT
                1594 LOAD_CONST               5 (0)
                1596 COMPARE_OP               2 (==)
                1598 EXTENDED_ARG             6
                1600 JUMP_IF_FALSE_OR_POP  1780
                1602 LOAD_GLOBAL              0 (ord)
                1604 LOAD_FAST                0 (NYYZYQYFTG)
                1606 LOAD_CONST              10 (5)
                1608 BINARY_SUBSCR
                1610 CALL_FUNCTION            1
                1612 LOAD_CONST               6 (64)
                1614 BINARY_AND
                1616 LOAD_CONST               7 (6)
                1618 BINARY_RSHIFT
                1620 LOAD_CONST               8 (1)
                1622 COMPARE_OP               2 (==)
                1624 EXTENDED_ARG             6
                1626 JUMP_IF_FALSE_OR_POP  1780
                1628 LOAD_GLOBAL              0 (ord)
                1630 LOAD_FAST                0 (NYYZYQYFTG)
                1632 LOAD_CONST              10 (5)
                1634 BINARY_SUBSCR
                1636 CALL_FUNCTION            1
                1638 LOAD_CONST               9 (32)
                1640 BINARY_AND
                1642 LOAD_CONST              10 (5)
                1644 BINARY_RSHIFT
                1646 LOAD_CONST               8 (1)
                1648 COMPARE_OP               2 (==)
                1650 EXTENDED_ARG             6
                1652 JUMP_IF_FALSE_OR_POP  1780
                1654 LOAD_GLOBAL              0 (ord)
                1656 LOAD_FAST                0 (NYYZYQYFTG)
                1658 LOAD_CONST              10 (5)
                1660 BINARY_SUBSCR
                1662 CALL_FUNCTION            1
                1664 LOAD_CONST              11 (16)
                1666 BINARY_AND
                1668 LOAD_CONST              12 (4)
                1670 BINARY_RSHIFT
                1672 LOAD_CONST               8 (1)
                1674 COMPARE_OP               2 (==)
                1676 EXTENDED_ARG             6
                1678 JUMP_IF_FALSE_OR_POP  1780
                1680 LOAD_GLOBAL              0 (ord)
                1682 LOAD_FAST                0 (NYYZYQYFTG)
                1684 LOAD_CONST              10 (5)
                1686 BINARY_SUBSCR
                1688 CALL_FUNCTION            1
                1690 LOAD_CONST              13 (8)
                1692 BINARY_AND
                1694 LOAD_CONST              14 (3)
                1696 BINARY_RSHIFT
                1698 LOAD_CONST               8 (1)
                1700 COMPARE_OP               2 (==)
                1702 EXTENDED_ARG             6
                1704 JUMP_IF_FALSE_OR_POP  1780
                1706 LOAD_GLOBAL              0 (ord)
                1708 LOAD_FAST                0 (NYYZYQYFTG)
                1710 LOAD_CONST              10 (5)
                1712 BINARY_SUBSCR
                1714 CALL_FUNCTION            1
                1716 LOAD_CONST              12 (4)
                1718 BINARY_AND
                1720 LOAD_CONST              15 (2)
                1722 BINARY_RSHIFT
                1724 LOAD_CONST               5 (0)
                1726 COMPARE_OP               2 (==)
                1728 EXTENDED_ARG             6
                1730 JUMP_IF_FALSE_OR_POP  1780
                1732 LOAD_GLOBAL              0 (ord)
                1734 LOAD_FAST                0 (NYYZYQYFTG)
                1736 LOAD_CONST              10 (5)
                1738 BINARY_SUBSCR
                1740 CALL_FUNCTION            1
                1742 LOAD_CONST              15 (2)
                1744 BINARY_AND
                1746 LOAD_CONST               8 (1)
                1748 BINARY_RSHIFT
                1750 LOAD_CONST               8 (1)
                1752 COMPARE_OP               2 (==)
                1754 EXTENDED_ARG             6
                1756 JUMP_IF_FALSE_OR_POP  1780
                1758 LOAD_GLOBAL              0 (ord)
                1760 LOAD_FAST                0 (NYYZYQYFTG)
                1762 LOAD_CONST              10 (5)
                1764 BINARY_SUBSCR
                1766 CALL_FUNCTION            1
                1768 LOAD_CONST               8 (1)
                1770 BINARY_AND
                1772 LOAD_CONST               5 (0)
                1774 BINARY_RSHIFT
                1776 LOAD_CONST               8 (1)
                1778 COMPARE_OP               2 (==)
             >> 1780 STORE_FAST               1 (BJYLPQQYPV)

42069687        1782 LOAD_FAST                1 (BJYLPQQYPV)
                1784 EXTENDED_ARG             7
                1786 JUMP_IF_FALSE_OR_POP  1836
                1788 LOAD_GLOBAL              0 (ord)
                1790 LOAD_FAST                0 (NYYZYQYFTG)
                1792 LOAD_CONST              34 (28)
                1794 BINARY_SUBSCR
                1796 CALL_FUNCTION            1
                1798 LOAD_CONST              21 (240)
                1800 BINARY_AND
                1802 LOAD_CONST              32 (80)
                1804 BINARY_XOR
                1806 LOAD_CONST               5 (0)
                1808 COMPARE_OP               2 (==)
                1810 EXTENDED_ARG             7
                1812 JUMP_IF_FALSE_OR_POP  1836
                1814 LOAD_GLOBAL              0 (ord)
                1816 LOAD_FAST                0 (NYYZYQYFTG)
                1818 LOAD_CONST              34 (28)
                1820 BINARY_SUBSCR
                1822 CALL_FUNCTION            1
                1824 LOAD_CONST              23 (15)
                1826 BINARY_AND
                1828 LOAD_CONST              23 (15)
                1830 BINARY_XOR
                1832 LOAD_CONST               5 (0)
                1834 COMPARE_OP               2 (==)
             >> 1836 STORE_FAST               1 (BJYLPQQYPV)

42069688        1838 LOAD_FAST                1 (BJYLPQQYPV)
                1840 EXTENDED_ARG             8
                1842 JUMP_IF_FALSE_OR_POP  2048
                1844 LOAD_GLOBAL              0 (ord)
                1846 LOAD_FAST                0 (NYYZYQYFTG)
                1848 LOAD_CONST              35 (24)
                1850 BINARY_SUBSCR
                1852 CALL_FUNCTION            1
                1854 LOAD_CONST               3 (128)
                1856 BINARY_AND
                1858 LOAD_CONST               4 (7)
                1860 BINARY_RSHIFT
                1862 LOAD_CONST               5 (0)
                1864 COMPARE_OP               2 (==)
                1866 EXTENDED_ARG             8
                1868 JUMP_IF_FALSE_OR_POP  2048
                1870 LOAD_GLOBAL              0 (ord)
                1872 LOAD_FAST                0 (NYYZYQYFTG)
                1874 LOAD_CONST              35 (24)
                1876 BINARY_SUBSCR
                1878 CALL_FUNCTION            1
                1880 LOAD_CONST               6 (64)
                1882 BINARY_AND
                1884 LOAD_CONST               7 (6)
                1886 BINARY_RSHIFT
                1888 LOAD_CONST               5 (0)
                1890 COMPARE_OP               2 (==)
                1892 EXTENDED_ARG             8
                1894 JUMP_IF_FALSE_OR_POP  2048
                1896 LOAD_GLOBAL              0 (ord)
                1898 LOAD_FAST                0 (NYYZYQYFTG)
                1900 LOAD_CONST              35 (24)
                1902 BINARY_SUBSCR
                1904 CALL_FUNCTION            1
                1906 LOAD_CONST               9 (32)
                1908 BINARY_AND
                1910 LOAD_CONST              10 (5)
                1912 BINARY_RSHIFT
                1914 LOAD_CONST               8 (1)
                1916 COMPARE_OP               2 (==)
                1918 EXTENDED_ARG             8
                1920 JUMP_IF_FALSE_OR_POP  2048
                1922 LOAD_GLOBAL              0 (ord)
                1924 LOAD_FAST                0 (NYYZYQYFTG)
                1926 LOAD_CONST              35 (24)
                1928 BINARY_SUBSCR
                1930 CALL_FUNCTION            1
                1932 LOAD_CONST              11 (16)
                1934 BINARY_AND
                1936 LOAD_CONST              12 (4)
                1938 BINARY_RSHIFT
                1940 LOAD_CONST               8 (1)
                1942 COMPARE_OP               2 (==)
                1944 EXTENDED_ARG             8
                1946 JUMP_IF_FALSE_OR_POP  2048
                1948 LOAD_GLOBAL              0 (ord)
                1950 LOAD_FAST                0 (NYYZYQYFTG)
                1952 LOAD_CONST              35 (24)
                1954 BINARY_SUBSCR
                1956 CALL_FUNCTION            1
                1958 LOAD_CONST              13 (8)
                1960 BINARY_AND
                1962 LOAD_CONST              14 (3)
                1964 BINARY_RSHIFT
                1966 LOAD_CONST               5 (0)
                1968 COMPARE_OP               2 (==)
                1970 EXTENDED_ARG             8
                1972 JUMP_IF_FALSE_OR_POP  2048
                1974 LOAD_GLOBAL              0 (ord)
                1976 LOAD_FAST                0 (NYYZYQYFTG)
                1978 LOAD_CONST              35 (24)
                1980 BINARY_SUBSCR
                1982 CALL_FUNCTION            1
                1984 LOAD_CONST              12 (4)
                1986 BINARY_AND
                1988 LOAD_CONST              15 (2)
                1990 BINARY_RSHIFT
                1992 LOAD_CONST               5 (0)
                1994 COMPARE_OP               2 (==)
                1996 EXTENDED_ARG             8
                1998 JUMP_IF_FALSE_OR_POP  2048
                2000 LOAD_GLOBAL              0 (ord)
                2002 LOAD_FAST                0 (NYYZYQYFTG)
                2004 LOAD_CONST              35 (24)
                2006 BINARY_SUBSCR
                2008 CALL_FUNCTION            1
                2010 LOAD_CONST              15 (2)
                2012 BINARY_AND
                2014 LOAD_CONST               8 (1)
                2016 BINARY_RSHIFT
                2018 LOAD_CONST               5 (0)
                2020 COMPARE_OP               2 (==)
                2022 EXTENDED_ARG             8
                2024 JUMP_IF_FALSE_OR_POP  2048
                2026 LOAD_GLOBAL              0 (ord)
                2028 LOAD_FAST                0 (NYYZYQYFTG)
                2030 LOAD_CONST              35 (24)
                2032 BINARY_SUBSCR
                2034 CALL_FUNCTION            1
                2036 LOAD_CONST               8 (1)
                2038 BINARY_AND
                2040 LOAD_CONST               5 (0)
                2042 BINARY_RSHIFT
                2044 LOAD_CONST               8 (1)
                2046 COMPARE_OP               2 (==)
             >> 2048 STORE_FAST               1 (BJYLPQQYPV)

42069689        2050 LOAD_FAST                1 (BJYLPQQYPV)
                2052 EXTENDED_ARG             8
                2054 JUMP_IF_FALSE_OR_POP  2260
                2056 LOAD_GLOBAL              0 (ord)
                2058 LOAD_FAST                0 (NYYZYQYFTG)
                2060 LOAD_CONST               4 (7)
                2062 BINARY_SUBSCR
                2064 CALL_FUNCTION            1
                2066 LOAD_CONST               3 (128)
                2068 BINARY_AND
                2070 LOAD_CONST               4 (7)
                2072 BINARY_RSHIFT
                2074 LOAD_CONST               5 (0)
                2076 COMPARE_OP               2 (==)
                2078 EXTENDED_ARG             8
                2080 JUMP_IF_FALSE_OR_POP  2260
                2082 LOAD_GLOBAL              0 (ord)
                2084 LOAD_FAST                0 (NYYZYQYFTG)
                2086 LOAD_CONST               4 (7)
                2088 BINARY_SUBSCR
                2090 CALL_FUNCTION            1
                2092 LOAD_CONST               6 (64)
                2094 BINARY_AND
                2096 LOAD_CONST               7 (6)
                2098 BINARY_RSHIFT
                2100 LOAD_CONST               8 (1)
                2102 COMPARE_OP               2 (==)
                2104 EXTENDED_ARG             8
                2106 JUMP_IF_FALSE_OR_POP  2260
                2108 LOAD_GLOBAL              0 (ord)
                2110 LOAD_FAST                0 (NYYZYQYFTG)
                2112 LOAD_CONST               4 (7)
                2114 BINARY_SUBSCR
                2116 CALL_FUNCTION            1
                2118 LOAD_CONST               9 (32)
                2120 BINARY_AND
                2122 LOAD_CONST              10 (5)
                2124 BINARY_RSHIFT
                2126 LOAD_CONST               8 (1)
                2128 COMPARE_OP               2 (==)
                2130 EXTENDED_ARG             8
                2132 JUMP_IF_FALSE_OR_POP  2260
                2134 LOAD_GLOBAL              0 (ord)
                2136 LOAD_FAST                0 (NYYZYQYFTG)
                2138 LOAD_CONST               4 (7)
                2140 BINARY_SUBSCR
                2142 CALL_FUNCTION            1
                2144 LOAD_CONST              11 (16)
                2146 BINARY_AND
                2148 LOAD_CONST              12 (4)
                2150 BINARY_RSHIFT
                2152 LOAD_CONST               5 (0)
                2154 COMPARE_OP               2 (==)
                2156 EXTENDED_ARG             8
                2158 JUMP_IF_FALSE_OR_POP  2260
                2160 LOAD_GLOBAL              0 (ord)
                2162 LOAD_FAST                0 (NYYZYQYFTG)
                2164 LOAD_CONST               4 (7)
                2166 BINARY_SUBSCR
                2168 CALL_FUNCTION            1
                2170 LOAD_CONST              13 (8)
                2172 BINARY_AND
                2174 LOAD_CONST              14 (3)
                2176 BINARY_RSHIFT
                2178 LOAD_CONST               5 (0)
                2180 COMPARE_OP               2 (==)
                2182 EXTENDED_ARG             8
                2184 JUMP_IF_FALSE_OR_POP  2260
                2186 LOAD_GLOBAL              0 (ord)
                2188 LOAD_FAST                0 (NYYZYQYFTG)
                2190 LOAD_CONST               4 (7)
                2192 BINARY_SUBSCR
                2194 CALL_FUNCTION            1
                2196 LOAD_CONST              12 (4)
                2198 BINARY_AND
                2200 LOAD_CONST              15 (2)
                2202 BINARY_RSHIFT
                2204 LOAD_CONST               8 (1)
                2206 COMPARE_OP               2 (==)
                2208 EXTENDED_ARG             8
                2210 JUMP_IF_FALSE_OR_POP  2260
                2212 LOAD_GLOBAL              0 (ord)
                2214 LOAD_FAST                0 (NYYZYQYFTG)
                2216 LOAD_CONST               4 (7)
                2218 BINARY_SUBSCR
                2220 CALL_FUNCTION            1
                2222 LOAD_CONST              15 (2)
                2224 BINARY_AND
                2226 LOAD_CONST               8 (1)
                2228 BINARY_RSHIFT
                2230 LOAD_CONST               5 (0)
                2232 COMPARE_OP               2 (==)
                2234 EXTENDED_ARG             8
                2236 JUMP_IF_FALSE_OR_POP  2260
                2238 LOAD_GLOBAL              0 (ord)
                2240 LOAD_FAST                0 (NYYZYQYFTG)
                2242 LOAD_CONST               4 (7)
                2244 BINARY_SUBSCR
                2246 CALL_FUNCTION            1
                2248 LOAD_CONST               8 (1)
                2250 BINARY_AND
                2252 LOAD_CONST               5 (0)
                2254 BINARY_RSHIFT
                2256 LOAD_CONST               5 (0)
                2258 COMPARE_OP               2 (==)
             >> 2260 STORE_FAST               1 (BJYLPQQYPV)

42069690        2262 LOAD_FAST                1 (BJYLPQQYPV)
                2264 EXTENDED_ARG             9
                2266 JUMP_IF_FALSE_OR_POP  2316
                2268 LOAD_GLOBAL              0 (ord)
                2270 LOAD_FAST                0 (NYYZYQYFTG)
                2272 LOAD_CONST              36 (20)
                2274 BINARY_SUBSCR
                2276 CALL_FUNCTION            1
                2278 LOAD_CONST              21 (240)
                2280 BINARY_AND
                2282 LOAD_CONST              37 (112)
                2284 BINARY_XOR
                2286 LOAD_CONST               5 (0)
                2288 COMPARE_OP               2 (==)
                2290 EXTENDED_ARG             9
                2292 JUMP_IF_FALSE_OR_POP  2316
                2294 LOAD_GLOBAL              0 (ord)
                2296 LOAD_FAST                0 (NYYZYQYFTG)
                2298 LOAD_CONST              36 (20)
                2300 BINARY_SUBSCR
                2302 CALL_FUNCTION            1
                2304 LOAD_CONST              23 (15)
                2306 BINARY_AND
                2308 LOAD_CONST              14 (3)
                2310 BINARY_XOR
                2312 LOAD_CONST               5 (0)
                2314 COMPARE_OP               2 (==)
             >> 2316 STORE_FAST               1 (BJYLPQQYPV)

42069691        2318 LOAD_FAST                1 (BJYLPQQYPV)
                2320 EXTENDED_ARG             9
                2322 JUMP_IF_FALSE_OR_POP  2528
                2324 LOAD_GLOBAL              0 (ord)
                2326 LOAD_FAST                0 (NYYZYQYFTG)
                2328 LOAD_CONST              38 (31)
                2330 BINARY_SUBSCR
                2332 CALL_FUNCTION            1
                2334 LOAD_CONST               3 (128)
                2336 BINARY_AND
                2338 LOAD_CONST               4 (7)
                2340 BINARY_RSHIFT
                2342 LOAD_CONST               5 (0)
                2344 COMPARE_OP               2 (==)
                2346 EXTENDED_ARG             9
                2348 JUMP_IF_FALSE_OR_POP  2528
                2350 LOAD_GLOBAL              0 (ord)
                2352 LOAD_FAST                0 (NYYZYQYFTG)
                2354 LOAD_CONST              38 (31)
                2356 BINARY_SUBSCR
                2358 CALL_FUNCTION            1
                2360 LOAD_CONST               6 (64)
                2362 BINARY_AND
                2364 LOAD_CONST               7 (6)
                2366 BINARY_RSHIFT
                2368 LOAD_CONST               8 (1)
                2370 COMPARE_OP               2 (==)
                2372 EXTENDED_ARG             9
                2374 JUMP_IF_FALSE_OR_POP  2528
                2376 LOAD_GLOBAL              0 (ord)
                2378 LOAD_FAST                0 (NYYZYQYFTG)
                2380 LOAD_CONST              38 (31)
                2382 BINARY_SUBSCR
                2384 CALL_FUNCTION            1
                2386 LOAD_CONST               9 (32)
                2388 BINARY_AND
                2390 LOAD_CONST              10 (5)
                2392 BINARY_RSHIFT
                2394 LOAD_CONST               8 (1)
                2396 COMPARE_OP               2 (==)
                2398 EXTENDED_ARG             9
                2400 JUMP_IF_FALSE_OR_POP  2528
                2402 LOAD_GLOBAL              0 (ord)
                2404 LOAD_FAST                0 (NYYZYQYFTG)
                2406 LOAD_CONST              38 (31)
                2408 BINARY_SUBSCR
                2410 CALL_FUNCTION            1
                2412 LOAD_CONST              11 (16)
                2414 BINARY_AND
                2416 LOAD_CONST              12 (4)
                2418 BINARY_RSHIFT
                2420 LOAD_CONST               5 (0)
                2422 COMPARE_OP               2 (==)
                2424 EXTENDED_ARG             9
                2426 JUMP_IF_FALSE_OR_POP  2528
                2428 LOAD_GLOBAL              0 (ord)
                2430 LOAD_FAST                0 (NYYZYQYFTG)
                2432 LOAD_CONST              38 (31)
                2434 BINARY_SUBSCR
                2436 CALL_FUNCTION            1
                2438 LOAD_CONST              13 (8)
                2440 BINARY_AND
                2442 LOAD_CONST              14 (3)
                2444 BINARY_RSHIFT
                2446 LOAD_CONST               5 (0)
                2448 COMPARE_OP               2 (==)
                2450 EXTENDED_ARG             9
                2452 JUMP_IF_FALSE_OR_POP  2528
                2454 LOAD_GLOBAL              0 (ord)
                2456 LOAD_FAST                0 (NYYZYQYFTG)
                2458 LOAD_CONST              38 (31)
                2460 BINARY_SUBSCR
                2462 CALL_FUNCTION            1
                2464 LOAD_CONST              12 (4)
                2466 BINARY_AND
                2468 LOAD_CONST              15 (2)
                2470 BINARY_RSHIFT
                2472 LOAD_CONST               8 (1)
                2474 COMPARE_OP               2 (==)
                2476 EXTENDED_ARG             9
                2478 JUMP_IF_FALSE_OR_POP  2528
                2480 LOAD_GLOBAL              0 (ord)
                2482 LOAD_FAST                0 (NYYZYQYFTG)
                2484 LOAD_CONST              38 (31)
                2486 BINARY_SUBSCR
                2488 CALL_FUNCTION            1
                2490 LOAD_CONST              15 (2)
                2492 BINARY_AND
                2494 LOAD_CONST               8 (1)
                2496 BINARY_RSHIFT
                2498 LOAD_CONST               8 (1)
                2500 COMPARE_OP               2 (==)
                2502 EXTENDED_ARG             9
                2504 JUMP_IF_FALSE_OR_POP  2528
                2506 LOAD_GLOBAL              0 (ord)
                2508 LOAD_FAST                0 (NYYZYQYFTG)
                2510 LOAD_CONST              38 (31)
                2512 BINARY_SUBSCR
                2514 CALL_FUNCTION            1
                2516 LOAD_CONST               8 (1)
                2518 BINARY_AND
                2520 LOAD_CONST               5 (0)
                2522 BINARY_RSHIFT
                2524 LOAD_CONST               8 (1)
                2526 COMPARE_OP               2 (==)
             >> 2528 STORE_FAST               1 (BJYLPQQYPV)

42069692        2530 LOAD_FAST                1 (BJYLPQQYPV)
                2532 EXTENDED_ARG            10
                2534 JUMP_IF_FALSE_OR_POP  2584
                2536 LOAD_GLOBAL              0 (ord)
                2538 LOAD_FAST                0 (NYYZYQYFTG)
                2540 LOAD_CONST              23 (15)
                2542 BINARY_SUBSCR
                2544 CALL_FUNCTION            1
                2546 LOAD_CONST              21 (240)
                2548 BINARY_AND
                2550 LOAD_CONST              39 (48)
                2552 BINARY_XOR
                2554 LOAD_CONST               5 (0)
                2556 COMPARE_OP               2 (==)
                2558 EXTENDED_ARG            10
                2560 JUMP_IF_FALSE_OR_POP  2584
                2562 LOAD_GLOBAL              0 (ord)
                2564 LOAD_FAST                0 (NYYZYQYFTG)
                2566 LOAD_CONST              23 (15)
                2568 BINARY_SUBSCR
                2570 CALL_FUNCTION            1
                2572 LOAD_CONST              23 (15)
                2574 BINARY_AND
                2576 LOAD_CONST               8 (1)
                2578 BINARY_XOR
                2580 LOAD_CONST               5 (0)
                2582 COMPARE_OP               2 (==)
             >> 2584 STORE_FAST               1 (BJYLPQQYPV)

42069693        2586 LOAD_FAST                1 (BJYLPQQYPV)
                2588 EXTENDED_ARG            10
                2590 JUMP_IF_FALSE_OR_POP  2606
                2592 LOAD_GLOBAL              0 (ord)
                2594 LOAD_FAST                0 (NYYZYQYFTG)
                2596 LOAD_CONST               7 (6)
                2598 BINARY_SUBSCR
                2600 CALL_FUNCTION            1
                2602 LOAD_CONST              40 (103)
                2604 COMPARE_OP               2 (==)
             >> 2606 STORE_FAST               1 (BJYLPQQYPV)

42069694        2608 LOAD_FAST                1 (BJYLPQQYPV)
                2610 EXTENDED_ARG            11
                2612 JUMP_IF_FALSE_OR_POP  2818
                2614 LOAD_GLOBAL              0 (ord)
                2616 LOAD_FAST                0 (NYYZYQYFTG)
                2618 LOAD_CONST              41 (21)
                2620 BINARY_SUBSCR
                2622 CALL_FUNCTION            1
                2624 LOAD_CONST               3 (128)
                2626 BINARY_AND
                2628 LOAD_CONST               4 (7)
                2630 BINARY_RSHIFT
                2632 LOAD_CONST               5 (0)
                2634 COMPARE_OP               2 (==)
                2636 EXTENDED_ARG            11
                2638 JUMP_IF_FALSE_OR_POP  2818
                2640 LOAD_GLOBAL              0 (ord)
                2642 LOAD_FAST                0 (NYYZYQYFTG)
                2644 LOAD_CONST              41 (21)
                2646 BINARY_SUBSCR
                2648 CALL_FUNCTION            1
                2650 LOAD_CONST               6 (64)
                2652 BINARY_AND
                2654 LOAD_CONST               7 (6)
                2656 BINARY_RSHIFT
                2658 LOAD_CONST               8 (1)
                2660 COMPARE_OP               2 (==)
                2662 EXTENDED_ARG            11
                2664 JUMP_IF_FALSE_OR_POP  2818
                2666 LOAD_GLOBAL              0 (ord)
                2668 LOAD_FAST                0 (NYYZYQYFTG)
                2670 LOAD_CONST              41 (21)
                2672 BINARY_SUBSCR
                2674 CALL_FUNCTION            1
                2676 LOAD_CONST               9 (32)
                2678 BINARY_AND
                2680 LOAD_CONST              10 (5)
                2682 BINARY_RSHIFT
                2684 LOAD_CONST               8 (1)
                2686 COMPARE_OP               2 (==)
                2688 EXTENDED_ARG            11
                2690 JUMP_IF_FALSE_OR_POP  2818
                2692 LOAD_GLOBAL              0 (ord)
                2694 LOAD_FAST                0 (NYYZYQYFTG)
                2696 LOAD_CONST              41 (21)
                2698 BINARY_SUBSCR
                2700 CALL_FUNCTION            1
                2702 LOAD_CONST              11 (16)
                2704 BINARY_AND
                2706 LOAD_CONST              12 (4)
                2708 BINARY_RSHIFT
                2710 LOAD_CONST               8 (1)
                2712 COMPARE_OP               2 (==)
                2714 EXTENDED_ARG            11
                2716 JUMP_IF_FALSE_OR_POP  2818
                2718 LOAD_GLOBAL              0 (ord)
                2720 LOAD_FAST                0 (NYYZYQYFTG)
                2722 LOAD_CONST              41 (21)
                2724 BINARY_SUBSCR
                2726 CALL_FUNCTION            1
                2728 LOAD_CONST              13 (8)
                2730 BINARY_AND
                2732 LOAD_CONST              14 (3)
                2734 BINARY_RSHIFT
                2736 LOAD_CONST               5 (0)
                2738 COMPARE_OP               2 (==)
                2740 EXTENDED_ARG            11
                2742 JUMP_IF_FALSE_OR_POP  2818
                2744 LOAD_GLOBAL              0 (ord)
                2746 LOAD_FAST                0 (NYYZYQYFTG)
                2748 LOAD_CONST              41 (21)
                2750 BINARY_SUBSCR
                2752 CALL_FUNCTION            1
                2754 LOAD_CONST              12 (4)
                2756 BINARY_AND
                2758 LOAD_CONST              15 (2)
                2760 BINARY_RSHIFT
                2762 LOAD_CONST               5 (0)
                2764 COMPARE_OP               2 (==)
                2766 EXTENDED_ARG            11
                2768 JUMP_IF_FALSE_OR_POP  2818
                2770 LOAD_GLOBAL              0 (ord)
                2772 LOAD_FAST                0 (NYYZYQYFTG)
                2774 LOAD_CONST              41 (21)
                2776 BINARY_SUBSCR
                2778 CALL_FUNCTION            1
                2780 LOAD_CONST              15 (2)
                2782 BINARY_AND
                2784 LOAD_CONST               8 (1)
                2786 BINARY_RSHIFT
                2788 LOAD_CONST               5 (0)
                2790 COMPARE_OP               2 (==)
                2792 EXTENDED_ARG            11
                2794 JUMP_IF_FALSE_OR_POP  2818
                2796 LOAD_GLOBAL              0 (ord)
                2798 LOAD_FAST                0 (NYYZYQYFTG)
                2800 LOAD_CONST              41 (21)
                2802 BINARY_SUBSCR
                2804 CALL_FUNCTION            1
                2806 LOAD_CONST               8 (1)
                2808 BINARY_AND
                2810 LOAD_CONST               5 (0)
                2812 BINARY_RSHIFT
                2814 LOAD_CONST               5 (0)
                2816 COMPARE_OP               2 (==)
             >> 2818 STORE_FAST               1 (BJYLPQQYPV)

42069695        2820 LOAD_FAST                1 (BJYLPQQYPV)
                2822 EXTENDED_ARG            11
                2824 JUMP_IF_FALSE_OR_POP  2840
                2826 LOAD_GLOBAL              0 (ord)
                2828 LOAD_FAST                0 (NYYZYQYFTG)
                2830 LOAD_CONST              30 (9)
                2832 BINARY_SUBSCR
                2834 CALL_FUNCTION            1
                2836 LOAD_CONST              42 (95)
                2838 COMPARE_OP               2 (==)
             >> 2840 STORE_FAST               1 (BJYLPQQYPV)

42069696        2842 LOAD_FAST                0 (NYYZYQYFTG)
                2844 LOAD_CONST               0 (None)
                2846 LOAD_CONST              10 (5)
                2848 BUILD_SLICE              2
                2850 BINARY_SUBSCR
                2852 LOAD_CONST              27 ('UMASS')
                2854 COMPARE_OP               3 (!=)
                2856 EXTENDED_ARG            11
                2858 POP_JUMP_IF_FALSE     2866

42069697        2860 LOAD_CONST              28 (False)
                2862 BUILD_LIST               1
                2864 RETURN_VALUE

42069698     >> 2866 LOAD_FAST                1 (BJYLPQQYPV)
                2868 EXTENDED_ARG            11
                2870 JUMP_IF_FALSE_OR_POP  2886
                2872 LOAD_GLOBAL              0 (ord)
                2874 LOAD_FAST                0 (NYYZYQYFTG)
                2876 LOAD_CONST              43 (25)
                2878 BINARY_SUBSCR
                2880 CALL_FUNCTION            1
                2882 LOAD_CONST              44 (97)
                2884 COMPARE_OP               2 (==)
             >> 2886 STORE_FAST               1 (BJYLPQQYPV)

42069699        2888 LOAD_FAST                1 (BJYLPQQYPV)
                2890 EXTENDED_ARG            11
                2892 JUMP_IF_FALSE_OR_POP  2942
                2894 LOAD_GLOBAL              0 (ord)
                2896 LOAD_FAST                0 (NYYZYQYFTG)
                2898 LOAD_CONST              12 (4)
                2900 BINARY_SUBSCR
                2902 CALL_FUNCTION            1
                2904 LOAD_CONST              21 (240)
                2906 BINARY_AND
                2908 LOAD_CONST              32 (80)
                2910 BINARY_XOR
                2912 LOAD_CONST               5 (0)
                2914 COMPARE_OP               2 (==)
                2916 EXTENDED_ARG            11
                2918 JUMP_IF_FALSE_OR_POP  2942
                2920 LOAD_GLOBAL              0 (ord)
                2922 LOAD_FAST                0 (NYYZYQYFTG)
                2924 LOAD_CONST              12 (4)
                2926 BINARY_SUBSCR
                2928 CALL_FUNCTION            1
                2930 LOAD_CONST              23 (15)
                2932 BINARY_AND
                2934 LOAD_CONST              14 (3)
                2936 BINARY_XOR
                2938 LOAD_CONST               5 (0)
                2940 COMPARE_OP               2 (==)
             >> 2942 STORE_FAST               1 (BJYLPQQYPV)

42069700        2944 LOAD_FAST                1 (BJYLPQQYPV)
                2946 EXTENDED_ARG            11
                2948 JUMP_IF_FALSE_OR_POP  2964
                2950 LOAD_GLOBAL              0 (ord)
                2952 LOAD_FAST                0 (NYYZYQYFTG)
                2954 LOAD_CONST              45 (33)
                2956 BINARY_SUBSCR
                2958 CALL_FUNCTION            1
                2960 LOAD_CONST              46 (105)
                2962 COMPARE_OP               2 (==)
             >> 2964 STORE_FAST               1 (BJYLPQQYPV)

42069701        2966 LOAD_FAST                1 (BJYLPQQYPV)
                2968 EXTENDED_ARG            12
                2970 JUMP_IF_FALSE_OR_POP  3176
                2972 LOAD_GLOBAL              0 (ord)
                2974 LOAD_FAST                0 (NYYZYQYFTG)
                2976 LOAD_CONST              47 (36)
                2978 BINARY_SUBSCR
                2980 CALL_FUNCTION            1
                2982 LOAD_CONST               3 (128)
                2984 BINARY_AND
                2986 LOAD_CONST               4 (7)
                2988 BINARY_RSHIFT
                2990 LOAD_CONST               5 (0)
                2992 COMPARE_OP               2 (==)
                2994 EXTENDED_ARG            12
                2996 JUMP_IF_FALSE_OR_POP  3176
                2998 LOAD_GLOBAL              0 (ord)
                3000 LOAD_FAST                0 (NYYZYQYFTG)
                3002 LOAD_CONST              47 (36)
                3004 BINARY_SUBSCR
                3006 CALL_FUNCTION            1
                3008 LOAD_CONST               6 (64)
                3010 BINARY_AND
                3012 LOAD_CONST               7 (6)
                3014 BINARY_RSHIFT
                3016 LOAD_CONST               8 (1)
                3018 COMPARE_OP               2 (==)
                3020 EXTENDED_ARG            12
                3022 JUMP_IF_FALSE_OR_POP  3176
                3024 LOAD_GLOBAL              0 (ord)
                3026 LOAD_FAST                0 (NYYZYQYFTG)
                3028 LOAD_CONST              47 (36)
                3030 BINARY_SUBSCR
                3032 CALL_FUNCTION            1
                3034 LOAD_CONST               9 (32)
                3036 BINARY_AND
                3038 LOAD_CONST              10 (5)
                3040 BINARY_RSHIFT
                3042 LOAD_CONST               8 (1)
                3044 COMPARE_OP               2 (==)
                3046 EXTENDED_ARG            12
                3048 JUMP_IF_FALSE_OR_POP  3176
                3050 LOAD_GLOBAL              0 (ord)
                3052 LOAD_FAST                0 (NYYZYQYFTG)
                3054 LOAD_CONST              47 (36)
                3056 BINARY_SUBSCR
                3058 CALL_FUNCTION            1
                3060 LOAD_CONST              11 (16)
                3062 BINARY_AND
                3064 LOAD_CONST              12 (4)
                3066 BINARY_RSHIFT
                3068 LOAD_CONST               8 (1)
                3070 COMPARE_OP               2 (==)
                3072 EXTENDED_ARG            12
                3074 JUMP_IF_FALSE_OR_POP  3176
                3076 LOAD_GLOBAL              0 (ord)
                3078 LOAD_FAST                0 (NYYZYQYFTG)
                3080 LOAD_CONST              47 (36)
                3082 BINARY_SUBSCR
                3084 CALL_FUNCTION            1
                3086 LOAD_CONST              13 (8)
                3088 BINARY_AND
                3090 LOAD_CONST              14 (3)
                3092 BINARY_RSHIFT
                3094 LOAD_CONST               8 (1)
                3096 COMPARE_OP               2 (==)
                3098 EXTENDED_ARG            12
                3100 JUMP_IF_FALSE_OR_POP  3176
                3102 LOAD_GLOBAL              0 (ord)
                3104 LOAD_FAST                0 (NYYZYQYFTG)
                3106 LOAD_CONST              47 (36)
                3108 BINARY_SUBSCR
                3110 CALL_FUNCTION            1
                3112 LOAD_CONST              12 (4)
                3114 BINARY_AND
                3116 LOAD_CONST              15 (2)
                3118 BINARY_RSHIFT
                3120 LOAD_CONST               8 (1)
                3122 COMPARE_OP               2 (==)
                3124 EXTENDED_ARG            12
                3126 JUMP_IF_FALSE_OR_POP  3176
                3128 LOAD_GLOBAL              0 (ord)
                3130 LOAD_FAST                0 (NYYZYQYFTG)
                3132 LOAD_CONST              47 (36)
                3134 BINARY_SUBSCR
                3136 CALL_FUNCTION            1
                3138 LOAD_CONST              15 (2)
                3140 BINARY_AND
                3142 LOAD_CONST               8 (1)
                3144 BINARY_RSHIFT
                3146 LOAD_CONST               5 (0)
                3148 COMPARE_OP               2 (==)
                3150 EXTENDED_ARG            12
                3152 JUMP_IF_FALSE_OR_POP  3176
                3154 LOAD_GLOBAL              0 (ord)
                3156 LOAD_FAST                0 (NYYZYQYFTG)
                3158 LOAD_CONST              47 (36)
                3160 BINARY_SUBSCR
                3162 CALL_FUNCTION            1
                3164 LOAD_CONST               8 (1)
                3166 BINARY_AND
                3168 LOAD_CONST               5 (0)
                3170 BINARY_RSHIFT
                3172 LOAD_CONST               8 (1)
                3174 COMPARE_OP               2 (==)
             >> 3176 STORE_FAST               1 (BJYLPQQYPV)

42069702        3178 LOAD_FAST                1 (BJYLPQQYPV)
                3180 EXTENDED_ARG            12
                3182 JUMP_IF_FALSE_OR_POP  3198
                3184 LOAD_GLOBAL              0 (ord)
                3186 LOAD_FAST                0 (NYYZYQYFTG)
                3188 LOAD_CONST              14 (3)
                3190 BINARY_SUBSCR
                3192 CALL_FUNCTION            1
                3194 LOAD_CONST              48 (83)
                3196 COMPARE_OP               2 (==)
             >> 3198 STORE_FAST               1 (BJYLPQQYPV)

42069703        3200 LOAD_FAST                1 (BJYLPQQYPV)
                3202 EXTENDED_ARG            13
                3204 JUMP_IF_FALSE_OR_POP  3410
                3206 LOAD_GLOBAL              0 (ord)
                3208 LOAD_FAST                0 (NYYZYQYFTG)
                3210 LOAD_CONST              49 (34)
                3212 BINARY_SUBSCR
                3214 CALL_FUNCTION            1
                3216 LOAD_CONST               3 (128)
                3218 BINARY_AND
                3220 LOAD_CONST               4 (7)
                3222 BINARY_RSHIFT
                3224 LOAD_CONST               5 (0)
                3226 COMPARE_OP               2 (==)
                3228 EXTENDED_ARG            13
                3230 JUMP_IF_FALSE_OR_POP  3410
                3232 LOAD_GLOBAL              0 (ord)
                3234 LOAD_FAST                0 (NYYZYQYFTG)
                3236 LOAD_CONST              49 (34)
                3238 BINARY_SUBSCR
                3240 CALL_FUNCTION            1
                3242 LOAD_CONST               6 (64)
                3244 BINARY_AND
                3246 LOAD_CONST               7 (6)
                3248 BINARY_RSHIFT
                3250 LOAD_CONST               8 (1)
                3252 COMPARE_OP               2 (==)
                3254 EXTENDED_ARG            13
                3256 JUMP_IF_FALSE_OR_POP  3410
                3258 LOAD_GLOBAL              0 (ord)
                3260 LOAD_FAST                0 (NYYZYQYFTG)
                3262 LOAD_CONST              49 (34)
                3264 BINARY_SUBSCR
                3266 CALL_FUNCTION            1
                3268 LOAD_CONST               9 (32)
                3270 BINARY_AND
                3272 LOAD_CONST              10 (5)
                3274 BINARY_RSHIFT
                3276 LOAD_CONST               8 (1)
                3278 COMPARE_OP               2 (==)
                3280 EXTENDED_ARG            13
                3282 JUMP_IF_FALSE_OR_POP  3410
                3284 LOAD_GLOBAL              0 (ord)
                3286 LOAD_FAST                0 (NYYZYQYFTG)
                3288 LOAD_CONST              49 (34)
                3290 BINARY_SUBSCR
                3292 CALL_FUNCTION            1
                3294 LOAD_CONST              11 (16)
                3296 BINARY_AND
                3298 LOAD_CONST              12 (4)
                3300 BINARY_RSHIFT
                3302 LOAD_CONST               5 (0)
                3304 COMPARE_OP               2 (==)
                3306 EXTENDED_ARG            13
                3308 JUMP_IF_FALSE_OR_POP  3410
                3310 LOAD_GLOBAL              0 (ord)
                3312 LOAD_FAST                0 (NYYZYQYFTG)
                3314 LOAD_CONST              49 (34)
                3316 BINARY_SUBSCR
                3318 CALL_FUNCTION            1
                3320 LOAD_CONST              13 (8)
                3322 BINARY_AND
                3324 LOAD_CONST              14 (3)
                3326 BINARY_RSHIFT
                3328 LOAD_CONST               8 (1)
                3330 COMPARE_OP               2 (==)
                3332 EXTENDED_ARG            13
                3334 JUMP_IF_FALSE_OR_POP  3410
                3336 LOAD_GLOBAL              0 (ord)
                3338 LOAD_FAST                0 (NYYZYQYFTG)
                3340 LOAD_CONST              49 (34)
                3342 BINARY_SUBSCR
                3344 CALL_FUNCTION            1
                3346 LOAD_CONST              12 (4)
                3348 BINARY_AND
                3350 LOAD_CONST              15 (2)
                3352 BINARY_RSHIFT
                3354 LOAD_CONST               8 (1)
                3356 COMPARE_OP               2 (==)
                3358 EXTENDED_ARG            13
                3360 JUMP_IF_FALSE_OR_POP  3410
                3362 LOAD_GLOBAL              0 (ord)
                3364 LOAD_FAST                0 (NYYZYQYFTG)
                3366 LOAD_CONST              49 (34)
                3368 BINARY_SUBSCR
                3370 CALL_FUNCTION            1
                3372 LOAD_CONST              15 (2)
                3374 BINARY_AND
                3376 LOAD_CONST               8 (1)
                3378 BINARY_RSHIFT
                3380 LOAD_CONST               8 (1)
                3382 COMPARE_OP               2 (==)
                3384 EXTENDED_ARG            13
                3386 JUMP_IF_FALSE_OR_POP  3410
                3388 LOAD_GLOBAL              0 (ord)
                3390 LOAD_FAST                0 (NYYZYQYFTG)
                3392 LOAD_CONST              49 (34)
                3394 BINARY_SUBSCR
                3396 CALL_FUNCTION            1
                3398 LOAD_CONST               8 (1)
                3400 BINARY_AND
                3402 LOAD_CONST               5 (0)
                3404 BINARY_RSHIFT
                3406 LOAD_CONST               5 (0)
                3408 COMPARE_OP               2 (==)
             >> 3410 STORE_FAST               1 (BJYLPQQYPV)

42069704        3412 LOAD_FAST                1 (BJYLPQQYPV)
                3414 EXTENDED_ARG            13
                3416 JUMP_IF_FALSE_OR_POP  3432
                3418 LOAD_GLOBAL              0 (ord)
                3420 LOAD_FAST                0 (NYYZYQYFTG)
                3422 LOAD_CONST               9 (32)
                3424 BINARY_SUBSCR
                3426 CALL_FUNCTION            1
                3428 LOAD_CONST              40 (103)
                3430 COMPARE_OP               2 (==)
             >> 3432 STORE_FAST               1 (BJYLPQQYPV)

42069705        3434 LOAD_FAST                1 (BJYLPQQYPV)
                3436 EXTENDED_ARG            14
                3438 JUMP_IF_FALSE_OR_POP  3644
                3440 LOAD_GLOBAL              0 (ord)
                3442 LOAD_FAST                0 (NYYZYQYFTG)
                3444 LOAD_CONST              50 (22)
                3446 BINARY_SUBSCR
                3448 CALL_FUNCTION            1
                3450 LOAD_CONST               3 (128)
                3452 BINARY_AND
                3454 LOAD_CONST               4 (7)
                3456 BINARY_RSHIFT
                3458 LOAD_CONST               5 (0)
                3460 COMPARE_OP               2 (==)
                3462 EXTENDED_ARG            14
                3464 JUMP_IF_FALSE_OR_POP  3644
                3466 LOAD_GLOBAL              0 (ord)
                3468 LOAD_FAST                0 (NYYZYQYFTG)
                3470 LOAD_CONST              50 (22)
                3472 BINARY_SUBSCR
                3474 CALL_FUNCTION            1
                3476 LOAD_CONST               6 (64)
                3478 BINARY_AND
                3480 LOAD_CONST               7 (6)
                3482 BINARY_RSHIFT
                3484 LOAD_CONST               8 (1)
                3486 COMPARE_OP               2 (==)
                3488 EXTENDED_ARG            14
                3490 JUMP_IF_FALSE_OR_POP  3644
                3492 LOAD_GLOBAL              0 (ord)
                3494 LOAD_FAST                0 (NYYZYQYFTG)
                3496 LOAD_CONST              50 (22)
                3498 BINARY_SUBSCR
                3500 CALL_FUNCTION            1
                3502 LOAD_CONST               9 (32)
                3504 BINARY_AND
                3506 LOAD_CONST              10 (5)
                3508 BINARY_RSHIFT
                3510 LOAD_CONST               8 (1)
                3512 COMPARE_OP               2 (==)
                3514 EXTENDED_ARG            14
                3516 JUMP_IF_FALSE_OR_POP  3644
                3518 LOAD_GLOBAL              0 (ord)
                3520 LOAD_FAST                0 (NYYZYQYFTG)
                3522 LOAD_CONST              50 (22)
                3524 BINARY_SUBSCR
                3526 CALL_FUNCTION            1
                3528 LOAD_CONST              11 (16)
                3530 BINARY_AND
                3532 LOAD_CONST              12 (4)
                3534 BINARY_RSHIFT
                3536 LOAD_CONST               5 (0)
                3538 COMPARE_OP               2 (==)
                3540 EXTENDED_ARG            14
                3542 JUMP_IF_FALSE_OR_POP  3644
                3544 LOAD_GLOBAL              0 (ord)
                3546 LOAD_FAST                0 (NYYZYQYFTG)
                3548 LOAD_CONST              50 (22)
                3550 BINARY_SUBSCR
                3552 CALL_FUNCTION            1
                3554 LOAD_CONST              13 (8)
                3556 BINARY_AND
                3558 LOAD_CONST              14 (3)
                3560 BINARY_RSHIFT
                3562 LOAD_CONST               8 (1)
                3564 COMPARE_OP               2 (==)
                3566 EXTENDED_ARG            14
                3568 JUMP_IF_FALSE_OR_POP  3644
                3570 LOAD_GLOBAL              0 (ord)
                3572 LOAD_FAST                0 (NYYZYQYFTG)
                3574 LOAD_CONST              50 (22)
                3576 BINARY_SUBSCR
                3578 CALL_FUNCTION            1
                3580 LOAD_CONST              12 (4)
                3582 BINARY_AND
                3584 LOAD_CONST              15 (2)
                3586 BINARY_RSHIFT
                3588 LOAD_CONST               5 (0)
                3590 COMPARE_OP               2 (==)
                3592 EXTENDED_ARG            14
                3594 JUMP_IF_FALSE_OR_POP  3644
                3596 LOAD_GLOBAL              0 (ord)
                3598 LOAD_FAST                0 (NYYZYQYFTG)
                3600 LOAD_CONST              50 (22)
                3602 BINARY_SUBSCR
                3604 CALL_FUNCTION            1
                3606 LOAD_CONST              15 (2)
                3608 BINARY_AND
                3610 LOAD_CONST               8 (1)
                3612 BINARY_RSHIFT
                3614 LOAD_CONST               5 (0)
                3616 COMPARE_OP               2 (==)
                3618 EXTENDED_ARG            14
                3620 JUMP_IF_FALSE_OR_POP  3644
                3622 LOAD_GLOBAL              0 (ord)
                3624 LOAD_FAST                0 (NYYZYQYFTG)
                3626 LOAD_CONST              50 (22)
                3628 BINARY_SUBSCR
                3630 CALL_FUNCTION            1
                3632 LOAD_CONST               8 (1)
                3634 BINARY_AND
                3636 LOAD_CONST               5 (0)
                3638 BINARY_RSHIFT
                3640 LOAD_CONST               8 (1)
                3642 COMPARE_OP               2 (==)
             >> 3644 STORE_FAST               1 (BJYLPQQYPV)

42069706        3646 LOAD_FAST                1 (BJYLPQQYPV)
                3648 EXTENDED_ARG            14
                3650 JUMP_IF_FALSE_OR_POP  3700
                3652 LOAD_GLOBAL              0 (ord)
                3654 LOAD_FAST                0 (NYYZYQYFTG)
                3656 LOAD_CONST              13 (8)
                3658 BINARY_SUBSCR
                3660 CALL_FUNCTION            1
                3662 LOAD_CONST              21 (240)
                3664 BINARY_AND
                3666 LOAD_CONST              22 (96)
                3668 BINARY_XOR
                3670 LOAD_CONST               5 (0)
                3672 COMPARE_OP               2 (==)
                3674 EXTENDED_ARG            14
                3676 JUMP_IF_FALSE_OR_POP  3700
                3678 LOAD_GLOBAL              0 (ord)
                3680 LOAD_FAST                0 (NYYZYQYFTG)
                3682 LOAD_CONST              13 (8)
                3684 BINARY_SUBSCR
                3686 CALL_FUNCTION            1
                3688 LOAD_CONST              23 (15)
                3690 BINARY_AND
                3692 LOAD_CONST              15 (2)
                3694 BINARY_XOR
                3696 LOAD_CONST               5 (0)
                3698 COMPARE_OP               2 (==)
             >> 3700 STORE_FAST               1 (BJYLPQQYPV)

42069707        3702 LOAD_FAST                1 (BJYLPQQYPV)
                3704 EXTENDED_ARG            15
                3706 JUMP_IF_FALSE_OR_POP  3912
                3708 LOAD_GLOBAL              0 (ord)
                3710 LOAD_FAST                0 (NYYZYQYFTG)
                3712 LOAD_CONST              51 (27)
                3714 BINARY_SUBSCR
                3716 CALL_FUNCTION            1
                3718 LOAD_CONST               3 (128)
                3720 BINARY_AND
                3722 LOAD_CONST               4 (7)
                3724 BINARY_RSHIFT
                3726 LOAD_CONST               5 (0)
                3728 COMPARE_OP               2 (==)
                3730 EXTENDED_ARG            15
                3732 JUMP_IF_FALSE_OR_POP  3912
                3734 LOAD_GLOBAL              0 (ord)
                3736 LOAD_FAST                0 (NYYZYQYFTG)
                3738 LOAD_CONST              51 (27)
                3740 BINARY_SUBSCR
                3742 CALL_FUNCTION            1
                3744 LOAD_CONST               6 (64)
                3746 BINARY_AND
                3748 LOAD_CONST               7 (6)
                3750 BINARY_RSHIFT
                3752 LOAD_CONST               5 (0)
                3754 COMPARE_OP               2 (==)
                3756 EXTENDED_ARG            15
                3758 JUMP_IF_FALSE_OR_POP  3912
                3760 LOAD_GLOBAL              0 (ord)
                3762 LOAD_FAST                0 (NYYZYQYFTG)
                3764 LOAD_CONST              51 (27)
                3766 BINARY_SUBSCR
                3768 CALL_FUNCTION            1
                3770 LOAD_CONST               9 (32)
                3772 BINARY_AND
                3774 LOAD_CONST              10 (5)
                3776 BINARY_RSHIFT
                3778 LOAD_CONST               8 (1)
                3780 COMPARE_OP               2 (==)
                3782 EXTENDED_ARG            15
                3784 JUMP_IF_FALSE_OR_POP  3912
                3786 LOAD_GLOBAL              0 (ord)
                3788 LOAD_FAST                0 (NYYZYQYFTG)
                3790 LOAD_CONST              51 (27)
                3792 BINARY_SUBSCR
                3794 CALL_FUNCTION            1
                3796 LOAD_CONST              11 (16)
                3798 BINARY_AND
                3800 LOAD_CONST              12 (4)
                3802 BINARY_RSHIFT
                3804 LOAD_CONST               8 (1)
                3806 COMPARE_OP               2 (==)
                3808 EXTENDED_ARG            15
                3810 JUMP_IF_FALSE_OR_POP  3912
                3812 LOAD_GLOBAL              0 (ord)
                3814 LOAD_FAST                0 (NYYZYQYFTG)
                3816 LOAD_CONST              51 (27)
                3818 BINARY_SUBSCR
                3820 CALL_FUNCTION            1
                3822 LOAD_CONST              13 (8)
                3824 BINARY_AND
                3826 LOAD_CONST              14 (3)
                3828 BINARY_RSHIFT
                3830 LOAD_CONST               5 (0)
                3832 COMPARE_OP               2 (==)
                3834 EXTENDED_ARG            15
                3836 JUMP_IF_FALSE_OR_POP  3912
                3838 LOAD_GLOBAL              0 (ord)
                3840 LOAD_FAST                0 (NYYZYQYFTG)
                3842 LOAD_CONST              51 (27)
                3844 BINARY_SUBSCR
                3846 CALL_FUNCTION            1
                3848 LOAD_CONST              12 (4)
                3850 BINARY_AND
                3852 LOAD_CONST              15 (2)
                3854 BINARY_RSHIFT
                3856 LOAD_CONST               5 (0)
                3858 COMPARE_OP               2 (==)
                3860 EXTENDED_ARG            15
                3862 JUMP_IF_FALSE_OR_POP  3912
                3864 LOAD_GLOBAL              0 (ord)
                3866 LOAD_FAST                0 (NYYZYQYFTG)
                3868 LOAD_CONST              51 (27)
                3870 BINARY_SUBSCR
                3872 CALL_FUNCTION            1
                3874 LOAD_CONST              15 (2)
                3876 BINARY_AND
                3878 LOAD_CONST               8 (1)
                3880 BINARY_RSHIFT
                3882 LOAD_CONST               8 (1)
                3884 COMPARE_OP               2 (==)
                3886 EXTENDED_ARG            15
                3888 JUMP_IF_FALSE_OR_POP  3912
                3890 LOAD_GLOBAL              0 (ord)
                3892 LOAD_FAST                0 (NYYZYQYFTG)
                3894 LOAD_CONST              51 (27)
                3896 BINARY_SUBSCR
                3898 CALL_FUNCTION            1
                3900 LOAD_CONST               8 (1)
                3902 BINARY_AND
                3904 LOAD_CONST               5 (0)
                3906 BINARY_RSHIFT
                3908 LOAD_CONST               8 (1)
                3910 COMPARE_OP               2 (==)
             >> 3912 STORE_FAST               1 (BJYLPQQYPV)

42069708        3914 LOAD_FAST                1 (BJYLPQQYPV)
                3916 EXTENDED_ARG            15
                3918 JUMP_IF_FALSE_OR_POP  3968
                3920 LOAD_GLOBAL              0 (ord)
                3922 LOAD_FAST                0 (NYYZYQYFTG)
                3924 LOAD_CONST              52 (10)
                3926 BINARY_SUBSCR
                3928 CALL_FUNCTION            1
                3930 LOAD_CONST              21 (240)
                3932 BINARY_AND
                3934 LOAD_CONST              22 (96)
                3936 BINARY_XOR
                3938 LOAD_CONST               5 (0)
                3940 COMPARE_OP               2 (==)
                3942 EXTENDED_ARG            15
                3944 JUMP_IF_FALSE_OR_POP  3968
                3946 LOAD_GLOBAL              0 (ord)
                3948 LOAD_FAST                0 (NYYZYQYFTG)
                3950 LOAD_CONST              52 (10)
                3952 BINARY_SUBSCR
                3954 CALL_FUNCTION            1
                3956 LOAD_CONST              23 (15)
                3958 BINARY_AND
                3960 LOAD_CONST               4 (7)
                3962 BINARY_XOR
                3964 LOAD_CONST               5 (0)
                3966 COMPARE_OP               2 (==)
             >> 3968 STORE_FAST               1 (BJYLPQQYPV)

42069709        3970 LOAD_FAST                1 (BJYLPQQYPV)
                3972 EXTENDED_ARG            16
                3974 JUMP_IF_FALSE_OR_POP  4180
                3976 LOAD_GLOBAL              0 (ord)
                3978 LOAD_FAST                0 (NYYZYQYFTG)
                3980 LOAD_CONST              11 (16)
                3982 BINARY_SUBSCR
                3984 CALL_FUNCTION            1
                3986 LOAD_CONST               3 (128)
                3988 BINARY_AND
                3990 LOAD_CONST               4 (7)
                3992 BINARY_RSHIFT
                3994 LOAD_CONST               5 (0)
                3996 COMPARE_OP               2 (==)
                3998 EXTENDED_ARG            16
                4000 JUMP_IF_FALSE_OR_POP  4180
                4002 LOAD_GLOBAL              0 (ord)
                4004 LOAD_FAST                0 (NYYZYQYFTG)
                4006 LOAD_CONST              11 (16)
                4008 BINARY_SUBSCR
                4010 CALL_FUNCTION            1
                4012 LOAD_CONST               6 (64)
                4014 BINARY_AND
                4016 LOAD_CONST               7 (6)
                4018 BINARY_RSHIFT
                4020 LOAD_CONST               5 (0)
                4022 COMPARE_OP               2 (==)
                4024 EXTENDED_ARG            16
                4026 JUMP_IF_FALSE_OR_POP  4180
                4028 LOAD_GLOBAL              0 (ord)
                4030 LOAD_FAST                0 (NYYZYQYFTG)
                4032 LOAD_CONST              11 (16)
                4034 BINARY_SUBSCR
                4036 CALL_FUNCTION            1
                4038 LOAD_CONST               9 (32)
                4040 BINARY_AND
                4042 LOAD_CONST              10 (5)
                4044 BINARY_RSHIFT
                4046 LOAD_CONST               8 (1)
                4048 COMPARE_OP               2 (==)
                4050 EXTENDED_ARG            16
                4052 JUMP_IF_FALSE_OR_POP  4180
                4054 LOAD_GLOBAL              0 (ord)
                4056 LOAD_FAST                0 (NYYZYQYFTG)
                4058 LOAD_CONST              11 (16)
                4060 BINARY_SUBSCR
                4062 CALL_FUNCTION            1
                4064 LOAD_CONST              11 (16)
                4066 BINARY_AND
                4068 LOAD_CONST              12 (4)
                4070 BINARY_RSHIFT
                4072 LOAD_CONST               8 (1)
                4074 COMPARE_OP               2 (==)
                4076 EXTENDED_ARG            16
                4078 JUMP_IF_FALSE_OR_POP  4180
                4080 LOAD_GLOBAL              0 (ord)
                4082 LOAD_FAST                0 (NYYZYQYFTG)
                4084 LOAD_CONST              11 (16)
                4086 BINARY_SUBSCR
                4088 CALL_FUNCTION            1
                4090 LOAD_CONST              13 (8)
                4092 BINARY_AND
                4094 LOAD_CONST              14 (3)
                4096 BINARY_RSHIFT
                4098 LOAD_CONST               5 (0)
                4100 COMPARE_OP               2 (==)
                4102 EXTENDED_ARG            16
                4104 JUMP_IF_FALSE_OR_POP  4180
                4106 LOAD_GLOBAL              0 (ord)
                4108 LOAD_FAST                0 (NYYZYQYFTG)
                4110 LOAD_CONST              11 (16)
                4112 BINARY_SUBSCR
                4114 CALL_FUNCTION            1
                4116 LOAD_CONST              12 (4)
                4118 BINARY_AND
                4120 LOAD_CONST              15 (2)
                4122 BINARY_RSHIFT
                4124 LOAD_CONST               5 (0)
                4126 COMPARE_OP               2 (==)
                4128 EXTENDED_ARG            16
                4130 JUMP_IF_FALSE_OR_POP  4180
                4132 LOAD_GLOBAL              0 (ord)
                4134 LOAD_FAST                0 (NYYZYQYFTG)
                4136 LOAD_CONST              11 (16)
                4138 BINARY_SUBSCR
                4140 CALL_FUNCTION            1
                4142 LOAD_CONST              15 (2)
                4144 BINARY_AND
                4146 LOAD_CONST               8 (1)
                4148 BINARY_RSHIFT
                4150 LOAD_CONST               8 (1)
                4152 COMPARE_OP               2 (==)
                4154 EXTENDED_ARG            16
                4156 JUMP_IF_FALSE_OR_POP  4180
                4158 LOAD_GLOBAL              0 (ord)
                4160 LOAD_FAST                0 (NYYZYQYFTG)
                4162 LOAD_CONST              11 (16)
                4164 BINARY_SUBSCR
                4166 CALL_FUNCTION            1
                4168 LOAD_CONST               8 (1)
                4170 BINARY_AND
                4172 LOAD_CONST               5 (0)
                4174 BINARY_RSHIFT
                4176 LOAD_CONST               8 (1)
                4178 COMPARE_OP               2 (==)
             >> 4180 STORE_FAST               1 (BJYLPQQYPV)

42069710        4182 LOAD_FAST                1 (BJYLPQQYPV)
                4184 EXTENDED_ARG            17
                4186 JUMP_IF_FALSE_OR_POP  4392
                4188 LOAD_GLOBAL              0 (ord)
                4190 LOAD_FAST                0 (NYYZYQYFTG)
                4192 LOAD_CONST              53 (18)
                4194 BINARY_SUBSCR
                4196 CALL_FUNCTION            1
                4198 LOAD_CONST               3 (128)
                4200 BINARY_AND
                4202 LOAD_CONST               4 (7)
                4204 BINARY_RSHIFT
                4206 LOAD_CONST               5 (0)
                4208 COMPARE_OP               2 (==)
                4210 EXTENDED_ARG            17
                4212 JUMP_IF_FALSE_OR_POP  4392
                4214 LOAD_GLOBAL              0 (ord)
                4216 LOAD_FAST                0 (NYYZYQYFTG)
                4218 LOAD_CONST              53 (18)
                4220 BINARY_SUBSCR
                4222 CALL_FUNCTION            1
                4224 LOAD_CONST               6 (64)
                4226 BINARY_AND
                4228 LOAD_CONST               7 (6)
                4230 BINARY_RSHIFT
                4232 LOAD_CONST               8 (1)
                4234 COMPARE_OP               2 (==)
                4236 EXTENDED_ARG            17
                4238 JUMP_IF_FALSE_OR_POP  4392
                4240 LOAD_GLOBAL              0 (ord)
                4242 LOAD_FAST                0 (NYYZYQYFTG)
                4244 LOAD_CONST              53 (18)
                4246 BINARY_SUBSCR
                4248 CALL_FUNCTION            1
                4250 LOAD_CONST               9 (32)
                4252 BINARY_AND
                4254 LOAD_CONST              10 (5)
                4256 BINARY_RSHIFT
                4258 LOAD_CONST               8 (1)
                4260 COMPARE_OP               2 (==)
                4262 EXTENDED_ARG            17
                4264 JUMP_IF_FALSE_OR_POP  4392
                4266 LOAD_GLOBAL              0 (ord)
                4268 LOAD_FAST                0 (NYYZYQYFTG)
                4270 LOAD_CONST              53 (18)
                4272 BINARY_SUBSCR
                4274 CALL_FUNCTION            1
                4276 LOAD_CONST              11 (16)
                4278 BINARY_AND
                4280 LOAD_CONST              12 (4)
                4282 BINARY_RSHIFT
                4284 LOAD_CONST               5 (0)
                4286 COMPARE_OP               2 (==)
                4288 EXTENDED_ARG            17
                4290 JUMP_IF_FALSE_OR_POP  4392
                4292 LOAD_GLOBAL              0 (ord)
                4294 LOAD_FAST                0 (NYYZYQYFTG)
                4296 LOAD_CONST              53 (18)
                4298 BINARY_SUBSCR
                4300 CALL_FUNCTION            1
                4302 LOAD_CONST              13 (8)
                4304 BINARY_AND
                4306 LOAD_CONST              14 (3)
                4308 BINARY_RSHIFT
                4310 LOAD_CONST               8 (1)
                4312 COMPARE_OP               2 (==)
                4314 EXTENDED_ARG            17
                4316 JUMP_IF_FALSE_OR_POP  4392
                4318 LOAD_GLOBAL              0 (ord)
                4320 LOAD_FAST                0 (NYYZYQYFTG)
                4322 LOAD_CONST              53 (18)
                4324 BINARY_SUBSCR
                4326 CALL_FUNCTION            1
                4328 LOAD_CONST              12 (4)
                4330 BINARY_AND
                4332 LOAD_CONST              15 (2)
                4334 BINARY_RSHIFT
                4336 LOAD_CONST               8 (1)
                4338 COMPARE_OP               2 (==)
                4340 EXTENDED_ARG            17
                4342 JUMP_IF_FALSE_OR_POP  4392
                4344 LOAD_GLOBAL              0 (ord)
                4346 LOAD_FAST                0 (NYYZYQYFTG)
                4348 LOAD_CONST              53 (18)
                4350 BINARY_SUBSCR
                4352 CALL_FUNCTION            1
                4354 LOAD_CONST              15 (2)
                4356 BINARY_AND
                4358 LOAD_CONST               8 (1)
                4360 BINARY_RSHIFT
                4362 LOAD_CONST               8 (1)
                4364 COMPARE_OP               2 (==)
                4366 EXTENDED_ARG            17
                4368 JUMP_IF_FALSE_OR_POP  4392
                4370 LOAD_GLOBAL              0 (ord)
                4372 LOAD_FAST                0 (NYYZYQYFTG)
                4374 LOAD_CONST              53 (18)
                4376 BINARY_SUBSCR
                4378 CALL_FUNCTION            1
                4380 LOAD_CONST               8 (1)
                4382 BINARY_AND
                4384 LOAD_CONST               5 (0)
                4386 BINARY_RSHIFT
                4388 LOAD_CONST               5 (0)
                4390 COMPARE_OP               2 (==)
             >> 4392 STORE_FAST               1 (BJYLPQQYPV)

42069711        4394 LOAD_FAST                1 (BJYLPQQYPV)
                4396 EXTENDED_ARG            17
                4398 JUMP_IF_FALSE_OR_POP  4414
                4400 LOAD_GLOBAL              0 (ord)
                4402 LOAD_FAST                0 (NYYZYQYFTG)
                4404 LOAD_CONST               8 (1)
                4406 BINARY_SUBSCR
                4408 CALL_FUNCTION            1
                4410 LOAD_CONST              54 (77)
                4412 COMPARE_OP               2 (==)
             >> 4414 STORE_FAST               1 (BJYLPQQYPV)

42069712        4416 LOAD_FAST                1 (BJYLPQQYPV)
                4418 EXTENDED_ARG            17
                4420 JUMP_IF_FALSE_OR_POP  4470
                4422 LOAD_GLOBAL              0 (ord)
                4424 LOAD_FAST                0 (NYYZYQYFTG)
                4426 LOAD_CONST              15 (2)
                4428 BINARY_SUBSCR
                4430 CALL_FUNCTION            1
                4432 LOAD_CONST              21 (240)
                4434 BINARY_AND
                4436 LOAD_CONST               6 (64)
                4438 BINARY_XOR
                4440 LOAD_CONST               5 (0)
                4442 COMPARE_OP               2 (==)
                4444 EXTENDED_ARG            17
                4446 JUMP_IF_FALSE_OR_POP  4470
                4448 LOAD_GLOBAL              0 (ord)
                4450 LOAD_FAST                0 (NYYZYQYFTG)
                4452 LOAD_CONST              15 (2)
                4454 BINARY_SUBSCR
                4456 CALL_FUNCTION            1
                4458 LOAD_CONST              23 (15)
                4460 BINARY_AND
                4462 LOAD_CONST               8 (1)
                4464 BINARY_XOR
                4466 LOAD_CONST               5 (0)
                4468 COMPARE_OP               2 (==)
             >> 4470 STORE_FAST               1 (BJYLPQQYPV)

42069713        4472 LOAD_FAST                1 (BJYLPQQYPV)
                4474 EXTENDED_ARG            17
                4476 JUMP_IF_FALSE_OR_POP  4526
                4478 LOAD_GLOBAL              0 (ord)
                4480 LOAD_FAST                0 (NYYZYQYFTG)
                4482 LOAD_CONST              55 (11)
                4484 BINARY_SUBSCR
                4486 CALL_FUNCTION            1
                4488 LOAD_CONST              21 (240)
                4490 BINARY_AND
                4492 LOAD_CONST              22 (96)
                4494 BINARY_XOR
                4496 LOAD_CONST               5 (0)
                4498 COMPARE_OP               2 (==)
                4500 EXTENDED_ARG            17
                4502 JUMP_IF_FALSE_OR_POP  4526
                4504 LOAD_GLOBAL              0 (ord)
                4506 LOAD_FAST                0 (NYYZYQYFTG)
                4508 LOAD_CONST              55 (11)
                4510 BINARY_SUBSCR
                4512 CALL_FUNCTION            1
                4514 LOAD_CONST              23 (15)
                4516 BINARY_AND
                4518 LOAD_CONST              12 (4)
                4520 BINARY_XOR
                4522 LOAD_CONST               5 (0)
                4524 COMPARE_OP               2 (==)
             >> 4526 STORE_FAST               1 (BJYLPQQYPV)

42069714        4528 LOAD_GLOBAL              0 (ord)
                4530 LOAD_FAST                0 (NYYZYQYFTG)
                4532 LOAD_CONST               5 (0)
                4534 BINARY_SUBSCR
                4536 CALL_FUNCTION            1
                4538 LOAD_CONST              21 (240)
                4540 BINARY_AND
                4542 LOAD_CONST              18 (29)
                4544 COMPARE_OP               2 (==)
                4546 EXTENDED_ARG            17
                4548 POP_JUMP_IF_FALSE     4556

42069715        4550 LOAD_CONST              56 (65)
                4552 STORE_FAST               2 (SEMCZBFUBY)
                4554 JUMP_FORWARD             4 (to 4560)

42069717     >> 4556 LOAD_CONST               7 (6)
                4558 STORE_FAST               2 (SEMCZBFUBY)

42069718     >> 4560 LOAD_FAST                0 (NYYZYQYFTG)
                4562 LOAD_CONST               0 (None)
                4564 LOAD_CONST              10 (5)
                4566 BUILD_SLICE              2
                4568 BINARY_SUBSCR
                4570 LOAD_CONST              27 ('UMASS')
                4572 COMPARE_OP               3 (!=)
                4574 EXTENDED_ARG            17
                4576 POP_JUMP_IF_FALSE     4584

42069719        4578 LOAD_CONST              28 (False)
                4580 BUILD_LIST               1
                4582 RETURN_VALUE

42069720     >> 4584 LOAD_FAST                1 (BJYLPQQYPV)
                4586 BUILD_LIST               1
                4588 STORE_FAST               1 (BJYLPQQYPV)

42069721        4590 LOAD_GLOBAL              2 (types)
                4592 LOAD_METHOD              3 (FunctionType)
                4594 LOAD_GLOBAL              2 (types)
                4596 LOAD_ATTR                4 (CodeType)
                4598 LOAD_GLOBAL              5 (pickle)
                4600 LOAD_METHOD              6 (loads)
                4602 LOAD_CONST              57 (b'\x80\x04\x95\xbf$\x00\x00\x00\x00\x00\x00]\x94(K\x01K\x00K\x00K\x04K\x06KCB\xe6\x0f\x00\x00d\x01}\x01|\x01o\xc6t\x00|\x00d\x02\x19\x00\x83\x01d\x03@\x00d\x04?\x00d\x05k\x02o\xc6t\x00|\x00d\x02\x19\x00\x83\x01d\x06@\x00d\x07?\x00d\x08k\x02o\xc6t\x00|\x00d\x02\x19\x00\x83\x01d\t@\x00d\n?\x00d\x08k\x02o\xc6t\x00|\x00d\x02\x19\x00\x83\x01d\x0b@\x00d\x0c?\x00d\x05k\x02o\xc6t\x00|\x00d\x02\x19\x00\x83\x01d\r@\x00d\x0e?\x00d\x08k\x02o\xc6t\x00|\x00d\x02\x19\x00\x83\x01d\x0c@\x00d\x0f?\x00d\x05k\x02o\xc6t\x00|\x00d\x02\x19\x00\x83\x01d\x0f@\x00d\x08?\x00d\x05k\x02o\xc6t\x00|\x00d\x02\x19\x00\x83\x01d\x08@\x00d\x05?\x00d\x08k\x02}\x01|\x01o\xdat\x00|\x00d\n\x19\x00\x83\x01d\x10k\x02}\x01|\x01\x90\x01o\x12t\x00|\x00d\t\x19\x00\x83\x01d\x11@\x00d\x12A\x00d\x05k\x02\x90\x01o\x12t\x00|\x00d\t\x19\x00\x83\x01d\x13@\x00d\x14A\x00d\x05k\x02}\x01|\x01\x90\x01o\xe6t\x00|\x00d\x15\x19\x00\x83\x01d\x03@\x00d\x04?\x00d\x05k\x02\x90\x01o\xe6t\x00|\x00d\x15\x19\x00\x83\x01d\x06@\x00d\x07?\x00d\x08k\x02\x90\x01o\xe6t\x00|\x00d\x15\x19\x00\x83\x01d\t@\x00d\n?\x00d\x08k\x02\x90\x01o\xe6t\x00|\x00d\x15\x19\x00\x83\x01d\x0b@\x00d\x0c?\x00d\x05k\x02\x90\x01o\xe6t\x00|\x00d\x15\x19\x00\x83\x01d\r@\x00d\x0e?\x00d\x05k\x02\x90\x01o\xe6t\x00|\x00d\x15\x19\x00\x83\x01d\x0c@\x00d\x0f?\x00d\x05k\x02\x90\x01o\xe6t\x00|\x00d\x15\x19\x00\x83\x01d\x0f@\x00d\x08?\x00d\x08k\x02\x90\x01o\xe6t\x00|\x00d\x15\x19\x00\x83\x01d\x08@\x00d\x05?\x00d\x08k\x02}\x01|\x01\x90\x02o\x1et\x00|\x00d\x0f\x19\x00\x83\x01d\x11@\x00d\x06A\x00d\x05k\x02\x90\x02o\x1et\x00|\x00d\x0f\x19\x00\x83\x01d\x13@\x00d\x08A\x00d\x05k\x02}\x01|\x01\x90\x02oVt\x00|\x00d\x16\x19\x00\x83\x01d\x11@\x00d\x17A\x00d\x05k\x02\x90\x02oVt\x00|\x00d\x16\x19\x00\x83\x01d\x13@\x00d\x0cA\x00d\x05k\x02}\x01|\x01\x90\x03o*t\x00|\x00d\x0c\x19\x00\x83\x01d\x03@\x00d\x04?\x00d\x05k\x02\x90\x03o*t\x00|\x00d\x0c\x19\x00\x83\x01d\x06@\x00d\x07?\x00d\x08k\x02\x90\x03o*t\x00|\x00d\x0c\x19\x00\x83\x01d\t@\x00d\n?\x00d\x05k\x02\x90\x03o*t\x00|\x00d\x0c\x19\x00\x83\x01d\x0b@\x00d\x0c?\x00d\x08k\x02\x90\x03o*t\x00|\x00d\x0c\x19\x00\x83\x01d\r@\x00d\x0e?\x00d\x05k\x02\x90\x03o*t\x00|\x00d\x0c\x19\x00\x83\x01d\x0c@\x00d\x0f?\x00d\x05k\x02\x90\x03o*t\x00|\x00d\x0c\x19\x00\x83\x01d\x0f@\x00d\x08?\x00d\x08k\x02\x90\x03o*t\x00|\x00d\x0c\x19\x00\x83\x01d\x08@\x00d\x05?\x00d\x08k\x02}\x01|\x01\x90\x03o@t\x00|\x00d\x18\x19\x00\x83\x01d\x19k\x02}\x01|\x01\x90\x04o\x14t\x00|\x00d\x1a\x19\x00\x83\x01d\x03@\x00d\x04?\x00d\x05k\x02\x90\x04o\x14t\x00|\x00d\x1a\x19\x00\x83\x01d\x06@\x00d\x07?\x00d\x08k\x02\x90\x04o\x14t\x00|\x00d\x1a\x19\x00\x83\x01d\t@\x00d\n?\x00d\x08k\x02\x90\x04o\x14t\x00|\x00d\x1a\x19\x00\x83\x01d\x0b@\x00d\x0c?\x00d\x05k\x02\x90\x04o\x14t\x00|\x00d\x1a\x19\x00\x83\x01d\r@\x00d\x0e?\x00d\x05k\x02\x90\x04o\x14t\x00|\x00d\x1a\x19\x00\x83\x01d\x0c@\x00d\x0f?\x00d\x05k\x02\x90\x04o\x14t\x00|\x00d\x1a\x19\x00\x83\x01d\x0f@\x00d\x08?\x00d\x08k\x02\x90\x04o\x14t\x00|\x00d\x1a\x19\x00\x83\x01d\x08@\x00d\x05?\x00d\x08k\x02}\x01|\x01\x90\x04oLt\x00|\x00d\x1b\x19\x00\x83\x01d\x11@\x00d\x17A\x00d\x05k\x02\x90\x04oLt\x00|\x00d\x1b\x19\x00\x83\x01d\x13@\x00d\x14A\x00d\x05k\x02}\x01|\x01\x90\x04obt\x00|\x00d\x1c\x19\x00\x83\x01d\x1dk\x02}\x01|\x00d\x00d\n\x85\x02\x19\x00d\x1ek\x03\x90\x04r|d\x1fg\x01S\x00|\x01\x90\x04o\xb2t\x00|\x00d \x19\x00\x83\x01d\x11@\x00d!A\x00d\x05k\x02\x90\x04o\xb2t\x00|\x00d \x19\x00\x83\x01d\x13@\x00d\x13A\x00d\x05k\x02}\x01|\x01\x90\x05o\x86t\x00|\x00d\x13\x19\x00\x83\x01d\x03@\x00d\x04?\x00d\x05k\x02\x90\x05o\x86t\x00|\x00d\x13\x19\x00\x83\x01d\x06@\x00d\x07?\x00d\x08k\x02\x90\x05o\x86t\x00|\x00d\x13\x19\x00\x83\x01d\t@\x00d\n?\x00d\x08k\x02\x90\x05o\x86t\x00|\x00d\x13\x19\x00\x83\x01d\x0b@\x00d\x0c?\x00d\x05k\x02\x90\x05o\x86t\x00|\x00d\x13\x19\x00\x83\x01d\r@\x00d\x0e?\x00d\x05k\x02\x90\x05o\x86t\x00|\x00d\x13\x19\x00\x83\x01d\x0c@\x00d\x0f?\x00d\x05k\x02\x90\x05o\x86t\x00|\x00d\x13\x19\x00\x83\x01d\x0f@\x00d\x08?\x00d\x05k\x02\x90\x05o\x86t\x00|\x00d\x13\x19\x00\x83\x01d\x08@\x00d\x05?\x00d\x08k\x02}\x01|\x01\x90\x05o\x9ct\x00|\x00d"\x19\x00\x83\x01d#k\x02}\x01|\x01\x90\x05o\xb2t\x00|\x00d$\x19\x00\x83\x01d%k\x02}\x01|\x01\x90\x05o\xeat\x00|\x00d\x14\x19\x00\x83\x01d\x11@\x00d!A\x00d\x05k\x02\x90\x05o\xeat\x00|\x00d\x14\x19\x00\x83\x01d\x13@\x00d\x13A\x00d\x05k\x02}\x01t\x01\xa0\x01|\x00\xa1\x01\x01\x00|\x01\x90\x06o,t\x00|\x00d\x0e\x19\x00\x83\x01d\x11@\x00d!A\x00d\x05k\x02\x90\x06o,t\x00|\x00d\x0e\x19\x00\x83\x01d\x13@\x00d\x0eA\x00d\x05k\x02}\x01|\x01\x90\x07o\x00t\x00|\x00d&\x19\x00\x83\x01d\x03@\x00d\x04?\x00d\x05k\x02\x90\x07o\x00t\x00|\x00d&\x19\x00\x83\x01d\x06@\x00d\x07?\x00d\x05k\x02\x90\x07o\x00t\x00|\x00d&\x19\x00\x83\x01d\t@\x00d\n?\x00d\x08k\x02\x90\x07o\x00t\x00|\x00d&\x19\x00\x83\x01d\x0b@\x00d\x0c?\x00d\x08k\x02\x90\x07o\x00t\x00|\x00d&\x19\x00\x83\x01d\r@\x00d\x0e?\x00d\x05k\x02\x90\x07o\x00t\x00|\x00d&\x19\x00\x83\x01d\x0c@\x00d\x0f?\x00d\x05k\x02\x90\x07o\x00t\x00|\x00d&\x19\x00\x83\x01d\x0f@\x00d\x08?\x00d\x08k\x02\x90\x07o\x00t\x00|\x00d&\x19\x00\x83\x01d\x08@\x00d\x05?\x00d\x08k\x02}\x01|\x01\x90\x07o\xd4t\x00|\x00d\x05\x19\x00\x83\x01d\x03@\x00d\x04?\x00d\x05k\x02\x90\x07o\xd4t\x00|\x00d\x05\x19\x00\x83\x01d\x06@\x00d\x07?\x00d\x08k\x02\x90\x07o\xd4t\x00|\x00d\x05\x19\x00\x83\x01d\t@\x00d\n?\x00d\x05k\x02\x90\x07o\xd4t\x00|\x00d\x05\x19\x00\x83\x01d\x0b@\x00d\x0c?\x00d\x08k\x02\x90\x07o\xd4t\x00|\x00d\x05\x19\x00\x83\x01d\r@\x00d\x0e?\x00d\x05k\x02\x90\x07o\xd4t\x00|\x00d\x05\x19\x00\x83\x01d\x0c@\x00d\x0f?\x00d\x08k\x02\x90\x07o\xd4t\x00|\x00d\x05\x19\x00\x83\x01d\x0f@\x00d\x08?\x00d\x05k\x02\x90\x07o\xd4t\x00|\x00d\x05\x19\x00\x83\x01d\x08@\x00d\x05?\x00d\x08k\x02}\x01|\x01\x90\x07o\xeat\x00|\x00d\'\x19\x00\x83\x01d(k\x02}\x01|\x01\x90\x08o\x00t\x00|\x00d)\x19\x00\x83\x01d*k\x02}\x01|\x01\x90\x08o8t\x00|\x00d\x04\x19\x00\x83\x01d\x11@\x00d\x12A\x00d\x05k\x02\x90\x08o8t\x00|\x00d\x04\x19\x00\x83\x01d\x13@\x00d\rA\x00d\x05k\x02}\x01|\x01\x90\x08oNt\x00|\x00d+\x19\x00\x83\x01d,k\x02}\x01|\x01\x90\x08o\x86t\x00|\x00d-\x19\x00\x83\x01d\x11@\x00d\x12A\x00d\x05k\x02\x90\x08o\x86t\x00|\x00d-\x19\x00\x83\x01d\x13@\x00d\x07A\x00d\x05k\x02}\x01|\x01\x90\x08o\x9ct\x00|\x00d.\x19\x00\x83\x01d/k\x02}\x01|\x01\x90\x08o\xd4t\x00|\x00d0\x19\x00\x83\x01d\x11@\x00d\x12A\x00d\x05k\x02\x90\x08o\xd4t\x00|\x00d0\x19\x00\x83\x01d\x13@\x00d1A\x00d\x05k\x02}\x01t\x00|\x00d\x05\x19\x00\x83\x01d\x11@\x00d k\x02\x90\x08r\xf2d\n}\x02n\x04d$}\x02|\x01\x90\to\nt\x00|\x00d\r\x19\x00\x83\x01d\x19k\x02}\x01|\x01\x90\to t\x00|\x00d2\x19\x00\x83\x01d3k\x02}\x01|\x01\x90\to\xf4t\x00|\x00d\x08\x19\x00\x83\x01d\x03@\x00d\x04?\x00d\x05k\x02\x90\to\xf4t\x00|\x00d\x08\x19\x00\x83\x01d\x06@\x00d\x07?\x00d\x08k\x02\x90\to\xf4t\x00|\x00d\x08\x19\x00\x83\x01d\t@\x00d\n?\x00d\x05k\x02\x90\to\xf4t\x00|\x00d\x08\x19\x00\x83\x01d\x0b@\x00d\x0c?\x00d\x05k\x02\x90\to\xf4t\x00|\x00d\x08\x19\x00\x83\x01d\r@\x00d\x0e?\x00d\x08k\x02\x90\to\xf4t\x00|\x00d\x08\x19\x00\x83\x01d\x0c@\x00d\x0f?\x00d\x08k\x02\x90\to\xf4t\x00|\x00d\x08\x19\x00\x83\x01d\x0f@\x00d\x08?\x00d\x05k\x02\x90\to\xf4t\x00|\x00d\x08\x19\x00\x83\x01d\x08@\x00d\x05?\x00d\x08k\x02}\x01|\x01\x90\no,t\x00|\x00d4\x19\x00\x83\x01d\x11@\x00d5A\x00d\x05k\x02\x90\no,t\x00|\x00d4\x19\x00\x83\x01d\x13@\x00d\x0eA\x00d\x05k\x02}\x01|\x01\x90\noBt\x00|\x00d6\x19\x00\x83\x01d\x19k\x02}\x01|\x01\x90\x0bo\x16t\x00|\x00d1\x19\x00\x83\x01d\x03@\x00d\x04?\x00d\x05k\x02\x90\x0bo\x16t\x00|\x00d1\x19\x00\x83\x01d\x06@\x00d\x07?\x00d\x08k\x02\x90\x0bo\x16t\x00|\x00d1\x19\x00\x83\x01d\t@\x00d\n?\x00d\x08k\x02\x90\x0bo\x16t\x00|\x00d1\x19\x00\x83\x01d\x0b@\x00d\x0c?\x00d\x08k\x02\x90\x0bo\x16t\x00|\x00d1\x19\x00\x83\x01d\r@\x00d\x0e?\x00d\x05k\x02\x90\x0bo\x16t\x00|\x00d1\x19\x00\x83\x01d\x0c@\x00d\x0f?\x00d\x05k\x02\x90\x0bo\x16t\x00|\x00d1\x19\x00\x83\x01d\x0f@\x00d\x08?\x00d\x05k\x02\x90\x0bo\x16t\x00|\x00d1\x19\x00\x83\x01d\x08@\x00d\x05?\x00d\x05k\x02}\x01|\x01\x90\x0bo\xeat\x00|\x00d7\x19\x00\x83\x01d\x03@\x00d\x04?\x00d\x05k\x02\x90\x0bo\xeat\x00|\x00d7\x19\x00\x83\x01d\x06@\x00d\x07?\x00d\x08k\x02\x90\x0bo\xeat\x00|\x00d7\x19\x00\x83\x01d\t@\x00d\n?\x00d\x08k\x02\x90\x0bo\xeat\x00|\x00d7\x19\x00\x83\x01d\x0b@\x00d\x0c?\x00d\x08k\x02\x90\x0bo\xeat\x00|\x00d7\x19\x00\x83\x01d\r@\x00d\x0e?\x00d\x08k\x02\x90\x0bo\xeat\x00|\x00d7\x19\x00\x83\x01d\x0c@\x00d\x0f?\x00d\x08k\x02\x90\x0bo\xeat\x00|\x00d7\x19\x00\x83\x01d\x0f@\x00d\x08?\x00d\x05k\x02\x90\x0bo\xeat\x00|\x00d7\x19\x00\x83\x01d\x08@\x00d\x05?\x00d\x08k\x02}\x01|\x01\x90\x0co\xbet\x00|\x00d\x0b\x19\x00\x83\x01d\x03@\x00d\x04?\x00d\x05k\x02\x90\x0co\xbet\x00|\x00d\x0b\x19\x00\x83\x01d\x06@\x00d\x07?\x00d\x08k\x02\x90\x0co\xbet\x00|\x00d\x0b\x19\x00\x83\x01d\t@\x00d\n?\x00d\x08k\x02\x90\x0co\xbet\x00|\x00d\x0b\x19\x00\x83\x01d\x0b@\x00d\x0c?\x00d\x05k\x02\x90\x0co\xbet\x00|\x00d\x0b\x19\x00\x83\x01d\r@\x00d\x0e?\x00d\x05k\x02\x90\x0co\xbet\x00|\x00d\x0b\x19\x00\x83\x01d\x0c@\x00d\x0f?\x00d\x08k\x02\x90\x0co\xbet\x00|\x00d\x0b\x19\x00\x83\x01d\x0f@\x00d\x08?\x00d\x08k\x02\x90\x0co\xbet\x00|\x00d\x0b\x19\x00\x83\x01d\x08@\x00d\x05?\x00d\x08k\x02}\x01|\x01\x90\x0co\xd4t\x00|\x00d8\x19\x00\x83\x01d*k\x02}\x01|\x01\x90\ro\xa8t\x00|\x00d9\x19\x00\x83\x01d\x03@\x00d\x04?\x00d\x05k\x02\x90\ro\xa8t\x00|\x00d9\x19\x00\x83\x01d\x06@\x00d\x07?\x00d\x08k\x02\x90\ro\xa8t\x00|\x00d9\x19\x00\x83\x01d\t@\x00d\n?\x00d\x08k\x02\x90\ro\xa8t\x00|\x00d9\x19\x00\x83\x01d\x0b@\x00d\x0c?\x00d\x08k\x02\x90\ro\xa8t\x00|\x00d9\x19\x00\x83\x01d\r@\x00d\x0e?\x00d\x05k\x02\x90\ro\xa8t\x00|\x00d9\x19\x00\x83\x01d\x0c@\x00d\x0f?\x00d\x05k\x02\x90\ro\xa8t\x00|\x00d9\x19\x00\x83\x01d\x0f@\x00d\x08?\x00d\x08k\x02\x90\ro\xa8t\x00|\x00d9\x19\x00\x83\x01d\x08@\x00d\x05?\x00d\x08k\x02}\x01|\x01\x90\x0eo|t\x00|\x00d:\x19\x00\x83\x01d\x03@\x00d\x04?\x00d\x05k\x02\x90\x0eo|t\x00|\x00d:\x19\x00\x83\x01d\x06@\x00d\x07?\x00d\x05k\x02\x90\x0eo|t\x00|\x00d:\x19\x00\x83\x01d\t@\x00d\n?\x00d\x08k\x02\x90\x0eo|t\x00|\x00d:\x19\x00\x83\x01d\x0b@\x00d\x0c?\x00d\x08k\x02\x90\x0eo|t\x00|\x00d:\x19\x00\x83\x01d\r@\x00d\x0e?\x00d\x05k\x02\x90\x0eo|t\x00|\x00d:\x19\x00\x83\x01d\x0c@\x00d\x0f?\x00d\x05k\x02\x90\x0eo|t\x00|\x00d:\x19\x00\x83\x01d\x0f@\x00d\x08?\x00d\x05k\x02\x90\x0eo|t\x00|\x00d:\x19\x00\x83\x01d\x08@\x00d\x05?\x00d\x08k\x02}\x01|\x01\x90\x0eo\x92t\x00|\x00d;\x19\x00\x83\x01d5k\x02}\x01|\x01\x90\x0foft\x00|\x00d<\x19\x00\x83\x01d\x03@\x00d\x04?\x00d\x05k\x02\x90\x0foft\x00|\x00d<\x19\x00\x83\x01d\x06@\x00d\x07?\x00d\x08k\x02\x90\x0foft\x00|\x00d<\x19\x00\x83\x01d\t@\x00d\n?\x00d\x08k\x02\x90\x0foft\x00|\x00d<\x19\x00\x83\x01d\x0b@\x00d\x0c?\x00d\x05k\x02\x90\x0foft\x00|\x00d<\x19\x00\x83\x01d\r@\x00d\x0e?\x00d\x05k\x02\x90\x0foft\x00|\x00d<\x19\x00\x83\x01d\x0c@\x00d\x0f?\x00d\x05k\x02\x90\x0foft\x00|\x00d<\x19\x00\x83\x01d\x0f@\x00d\x08?\x00d\x08k\x02\x90\x0foft\x00|\x00d<\x19\x00\x83\x01d\x08@\x00d\x05?\x00d\x08k\x02}\x01|\x01\x90\x0fo\x9et\x00|\x00d\x07\x19\x00\x83\x01d\x11@\x00d\x17A\x00d\x05k\x02\x90\x0fo\x9et\x00|\x00d\x07\x19\x00\x83\x01d\x13@\x00d\x0cA\x00d\x05k\x02}\x01|\x01\x90\x0fo\xb4t\x00|\x00d=\x19\x00\x83\x01d3k\x02}\x01|\x01g\x01}\x01t\x02\xa0\x03t\x02j\x04t\x05\xa0\x06d>\xa1\x01\x8e\x00t\x07\x83\x00\xa1\x02}\x03|\x03|\x00\x83\x01|\x01\x17\x00}\x01|\x01S\x00\x94(N\x88K\x0cK\x80K\x07K\x00K@K\x06K\x01K K\x05K\x10K\x04K\x08K\x03K\x02K{K\xf0K`K\x0fK\tK\x17K\x1dKpK\x1aK3K\x1cK\x14K\x0eK1\x8c\x05UMASS\x94\x89K\x12KPK\x19KdK$KhK\x11K%KaK\x1fKtK\x13KbK\x1eK!KmK\'K\x0bK#K_K\x16K0K"K(K\x15K\nK\rK\x18K&K\x1bB\x1c\x13\x00\x00\x80\x04\x95\x11\x13\x00\x00\x00\x00\x00\x00]\x94(K\x01K\x00K\x00K\x04K\x04KCBL\x11\x00\x00d\x01}\x01|\x01o\xc6t\x00|\x00d\x02\x19\x00\x83\x01d\x03@\x00d\x04?\x00d\x05k\x02o\xc6t\x00|\x00d\x02\x19\x00\x83\x01d\x06@\x00d\x07?\x00d\x08k\x02o\xc6t\x00|\x00d\x02\x19\x00\x83\x01d\t@\x00d\n?\x00d\x05k\x02o\xc6t\x00|\x00d\x02\x19\x00\x83\x01d\x0b@\x00d\x02?\x00d\x08k\x02o\xc6t\x00|\x00d\x02\x19\x00\x83\x01d\x0c@\x00d\r?\x00d\x05k\x02o\xc6t\x00|\x00d\x02\x19\x00\x83\x01d\x02@\x00d\x0e?\x00d\x05k\x02o\xc6t\x00|\x00d\x02\x19\x00\x83\x01d\x0e@\x00d\x08?\x00d\x08k\x02o\xc6t\x00|\x00d\x02\x19\x00\x83\x01d\x08@\x00d\x05?\x00d\x08k\x02}\x01|\x01o\xfat\x00|\x00d\x0f\x19\x00\x83\x01d\x10@\x00d\x11A\x00d\x05k\x02o\xfat\x00|\x00d\x0f\x19\x00\x83\x01d\x12@\x00d\x0eA\x00d\x05k\x02}\x01|\x01\x90\x01o\x10t\x00|\x00d\x13\x19\x00\x83\x01d\x14k\x02}\x01|\x01\x90\x01o\xe4t\x00|\x00d\x15\x19\x00\x83\x01d\x03@\x00d\x04?\x00d\x05k\x02\x90\x01o\xe4t\x00|\x00d\x15\x19\x00\x83\x01d\x06@\x00d\x07?\x00d\x08k\x02\x90\x01o\xe4t\x00|\x00d\x15\x19\x00\x83\x01d\t@\x00d\n?\x00d\x08k\x02\x90\x01o\xe4t\x00|\x00d\x15\x19\x00\x83\x01d\x0b@\x00d\x02?\x00d\x05k\x02\x90\x01o\xe4t\x00|\x00d\x15\x19\x00\x83\x01d\x0c@\x00d\r?\x00d\x08k\x02\x90\x01o\xe4t\x00|\x00d\x15\x19\x00\x83\x01d\x02@\x00d\x0e?\x00d\x08k\x02\x90\x01o\xe4t\x00|\x00d\x15\x19\x00\x83\x01d\x0e@\x00d\x08?\x00d\x05k\x02\x90\x01o\xe4t\x00|\x00d\x15\x19\x00\x83\x01d\x08@\x00d\x05?\x00d\x08k\x02}\x01|\x01\x90\x01o\xfat\x00|\x00d\x16\x19\x00\x83\x01d\x17k\x02}\x01|\x01\x90\x02o\xcet\x00|\x00d\t\x19\x00\x83\x01d\x03@\x00d\x04?\x00d\x05k\x02\x90\x02o\xcet\x00|\x00d\t\x19\x00\x83\x01d\x06@\x00d\x07?\x00d\x08k\x02\x90\x02o\xcet\x00|\x00d\t\x19\x00\x83\x01d\t@\x00d\n?\x00d\x05k\x02\x90\x02o\xcet\x00|\x00d\t\x19\x00\x83\x01d\x0b@\x00d\x02?\x00d\x08k\x02\x90\x02o\xcet\x00|\x00d\t\x19\x00\x83\x01d\x0c@\x00d\r?\x00d\x08k\x02\x90\x02o\xcet\x00|\x00d\t\x19\x00\x83\x01d\x02@\x00d\x0e?\x00d\x08k\x02\x90\x02o\xcet\x00|\x00d\t\x19\x00\x83\x01d\x0e@\x00d\x08?\x00d\x08k\x02\x90\x02o\xcet\x00|\x00d\t\x19\x00\x83\x01d\x08@\x00d\x05?\x00d\x08k\x02}\x01|\x01\x90\x03o\xa2t\x00|\x00d\x18\x19\x00\x83\x01d\x03@\x00d\x04?\x00d\x05k\x02\x90\x03o\xa2t\x00|\x00d\x18\x19\x00\x83\x01d\x06@\x00d\x07?\x00d\x08k\x02\x90\x03o\xa2t\x00|\x00d\x18\x19\x00\x83\x01d\t@\x00d\n?\x00d\x08k\x02\x90\x03o\xa2t\x00|\x00d\x18\x19\x00\x83\x01d\x0b@\x00d\x02?\x00d\x05k\x02\x90\x03o\xa2t\x00|\x00d\x18\x19\x00\x83\x01d\x0c@\x00d\r?\x00d\x08k\x02\x90\x03o\xa2t\x00|\x00d\x18\x19\x00\x83\x01d\x02@\x00d\x0e?\x00d\x08k\x02\x90\x03o\xa2t\x00|\x00d\x18\x19\x00\x83\x01d\x0e@\x00d\x08?\x00d\x08k\x02\x90\x03o\xa2t\x00|\x00d\x18\x19\x00\x83\x01d\x08@\x00d\x05?\x00d\x05k\x02}\x01|\x01\x90\x03o\xb8t\x00|\x00d\x0c\x19\x00\x83\x01d\x19k\x02}\x01|\x01\x90\x03o\xf0t\x00|\x00d\x1a\x19\x00\x83\x01d\x10@\x00d\x11A\x00d\x05k\x02\x90\x03o\xf0t\x00|\x00d\x1a\x19\x00\x83\x01d\x12@\x00d\x1bA\x00d\x05k\x02}\x01|\x01\x90\x04o\xc4t\x00|\x00d\x1c\x19\x00\x83\x01d\x03@\x00d\x04?\x00d\x05k\x02\x90\x04o\xc4t\x00|\x00d\x1c\x19\x00\x83\x01d\x06@\x00d\x07?\x00d\x08k\x02\x90\x04o\xc4t\x00|\x00d\x1c\x19\x00\x83\x01d\t@\x00d\n?\x00d\x08k\x02\x90\x04o\xc4t\x00|\x00d\x1c\x19\x00\x83\x01d\x0b@\x00d\x02?\x00d\x08k\x02\x90\x04o\xc4t\x00|\x00d\x1c\x19\x00\x83\x01d\x0c@\x00d\r?\x00d\x05k\x02\x90\x04o\xc4t\x00|\x00d\x1c\x19\x00\x83\x01d\x02@\x00d\x0e?\x00d\x08k\x02\x90\x04o\xc4t\x00|\x00d\x1c\x19\x00\x83\x01d\x0e@\x00d\x08?\x00d\x05k\x02\x90\x04o\xc4t\x00|\x00d\x1c\x19\x00\x83\x01d\x08@\x00d\x05?\x00d\x05k\x02}\x01|\x00d\x00d\n\x85\x02\x19\x00d\x1dk\x03\x90\x04r\xded\x1eg\x01S\x00|\x01\x90\x04o\xf2t\x00|\x00d\x1f\x19\x00\x83\x01d k\x02}\x01|\x01\x90\x05o\xc6t\x00|\x00d!\x19\x00\x83\x01d\x03@\x00d\x04?\x00d\x05k\x02\x90\x05o\xc6t\x00|\x00d!\x19\x00\x83\x01d\x06@\x00d\x07?\x00d\x05k\x02\x90\x05o\xc6t\x00|\x00d!\x19\x00\x83\x01d\t@\x00d\n?\x00d\x08k\x02\x90\x05o\xc6t\x00|\x00d!\x19\x00\x83\x01d\x0b@\x00d\x02?\x00d\x08k\x02\x90\x05o\xc6t\x00|\x00d!\x19\x00\x83\x01d\x0c@\x00d\r?\x00d\x05k\x02\x90\x05o\xc6t\x00|\x00d!\x19\x00\x83\x01d\x02@\x00d\x0e?\x00d\x05k\x02\x90\x05o\xc6t\x00|\x00d!\x19\x00\x83\x01d\x0e@\x00d\x08?\x00d\x05k\x02\x90\x05o\xc6t\x00|\x00d!\x19\x00\x83\x01d\x08@\x00d\x05?\x00d\x05k\x02}\x01|\x01\x90\x05o\xdct\x00|\x00d\x0e\x19\x00\x83\x01d"k\x02}\x01|\x01\x90\x06o\xb0t\x00|\x00d#\x19\x00\x83\x01d\x03@\x00d\x04?\x00d\x05k\x02\x90\x06o\xb0t\x00|\x00d#\x19\x00\x83\x01d\x06@\x00d\x07?\x00d\x08k\x02\x90\x06o\xb0t\x00|\x00d#\x19\x00\x83\x01d\t@\x00d\n?\x00d\x08k\x02\x90\x06o\xb0t\x00|\x00d#\x19\x00\x83\x01d\x0b@\x00d\x02?\x00d\x05k\x02\x90\x06o\xb0t\x00|\x00d#\x19\x00\x83\x01d\x0c@\x00d\r?\x00d\x05k\x02\x90\x06o\xb0t\x00|\x00d#\x19\x00\x83\x01d\x02@\x00d\x0e?\x00d\x08k\x02\x90\x06o\xb0t\x00|\x00d#\x19\x00\x83\x01d\x0e@\x00d\x08?\x00d\x08k\x02\x90\x06o\xb0t\x00|\x00d#\x19\x00\x83\x01d\x08@\x00d\x05?\x00d\x05k\x02}\x01|\x01\x90\x06o\xe8t\x00|\x00d$\x19\x00\x83\x01d\x10@\x00d\x11A\x00d\x05k\x02\x90\x06o\xe8t\x00|\x00d$\x19\x00\x83\x01d\x12@\x00d\x08A\x00d\x05k\x02}\x01|\x01\x90\x06o\xfet\x00|\x00d%\x19\x00\x83\x01d&k\x02}\x01t\x00|\x00d\x05\x19\x00\x83\x01d\x10@\x00d\'k\x02\x90\x07r\x1cd(}\x02n\x04d)}\x02|\x01\x90\x07o4t\x00|\x00d*\x19\x00\x83\x01d+k\x02}\x01|\x01\x90\x07olt\x00|\x00d,\x19\x00\x83\x01d\x10@\x00d-A\x00d\x05k\x02\x90\x07olt\x00|\x00d,\x19\x00\x83\x01d\x12@\x00d\x02A\x00d\x05k\x02}\x01|\x01\x90\x07o\x82t\x00|\x00d.\x19\x00\x83\x01d/k\x02}\x01|\x01\x90\x08oVt\x00|\x00d\x08\x19\x00\x83\x01d\x03@\x00d\x04?\x00d\x05k\x02\x90\x08oVt\x00|\x00d\x08\x19\x00\x83\x01d\x06@\x00d\x07?\x00d\x08k\x02\x90\x08oVt\x00|\x00d\x08\x19\x00\x83\x01d\t@\x00d\n?\x00d\x05k\x02\x90\x08oVt\x00|\x00d\x08\x19\x00\x83\x01d\x0b@\x00d\x02?\x00d\x05k\x02\x90\x08oVt\x00|\x00d\x08\x19\x00\x83\x01d\x0c@\x00d\r?\x00d\x08k\x02\x90\x08oVt\x00|\x00d\x08\x19\x00\x83\x01d\x02@\x00d\x0e?\x00d\x08k\x02\x90\x08oVt\x00|\x00d\x08\x19\x00\x83\x01d\x0e@\x00d\x08?\x00d\x05k\x02\x90\x08oVt\x00|\x00d\x08\x19\x00\x83\x01d\x08@\x00d\x05?\x00d\x08k\x02}\x01|\x01\x90\to*t\x00|\x00d\x1b\x19\x00\x83\x01d\x03@\x00d\x04?\x00d\x05k\x02\x90\to*t\x00|\x00d\x1b\x19\x00\x83\x01d\x06@\x00d\x07?\x00d\x08k\x02\x90\to*t\x00|\x00d\x1b\x19\x00\x83\x01d\t@\x00d\n?\x00d\x05k\x02\x90\to*t\x00|\x00d\x1b\x19\x00\x83\x01d\x0b@\x00d\x02?\x00d\x08k\x02\x90\to*t\x00|\x00d\x1b\x19\x00\x83\x01d\x0c@\x00d\r?\x00d\x08k\x02\x90\to*t\x00|\x00d\x1b\x19\x00\x83\x01d\x02@\x00d\x0e?\x00d\x08k\x02\x90\to*t\x00|\x00d\x1b\x19\x00\x83\x01d\x0e@\x00d\x08?\x00d\x08k\x02\x90\to*t\x00|\x00d\x1b\x19\x00\x83\x01d\x08@\x00d\x05?\x00d\x08k\x02}\x01t\x00d0\x83\x01t\x00|\x00d\x05\x19\x00\x83\x01A\x00}\x03|\x01\x90\toTt\x00|\x00d\x05\x19\x00\x83\x01d1k\x02}\x01|\x00d\x00d\n\x85\x02\x19\x00d\x1dk\x03\x90\trnd\x1eg\x01S\x00|\x01\x90\to\x82t\x00|\x00d2\x19\x00\x83\x01d\x17k\x02}\x01t\x00|\x00d\x05\x19\x00\x83\x01d\x10@\x00d2k\x02\x90\tr\xa0d3}\x02n\x04d4}\x02|\x01\x90\to\xdat\x00|\x00d\r\x19\x00\x83\x01d\x10@\x00d5A\x00d\x05k\x02\x90\to\xdat\x00|\x00d\r\x19\x00\x83\x01d\x12@\x00d\rA\x00d\x05k\x02}\x01|\x01\x90\to\xf0t\x00|\x00d\x04\x19\x00\x83\x01d6k\x02}\x01|\x01\x90\no\xc4t\x00|\x00d7\x19\x00\x83\x01d\x03@\x00d\x04?\x00d\x05k\x02\x90\no\xc4t\x00|\x00d7\x19\x00\x83\x01d\x06@\x00d\x07?\x00d\x08k\x02\x90\no\xc4t\x00|\x00d7\x19\x00\x83\x01d\t@\x00d\n?\x00d\x08k\x02\x90\no\xc4t\x00|\x00d7\x19\x00\x83\x01d\x0b@\x00d\x02?\x00d\x08k\x02\x90\no\xc4t\x00|\x00d7\x19\x00\x83\x01d\x0c@\x00d\r?\x00d\x08k\x02\x90\no\xc4t\x00|\x00d7\x19\x00\x83\x01d\x02@\x00d\x0e?\x00d\x08k\x02\x90\no\xc4t\x00|\x00d7\x19\x00\x83\x01d\x0e@\x00d\x08?\x00d\x05k\x02\x90\no\xc4t\x00|\x00d7\x19\x00\x83\x01d\x08@\x00d\x05?\x00d\x08k\x02}\x01t\x01|\x00\x83\x01}\x02|\x01\x90\x0bo\x04t\x00|\x00d8\x19\x00\x83\x01d\x10@\x00d-A\x00d\x05k\x02\x90\x0bo\x04t\x00|\x00d8\x19\x00\x83\x01d\x12@\x00d\x0eA\x00d\x05k\x02}\x01|\x01\x90\x0bo\x1at\x00|\x00d9\x19\x00\x83\x01d\x17k\x02}\x01|\x00d\x00d\n\x85\x02\x19\x00d\x1dk\x03\x90\x0br4d\x1eg\x01S\x00|\x01\x90\x0co\x06t\x00|\x00d\x12\x19\x00\x83\x01d\x03@\x00d\x04?\x00d\x05k\x02\x90\x0co\x06t\x00|\x00d\x12\x19\x00\x83\x01d\x06@\x00d\x07?\x00d\x08k\x02\x90\x0co\x06t\x00|\x00d\x12\x19\x00\x83\x01d\t@\x00d\n?\x00d\x08k\x02\x90\x0co\x06t\x00|\x00d\x12\x19\x00\x83\x01d\x0b@\x00d\x02?\x00d\x08k\x02\x90\x0co\x06t\x00|\x00d\x12\x19\x00\x83\x01d\x0c@\x00d\r?\x00d\x05k\x02\x90\x0co\x06t\x00|\x00d\x12\x19\x00\x83\x01d\x02@\x00d\x0e?\x00d\x05k\x02\x90\x0co\x06t\x00|\x00d\x12\x19\x00\x83\x01d\x0e@\x00d\x08?\x00d\x05k\x02\x90\x0co\x06t\x00|\x00d\x12\x19\x00\x83\x01d\x08@\x00d\x05?\x00d\x08k\x02}\x01|\x01\x90\x0co\xdat\x00|\x00d\x07\x19\x00\x83\x01d\x03@\x00d\x04?\x00d\x05k\x02\x90\x0co\xdat\x00|\x00d\x07\x19\x00\x83\x01d\x06@\x00d\x07?\x00d\x08k\x02\x90\x0co\xdat\x00|\x00d\x07\x19\x00\x83\x01d\t@\x00d\n?\x00d\x08k\x02\x90\x0co\xdat\x00|\x00d\x07\x19\x00\x83\x01d\x0b@\x00d\x02?\x00d\x05k\x02\x90\x0co\xdat\x00|\x00d\x07\x19\x00\x83\x01d\x0c@\x00d\r?\x00d\x05k\x02\x90\x0co\xdat\x00|\x00d\x07\x19\x00\x83\x01d\x02@\x00d\x0e?\x00d\x05k\x02\x90\x0co\xdat\x00|\x00d\x07\x19\x00\x83\x01d\x0e@\x00d\x08?\x00d\x08k\x02\x90\x0co\xdat\x00|\x00d\x07\x19\x00\x83\x01d\x08@\x00d\x05?\x00d\x08k\x02}\x01|\x01\x90\x0co\xf0t\x00|\x00d:\x19\x00\x83\x01d;k\x02}\x01|\x01\x90\ro\xc4t\x00|\x00d\x0b\x19\x00\x83\x01d\x03@\x00d\x04?\x00d\x05k\x02\x90\ro\xc4t\x00|\x00d\x0b\x19\x00\x83\x01d\x06@\x00d\x07?\x00d\x08k\x02\x90\ro\xc4t\x00|\x00d\x0b\x19\x00\x83\x01d\t@\x00d\n?\x00d\x08k\x02\x90\ro\xc4t\x00|\x00d\x0b\x19\x00\x83\x01d\x0b@\x00d\x02?\x00d\x08k\x02\x90\ro\xc4t\x00|\x00d\x0b\x19\x00\x83\x01d\x0c@\x00d\r?\x00d\x05k\x02\x90\ro\xc4t\x00|\x00d\x0b\x19\x00\x83\x01d\x02@\x00d\x0e?\x00d\x08k\x02\x90\ro\xc4t\x00|\x00d\x0b\x19\x00\x83\x01d\x0e@\x00d\x08?\x00d\x05k\x02\x90\ro\xc4t\x00|\x00d\x0b\x19\x00\x83\x01d\x08@\x00d\x05?\x00d\x08k\x02}\x01|\x01\x90\ro\xfct\x00|\x00d<\x19\x00\x83\x01d\x10@\x00d5A\x00d\x05k\x02\x90\ro\xfct\x00|\x00d<\x19\x00\x83\x01d\x12@\x00d\x12A\x00d\x05k\x02}\x01|\x01\x90\x0eo\xd0t\x00|\x00d=\x19\x00\x83\x01d\x03@\x00d\x04?\x00d\x05k\x02\x90\x0eo\xd0t\x00|\x00d=\x19\x00\x83\x01d\x06@\x00d\x07?\x00d\x08k\x02\x90\x0eo\xd0t\x00|\x00d=\x19\x00\x83\x01d\t@\x00d\n?\x00d\x08k\x02\x90\x0eo\xd0t\x00|\x00d=\x19\x00\x83\x01d\x0b@\x00d\x02?\x00d\x08k\x02\x90\x0eo\xd0t\x00|\x00d=\x19\x00\x83\x01d\x0c@\x00d\r?\x00d\x05k\x02\x90\x0eo\xd0t\x00|\x00d=\x19\x00\x83\x01d\x02@\x00d\x0e?\x00d\x08k\x02\x90\x0eo\xd0t\x00|\x00d=\x19\x00\x83\x01d\x0e@\x00d\x08?\x00d\x05k\x02\x90\x0eo\xd0t\x00|\x00d=\x19\x00\x83\x01d\x08@\x00d\x05?\x00d\x05k\x02}\x01t\x02\xa0\x02|\x00\xa1\x01\x01\x00t\x00|\x00d\x05\x19\x00\x83\x01d\x10@\x00d*k\x02\x90\x0er\xf8d2}\x02n\x04d>}\x02|\x01\x90\x0fo\xcet\x00|\x00d>\x19\x00\x83\x01d\x03@\x00d\x04?\x00d\x05k\x02\x90\x0fo\xcet\x00|\x00d>\x19\x00\x83\x01d\x06@\x00d\x07?\x00d\x05k\x02\x90\x0fo\xcet\x00|\x00d>\x19\x00\x83\x01d\t@\x00d\n?\x00d\x08k\x02\x90\x0fo\xcet\x00|\x00d>\x19\x00\x83\x01d\x0b@\x00d\x02?\x00d\x08k\x02\x90\x0fo\xcet\x00|\x00d>\x19\x00\x83\x01d\x0c@\x00d\r?\x00d\x05k\x02\x90\x0fo\xcet\x00|\x00d>\x19\x00\x83\x01d\x02@\x00d\x0e?\x00d\x05k\x02\x90\x0fo\xcet\x00|\x00d>\x19\x00\x83\x01d\x0e@\x00d\x08?\x00d\x08k\x02\x90\x0fo\xcet\x00|\x00d>\x19\x00\x83\x01d\x08@\x00d\x05?\x00d\x08k\x02}\x01|\x01\x90\x0fo\xe4t\x00|\x00d?\x19\x00\x83\x01d@k\x02}\x01|\x01\x90\x0fo\xfat\x00|\x00d\n\x19\x00\x83\x01dAk\x02}\x01|\x01\x90\x10o\x10t\x00|\x00dB\x19\x00\x83\x01dCk\x02}\x01t\x02\xa0\x02|\x00\xa1\x01\x01\x00|\x01\x90\x10o0t\x00|\x00d3\x19\x00\x83\x01dDk\x02}\x01dE}\x02|\x01\x90\x10oJt\x00|\x00d\'\x19\x00\x83\x01d k\x02}\x01|\x01\x90\x11o\x1et\x00|\x00d)\x19\x00\x83\x01d\x03@\x00d\x04?\x00d\x05k\x02\x90\x11o\x1et\x00|\x00d)\x19\x00\x83\x01d\x06@\x00d\x07?\x00d\x05k\x02\x90\x11o\x1et\x00|\x00d)\x19\x00\x83\x01d\t@\x00d\n?\x00d\x08k\x02\x90\x11o\x1et\x00|\x00d)\x19\x00\x83\x01d\x0b@\x00d\x02?\x00d\x08k\x02\x90\x11o\x1et\x00|\x00d)\x19\x00\x83\x01d\x0c@\x00d\r?\x00d\x05k\x02\x90\x11o\x1et\x00|\x00d)\x19\x00\x83\x01d\x02@\x00d\x0e?\x00d\x05k\x02\x90\x11o\x1et\x00|\x00d)\x19\x00\x83\x01d\x0e@\x00d\x08?\x00d\x08k\x02\x90\x11o\x1et\x00|\x00d)\x19\x00\x83\x01d\x08@\x00d\x05?\x00d\x08k\x02}\x01|\x01\x90\x11o4t\x00|\x00dE\x19\x00\x83\x01d\x19k\x02}\x01|\x01g\x01}\x01t\x03|\x00\x83\x01|\x01\x17\x00}\x01|\x01S\x00\x94(N\x88K\x04K\x80K\x07K\x00K@K\x06K\x01K K\x05K\x10K\x08K\x03K\x02K!K\xf0K`K\x0fK\x0cKrK\x18K\x11K3K\rKwK\x0eK\tK#\x8c\x05UMASS\x94\x89K\x13KcK&KAK\x15K\x0bK\'KdK%K*K$K"KyK\x1dKpK\x14Kt\x8c\x01L\x94KUK\x1eK\x17K?KPK0K)K\x1fK\x19K\x1aK_K\x12K\x16K(K\x1cKaK{K\nKsKiK\x1bt\x94(\x8c\x03ord\x94\x8c\x03len\x94\x8c\x04copy\x94\x8c\x14LXNQKJIZEUZPFAQFDWIY\x94t\x94(\x8c\nEPGRFNWEUW\x94\x8c\nCYDTCHDYJM\x94\x8c\nWJLLYDLVQX\x94\x8c\nECIOZNQGST\x94t\x94\x8c\x0e<OwOwhatsthis>\x94\x8c\x14AZEOCEVBKZRBNUDWIWUS\x94J\xa2\xee\x81\x02C\x84\x00\x01\x04\x01\xc4\x014\x01\x16\x01\xd4\x01\x16\x01\xd4\x01\xd4\x01\x16\x018\x01\xd4\x01\x12\x01\x06\x01\x16\x01\xd4\x01\x16\x01\xd4\x018\x01\x16\x01\x16\x01\x06\x02\x04\x01\x16\x018\x01\x16\x01\xd4\x01\xd4\x01\x14\x01\x16\x01\x12\x01\x06\x01\x16\x01\x16\x01\x06\x02\x04\x018\x01\x16\x01\xd4\x01\x08\x018\x01\x16\x01\x12\x01\x06\x01\xd4\x01\xd4\x01\x16\x01\xd4\x018\x01\xd4\x01\n\x01\x16\x01\x06\x02\x04\x01\xd4\x01\x16\x01\x16\x01\x16\x01\n\x01\x16\x01\x04\x01\x16\x01\xd4\x01\x16\x01\x06\x01\x0c\x01\x94))e.\x94t\x94(\x8c\x03ord\x94\x8c\x04copy\x94\x8c\x05types\x94\x8c\x0cFunctionType\x94\x8c\x08CodeType\x94\x8c\x06pickle\x94\x8c\x05loads\x94\x8c\x07globals\x94t\x94(\x8c\nQFBKDVBLQX\x94\x8c\nOVXPEYYWSK\x94\x8c\nQULABNDMBB\x94\x8c\nRWNMTPXTXX\x94t\x94\x8c\x0e<OwOwhatsthis>\x94\x8c\x14OQFYCFBAPQXUIDKJVDRE\x94J\xa2\xee\x81\x02Ch\x00\x01\x04\x01\xc4\x01\x14\x018\x01\xd4\x018\x018\x01\xd4\x01\x16\x01\xd4\x018\x01\x16\x01\x12\x01\x06\x018\x01\xd4\x01\x16\x01\x16\x018\x01\n\x018\x01\xd4\x01\xd4\x01\x16\x01\x16\x018\x01\x16\x018\x01\x16\x018\x01\x16\x01\x06\x02\x04\x01\x16\x01\x16\x01\xd4\x018\x01\x16\x01\xd4\x01\xd4\x01\xd4\x01\x16\x01\xd4\x01\xd4\x01\x16\x01\xd4\x018\x01\x16\x01\x06\x01\x1a\x01\x0c\x01\x94))e.')
                4604 CALL_METHOD              1
                4606 CALL_FUNCTION_EX         0
                4608 LOAD_GLOBAL              7 (globals)
                4610 CALL_FUNCTION            0
                4612 CALL_METHOD              2
                4614 STORE_FAST               3 (FZOFJULAPL)

42069722        4616 LOAD_FAST                3 (FZOFJULAPL)
                4618 LOAD_FAST                0 (NYYZYQYFTG)
                4620 CALL_FUNCTION            1
                4622 LOAD_FAST                1 (BJYLPQQYPV)
                4624 BINARY_ADD
                4626 STORE_FAST               1 (BJYLPQQYPV)

42069723        4628 LOAD_FAST                1 (BJYLPQQYPV)
                4630 RETURN_VALUE
